Workbook
Name 송보근: #REF!

Sheet Usage Apr 2026
A1: Please don't change this sheet and data except the column 'Verified' with the color light gold. If necessary, contact Yunseul Lee via Slack 1:1 DM. | J1: ㅇ
A2: You verify the cost of the last month and leave the mark V in the column 'Verified'. If the value in the last month is wrong, give the description to Yunseul Lee
A3: Provider | B3: Entity | C3: Studio | D3: Team | E3: Project | F3: Team code | G3: Project code | H3: Teams Room Pro | I3: Owner | J3: Cost Reviewer | K3: verified | L3: May 2025(KRW) | M3: June 2025(KRW) | N3: July 2025(KRW) | O3: Aug 2025(KRW) | P3: Sep 2025(KRW) | Q3: Oct 2025(KRW) | R3: Nov 2025(KRW) | S3: Dec 2025(KRW) | T3: Jan 2026(KRW) | U3: Feb 2026(KRW) | V3: Mar 2026(KRW) | W3: Apr 2027(KRW) | X3: Apr 2026 (USD or KRW) | Y3: Diff (KRW) (this month - last month) | Z3: Diff rate | AA3: Entity Code
A4: =VLOOKUP($H4,Akamai!$A:$H,2,0) -> Akamai | B4: =VLOOKUP($H4,Akamai!$A:$H,3,0) -> KRAFTON HQ | C4: =VLOOKUP($H4,Akamai!$A:$H,4,0) -> KRAFTON HQ | D4: =VLOOKUP($H4,Akamai!$A:$H,5,0) -> Publishing Tech PM Part | E4: =VLOOKUP($H4,Akamai!$A:$H,6,0) -> Dark and Darker_Mobile | F4: =VLOOKUP(표9[[#This Row],[Team]],표1[[내역]:[코스트 센터]],2,0) -> 101269 | G4: =VLOOKUP(표9[[#This Row],[Project]],표2[],2,0) -> P100030073 | H4: Dark&DarkerMoblie | I4: =VLOOKUP($H4,Akamai!$A:$H,7,0) -> 김정언 | J4: =VLOOKUP($H4,Akamai!$A:$H,8,0) -> 김정언 | K4: v | L4: 191794 | M4: 12151797 | N4: 1647138 | O4: 998557 | P4: 687485 | Q4: 656031 | R4: 372478 | S4: 371022 | T4: 241926 | U4: 56897 | V4: 49010 | W4: =ROUND(표9[[#This Row],[Apr 2026 (USD or KRW)]],0) -> 0 | Y4: =표9[[#This Row],[Apr 2027(KRW)]]-표9[[#This Row],[Mar 2026(KRW)]] -> -49010 | Z4: =IF(V4=0,"",(W4-V4)/V4) -> -1 | AA4: =VLOOKUP(표9[[#This Row],[Team]],표1[],3,0) -> 1000
A5: =VLOOKUP($H5,Akamai!$A:$H,2,0) -> Akamai | B5: =VLOOKUP($H5,Akamai!$A:$H,3,0) -> KRAFTON HQ | C5: =VLOOKUP($H5,Akamai!$A:$H,4,0) -> KRAFTON HQ | D5: =VLOOKUP($H5,Akamai!$A:$H,5,0) -> IT Dept. | E5: =VLOOKUP($H5,Akamai!$A:$H,6,0) -> OVERHEAD/OTHERS | F5: =VLOOKUP(표9[[#This Row],[Team]],표1[[내역]:[코스트 센터]],2,0) -> 100036 | G5: =VLOOKUP(표9[[#This Row],[Project]],표2[],2,0) -> I100099999 | H5: Global Traffic Management | I5: =VLOOKUP($H5,Akamai!$A:$H,7,0) -> 이윤슬 | J5: =VLOOKUP($H5,Akamai!$A:$H,8,0) -> 이윤슬 | K5: v | L5: 2850000 | M5: 2850000 | N5: 2850000 | O5: 2850000 | P5: 2850000 | Q5: 2850000 | R5: 2850000 | S5: 2850000 | T5: 2850000 | U5: 2850000 | V5: 2935500 | W5: =ROUND(표9[[#This Row],[Apr 2026 (USD or KRW)]],0) -> 0 | Y5: =표9[[#This Row],[Apr 2027(KRW)]]-표9[[#This Row],[Mar 2026(KRW)]] -> -2935500 | Z5: =IF(V5=0,"",(W5-V5)/V5) -> -1 | AA5: =VLOOKUP(표9[[#This Row],[Team]],표1[],3,0) -> 1000
A6: =VLOOKUP($H6,Akamai!$A:$H,2,0) -> Akamai | B6: =VLOOKUP($H6,Akamai!$A:$H,3,0) -> KRAFTON HQ | C6: =VLOOKUP($H6,Akamai!$A:$H,4,0) -> KRAFTON HQ | D6: =VLOOKUP($H6,Akamai!$A:$H,5,0) -> KOS Engineering Dept. | E6: =VLOOKUP($H6,Akamai!$A:$H,6,0) -> GPP | F6: =VLOOKUP(표9[[#This Row],[Team]],표1[[내역]:[코스트 센터]],2,0) -> 100025 | G6: =VLOOKUP(표9[[#This Row],[Project]],표2[],2,0) -> I100090813 | H6: GPP Dept | I6: =VLOOKUP($H6,Akamai!$A:$H,7,0) -> 이의석 | J6: =VLOOKUP($H6,Akamai!$A:$H,8,0) -> 이의석 | K6: v | L6: 16500000 | M6: 16500000 | N6: 17302333 | O6: 16500000 | P6: 16500000 | Q6: 16500000 | R6: 16500000 | S6: 19189620 | T6: 16500000 | U6: 16500000 | V6: 16995000 | W6: =ROUND(표9[[#This Row],[Apr 2026 (USD or KRW)]],0) -> 0 | Y6: =표9[[#This Row],[Apr 2027(KRW)]]-표9[[#This Row],[Mar 2026(KRW)]] -> -16995000 | Z6: =IF(V6=0,"",(W6-V6)/V6) -> -1 | AA6: =VLOOKUP(표9[[#This Row],[Team]],표1[],3,0) -> 1000
A7: =VLOOKUP($H7,Akamai!$A:$H,2,0) -> Akamai | B7: =VLOOKUP($H7,Akamai!$A:$H,3,0) -> KRAFTON HQ | C7: =VLOOKUP($H7,Akamai!$A:$H,4,0) -> KRAFTON HQ | D7: =VLOOKUP($H7,Akamai!$A:$H,5,0) -> IT Dept. | E7: =VLOOKUP($H7,Akamai!$A:$H,6,0) -> OVERHEAD/OTHERS | F7: =VLOOKUP(표9[[#This Row],[Team]],표1[[내역]:[코스트 센터]],2,0) -> 100036 | G7: =VLOOKUP(표9[[#This Row],[Project]],표2[],2,0) -> I100099999 | H7: IT Dept | I7: =VLOOKUP($H7,Akamai!$A:$H,7,0) -> 백용원 | J7: =VLOOKUP($H7,Akamai!$A:$H,8,0) -> 백용원 | K7: v | L7: 6736 | M7: 6295 | N7: 18686 | O7: 0 | P7: 0 | Q7: 0 | R7: 0 | S7: 22440 | T7: 0 | U7: 0 | V7: 0 | W7: =ROUND(표9[[#This Row],[Apr 2026 (USD or KRW)]],0) -> 0 | Y7: =표9[[#This Row],[Apr 2027(KRW)]]-표9[[#This Row],[Mar 2026(KRW)]] -> 0 | Z7: =IF(V7=0,"",(W7-V7)/V7) | AA7: =VLOOKUP(표9[[#This Row],[Team]],표1[],3,0) -> 1000
A8: =VLOOKUP($H8,Akamai!$A:$H,2,0) -> Akamai | B8: =VLOOKUP($H8,Akamai!$A:$H,3,0) -> KRAFTON HQ | C8: =VLOOKUP($H8,Akamai!$A:$H,4,0) -> PUBG NewState | D8: =VLOOKUP($H8,Akamai!$A:$H,5,0) -> [N/A]New State Dev Div. | E8: =VLOOKUP($H8,Akamai!$A:$H,6,0) -> PUBG:NEW STATE | F8: =VLOOKUP(표9[[#This Row],[Team]],표1[[내역]:[코스트 센터]],2,0) -> 100368 | G8: =VLOOKUP(표9[[#This Row],[Project]],표2[],2,0) -> P100030014 | H8: NewStateMobile | I8: 김태완 | J8: =VLOOKUP($H8,Akamai!$A:$H,8,0) -> 김태완 | K8: v | L8: 6202222 | M8: 6160035 | N8: 6218633 | O8: 6584628 | P8: 5198312 | Q8: 6649060 | R8: 6806509 | S8: 5804815 | T8: 6546446 | U8: 5466648 | V8: 5759285 | W8: =ROUND(표9[[#This Row],[Apr 2026 (USD or KRW)]],0) -> 0 | Y8: =표9[[#This Row],[Apr 2027(KRW)]]-표9[[#This Row],[Mar 2026(KRW)]] -> -5759285 | Z8: =IF(V8=0,"",(W8-V8)/V8) -> -1 | AA8: =VLOOKUP(표9[[#This Row],[Team]],표1[],3,0) -> 1000
A9: =VLOOKUP($H9,Akamai!$A:$H,2,0) -> Akamai | B9: =VLOOKUP($H9,Akamai!$A:$H,3,0) -> KRAFTON HQ | C9: =VLOOKUP($H9,Akamai!$A:$H,4,0) -> KRAFTON HQ | D9: =VLOOKUP($H9,Akamai!$A:$H,5,0) -> Publishing Tech PM Part | E9: =VLOOKUP($H9,Akamai!$A:$H,6,0) -> OVERHEAD/OTHERS | F9: =VLOOKUP(표9[[#This Row],[Team]],표1[[내역]:[코스트 센터]],2,0) -> 101269 | G9: =VLOOKUP(표9[[#This Row],[Project]],표2[],2,0) -> I100099999 | H9: NitroSmash | I9: =VLOOKUP($H9,Akamai!$A:$H,7,0) -> 김정언 | J9: =VLOOKUP($H9,Akamai!$A:$H,8,0) -> 김정언 | K9: v | P9: 160 | Q9: 1 | R9: 1 | S9: 1 | T9: 2 | U9: 0 | V9: 0 | W9: =ROUND(표9[[#This Row],[Apr 2026 (USD or KRW)]],0) -> 0 | Y9: =표9[[#This Row],[Apr 2027(KRW)]]-표9[[#This Row],[Mar 2026(KRW)]] -> 0 | Z9: =IF(V9=0,"",(W9-V9)/V9) | AA9: =VLOOKUP(표9[[#This Row],[Team]],표1[],3,0) -> 1000
A10: =VLOOKUP($H10,Akamai!$A:$H,2,0) -> Akamai | B10: =VLOOKUP($H10,Akamai!$A:$H,3,0) -> KRAFTON HQ | C10: =VLOOKUP($H10,Akamai!$A:$H,4,0) -> KRAFTON HQ | D10: =VLOOKUP($H10,Akamai!$A:$H,5,0) -> IT Dept. | E10: =VLOOKUP($H10,Akamai!$A:$H,6,0) -> OVERHEAD/OTHERS | F10: =VLOOKUP(표9[[#This Row],[Team]],표1[[내역]:[코스트 센터]],2,0) -> 100036 | G10: =VLOOKUP(표9[[#This Row],[Project]],표2[],2,0) -> I100099999 | H10: Protect&Perform SOA with Premium | I10: =VLOOKUP($H10,Akamai!$A:$H,7,0) -> 이윤슬 | J10: =VLOOKUP($H10,Akamai!$A:$H,8,0) -> 이윤슬 | K10: v | L10: 22950000 | M10: 22950000 | N10: 22950000 | O10: 22950000 | P10: 22950000 | Q10: 22950000 | R10: 22950000 | S10: 22950000 | T10: 22950000 | U10: 22950000 | V10: 23638500 | W10: =ROUND(표9[[#This Row],[Apr 2026 (USD or KRW)]],0) -> 0 | Y10: =표9[[#This Row],[Apr 2027(KRW)]]-표9[[#This Row],[Mar 2026(KRW)]] -> -23638500 | Z10: =IF(V10=0,"",(W10-V10)/V10) -> -1 | AA10: =VLOOKUP(표9[[#This Row],[Team]],표1[],3,0) -> 1000
A11: =VLOOKUP($H11,Akamai!$A:$H,2,0) -> Akamai | B11: =VLOOKUP($H11,Akamai!$A:$H,3,0) -> KRAFTON HQ | C11: =VLOOKUP($H11,Akamai!$A:$H,4,0) -> KRAFTON HQ | D11: =VLOOKUP($H11,Akamai!$A:$H,5,0) -> BGMI DevOps Team | E11: =VLOOKUP($H11,Akamai!$A:$H,6,0) -> (2022)BATTLEGROUNDS_MOBILE_IN | F11: =VLOOKUP(표9[[#This Row],[Team]],표1[[내역]:[코스트 센터]],2,0) -> 100553 | G11: =VLOOKUP(표9[[#This Row],[Project]],표2[],2,0) -> P100130012 | H11: PUBG India | I11: =VLOOKUP($H11,Akamai!$A:$H,7,0) -> 이돈현 | J11: =VLOOKUP($H11,Akamai!$A:$H,8,0) -> 이돈현 | K11: v | L11: 717155429 | M11: 534113519 | N11: 921689465 | O11: 689008671 | P11: 899905653 | Q11: 599777963 | R11: 865196956 | S11: 616285601 | T11: 844093018 | U11: 380658986 | V11: 468732101 | W11: =ROUND(표9[[#This Row],[Apr 2026 (USD or KRW)]],0) -> 0 | Y11: =표9[[#This Row],[Apr 2027(KRW)]]-표9[[#This Row],[Mar 2026(KRW)]] -> -468732101 | Z11: =IF(V11=0,"",(W11-V11)/V11) -> -1 | AA11: =VLOOKUP(표9[[#This Row],[Team]],표1[],3,0) -> 1000
A12: =VLOOKUP($H12,Akamai!$A:$H,2,0) -> Akamai | B12: =VLOOKUP($H12,Akamai!$A:$H,3,0) -> KRAFTON HQ | C12: =VLOOKUP($H12,Akamai!$A:$H,4,0) -> KRAFTON HQ | D12: =VLOOKUP($H12,Akamai!$A:$H,5,0) -> PUBG PC&Console Dev Div. | E12: =VLOOKUP($H12,Akamai!$A:$H,6,0) -> BATTLEGROUNDS_PC/CONSOLE | F12: =VLOOKUP(표9[[#This Row],[Team]],표1[[내역]:[코스트 센터]],2,0) -> 100414 | G12: =VLOOKUP(표9[[#This Row],[Project]],표2[],2,0) -> P100010012 | H12: PUBG PC/Console | I12: =VLOOKUP($H12,Akamai!$A:$H,7,0) -> 김정헌 | J12: =VLOOKUP($H12,Akamai!$A:$H,8,0) -> 최준석 | K12: v | L12: 1485849 | M12: 1439358 | N12: 1637229 | O12: 1394062 | P12: 1300651 | Q12: 1293148 | R12: 1354057 | S12: 1437475 | T12: 1357700 | U12: 1187780 | V12: 1542493 | W12: =ROUND(표9[[#This Row],[Apr 2026 (USD or KRW)]],0) -> 0 | Y12: =표9[[#This Row],[Apr 2027(KRW)]]-표9[[#This Row],[Mar 2026(KRW)]] -> -1542493 | Z12: =IF(V12=0,"",(W12-V12)/V12) -> -1 | AA12: =VLOOKUP(표9[[#This Row],[Team]],표1[],3,0) -> 1000
A13: =VLOOKUP($H13,Akamai!$A:$H,2,0) -> Akamai | B13: =VLOOKUP($H13,Akamai!$A:$H,3,0) -> KRAFTON HQ | C13: =VLOOKUP($H13,Akamai!$A:$H,4,0) -> KRAFTON HQ | D13: =VLOOKUP($H13,Akamai!$A:$H,5,0) -> IT Dept. | E13: =VLOOKUP($H13,Akamai!$A:$H,6,0) -> OVERHEAD/OTHERS | F13: =VLOOKUP(표9[[#This Row],[Team]],표1[[내역]:[코스트 센터]],2,0) -> 100036 | G13: =VLOOKUP(표9[[#This Row],[Project]],표2[],2,0) -> I100099999 | H13: SSL Network Access-Third-party - VIP | I13: =VLOOKUP($H13,Akamai!$A:$H,7,0) -> 이윤슬 | J13: =VLOOKUP($H13,Akamai!$A:$H,8,0) -> 이윤슬 | K13: v | L13: 250000 | M13: 250000 | N13: 250000 | O13: 250000 | P13: 250000 | Q13: 250000 | R13: 250000 | S13: 250000 | T13: 250000 | U13: 250000 | V13: 257500 | W13: =ROUND(표9[[#This Row],[Apr 2026 (USD or KRW)]],0) -> 0 | Y13: =표9[[#This Row],[Apr 2027(KRW)]]-표9[[#This Row],[Mar 2026(KRW)]] -> -257500 | Z13: =IF(V13=0,"",(W13-V13)/V13) -> -1 | AA13: =VLOOKUP(표9[[#This Row],[Team]],표1[],3,0) -> 1000
A14: =VLOOKUP($H14,AWS!$A:$H,2,0) -> AWS | B14: =VLOOKUP($H14,AWS!$A:$H,3,0) -> KRAFTON HQ | C14: =VLOOKUP($H14,AWS!$A:$H,4,0) -> PUBG STUDIO | D14: =VLOOKUP($H14,AWS!$A:$H,5,0) -> Game Security Engineering Dept. | E14: =VLOOKUP($H14,AWS!$A:$H,6,0) -> Dark and Darker_Mobile | F14: =VLOOKUP(표9[[#This Row],[Team]],표1[[내역]:[코스트 센터]],2,0) -> 100415 | G14: =VLOOKUP(표9[[#This Row],[Project]],표2[],2,0) -> P100030073 | H14: aws_ab-anticheat-service@bluehole.net(799954618127) | I14: =VLOOKUP($H14,AWS!$A:$H,8,0) -> 황범석 | J14: =VLOOKUP($H14,AWS!$A:$H,8,0) -> 황범석 | K14: v | L14: 1671608 | M14: 1845569 | N14: 1915815 | O14: 1909640 | P14: 1842532 | Q14: 2014054 | R14: 1980991 | S14: 2014224 | T14: 1331949 | U14: 0 | V14: 0 | W14: =ROUND(표9[[#This Row],[Apr 2026 (USD or KRW)]],0) -> 0 | Y14: =표9[[#This Row],[Apr 2027(KRW)]]-표9[[#This Row],[Mar 2026(KRW)]] -> 0 | Z14: =IF(V14=0,"",(W14-V14)/V14) | AA14: =VLOOKUP(표9[[#This Row],[Team]],표1[],3,0) -> 1000
A15: =VLOOKUP($H15,AWS!$A:$H,2,0) -> AWS | B15: =VLOOKUP($H15,AWS!$A:$H,3,0) -> Neptune | C15: =VLOOKUP($H15,AWS!$A:$H,4,0) -> Neptune | D15: =VLOOKUP($H15,AWS!$A:$H,5,0) -> 0 | E15: =VLOOKUP($H15,AWS!$A:$H,6,0) -> 0 | F15: =VLOOKUP(표9[[#This Row],[Team]],표1[[내역]:[코스트 센터]],2,0) -> #N/A | G15: =VLOOKUP(표9[[#This Row],[Project]],표2[],2,0) -> #N/A | H15: aws_adx_001@adxcorp.kr(302454496823) | I15: =VLOOKUP($H15,AWS!$A:$H,7,0) -> 0 | J15: =VLOOKUP($H15,AWS!$A:$H,8,0) -> 0 | N15: 18362681 | O15: 18359745 | P15: 17889520 | Q15: 19810937 | R15: 22521870 | S15: 23347104 | T15: 21843596 | U15: 17375608 | V15: 21201908 | W15: =ROUND(표9[[#This Row],[Apr 2026 (USD or KRW)]],0) -> 0 | Y15: =표9[[#This Row],[Apr 2027(KRW)]]-표9[[#This Row],[Mar 2026(KRW)]] -> -21201908 | Z15: =IF(V15=0,"",(W15-V15)/V15) -> -1 | AA15: =VLOOKUP(표9[[#This Row],[Team]],표1[],3,0) -> #N/A
A16: =VLOOKUP($H16,AWS!$A:$H,2,0) -> AWS | B16: =VLOOKUP($H16,AWS!$A:$H,3,0) -> Neptune | C16: =VLOOKUP($H16,AWS!$A:$H,4,0) -> Neptune | D16: =VLOOKUP($H16,AWS!$A:$H,5,0) -> 0 | E16: =VLOOKUP($H16,AWS!$A:$H,6,0) -> 0 | F16: =VLOOKUP(표9[[#This Row],[Team]],표1[[내역]:[코스트 센터]],2,0) -> #N/A | G16: =VLOOKUP(표9[[#This Row],[Project]],표2[],2,0) -> #N/A | H16: aws_adx_002@adxcorp.kr(796181577313) | I16: =VLOOKUP($H16,AWS!$A:$H,7,0) -> 0 | J16: =VLOOKUP($H16,AWS!$A:$H,8,0) -> 0 | N16: 15739959 | O16: 11897051 | P16: 14014693 | Q16: 12523100 | R16: 12159154 | S16: 14756395 | T16: 17951593 | U16: 13279139 | V16: 15292648 | W16: =ROUND(표9[[#This Row],[Apr 2026 (USD or KRW)]],0) -> 0 | Y16: =표9[[#This Row],[Apr 2027(KRW)]]-표9[[#This Row],[Mar 2026(KRW)]] -> -15292648 | Z16: =IF(V16=0,"",(W16-V16)/V16) -> -1 | AA16: =VLOOKUP(표9[[#This Row],[Team]],표1[],3,0) -> #N/A
A17: =VLOOKUP($H17,AWS!$A:$H,2,0) -> AWS | B17: =VLOOKUP($H17,AWS!$A:$H,3,0) -> Neptune | C17: =VLOOKUP($H17,AWS!$A:$H,4,0) -> Neptune | D17: =VLOOKUP($H17,AWS!$A:$H,5,0) -> 0 | E17: =VLOOKUP($H17,AWS!$A:$H,6,0) -> 0 | F17: =VLOOKUP(표9[[#This Row],[Team]],표1[[내역]:[코스트 센터]],2,0) -> #N/A | G17: =VLOOKUP(표9[[#This Row],[Project]],표2[],2,0) -> #N/A | H17: aws_adx_003@adxcorp.kr(765348431472) | I17: =VLOOKUP($H17,AWS!$A:$H,7,0) -> 0 | J17: =VLOOKUP($H17,AWS!$A:$H,8,0) -> 0 | N17: 2338429 | O17: 2051754 | P17: 1930885 | Q17: 2298205 | R17: 2156992 | S17: 2218858 | T17: 2139444 | U17: 1934424 | V17: 2179676 | W17: =ROUND(표9[[#This Row],[Apr 2026 (USD or KRW)]],0) -> 0 | Y17: =표9[[#This Row],[Apr 2027(KRW)]]-표9[[#This Row],[Mar 2026(KRW)]] -> -2179676 | Z17: =IF(V17=0,"",(W17-V17)/V17) -> -1 | AA17: =VLOOKUP(표9[[#This Row],[Team]],표1[],3,0) -> #N/A
A18: =VLOOKUP($H18,AWS!$A:$H,2,0) -> AWS | B18: =VLOOKUP($H18,AWS!$A:$H,3,0) -> Neptune | C18: =VLOOKUP($H18,AWS!$A:$H,4,0) -> Neptune | D18: =VLOOKUP($H18,AWS!$A:$H,5,0) -> 0 | E18: =VLOOKUP($H18,AWS!$A:$H,6,0) -> 0 | F18: =VLOOKUP(표9[[#This Row],[Team]],표1[[내역]:[코스트 센터]],2,0) -> #N/A | G18: =VLOOKUP(표9[[#This Row],[Project]],표2[],2,0) -> #N/A | H18: aws_adx_004@adxcorp.kr(142379511204) | J18: =VLOOKUP($H18,AWS!$A:$H,8,0) -> 0 | N18: 266511 | O18: 277368 | P18: 262240 | Q18: 275974 | R18: 274748 | S18: 277807 | T18: 276367 | U18: 249269 | V18: 292732 | W18: =ROUND(표9[[#This Row],[Apr 2026 (USD or KRW)]],0) -> 0 | Y18: =표9[[#This Row],[Apr 2027(KRW)]]-표9[[#This Row],[Mar 2026(KRW)]] -> -292732 | Z18: =IF(V18=0,"",(W18-V18)/V18) -> -1 | AA18: =VLOOKUP(표9[[#This Row],[Team]],표1[],3,0) -> #N/A
A19: =VLOOKUP($H19,AWS!$A:$H,2,0) -> AWS | B19: =VLOOKUP($H19,AWS!$A:$H,3,0) -> Neptune | C19: =VLOOKUP($H19,AWS!$A:$H,4,0) -> Neptune | D19: =VLOOKUP($H19,AWS!$A:$H,5,0) -> 0 | E19: =VLOOKUP($H19,AWS!$A:$H,6,0) -> 0 | F19: =VLOOKUP(표9[[#This Row],[Team]],표1[[내역]:[코스트 센터]],2,0) -> #N/A | G19: =VLOOKUP(표9[[#This Row],[Project]],표2[],2,0) -> #N/A | H19: aws_adx_005@adxcorp.kr(139869765471) | I19: =VLOOKUP($H19,AWS!$A:$H,7,0) -> 0 | J19: =VLOOKUP($H19,AWS!$A:$H,8,0) -> 0 | N19: 3707959 | O19: 3735238 | P19: 3645859 | Q19: 3796250 | R19: 3809735 | S19: 3804670 | T19: 3772958 | U19: 3535747 | V19: 4056545 | W19: =ROUND(표9[[#This Row],[Apr 2026 (USD or KRW)]],0) -> 0 | Y19: =표9[[#This Row],[Apr 2027(KRW)]]-표9[[#This Row],[Mar 2026(KRW)]] -> -4056545 | Z19: =IF(V19=0,"",(W19-V19)/V19) -> -1 | AA19: =VLOOKUP(표9[[#This Row],[Team]],표1[],3,0) -> #N/A
A20: =VLOOKUP($H20,AWS!$A:$H,2,0) -> AWS | B20: =VLOOKUP($H20,AWS!$A:$H,3,0) -> Neptune | C20: =VLOOKUP($H20,AWS!$A:$H,4,0) -> Neptune | D20: =VLOOKUP($H20,AWS!$A:$H,5,0) -> 0 | E20: =VLOOKUP($H20,AWS!$A:$H,6,0) -> 0 | F20: =VLOOKUP(표9[[#This Row],[Team]],표1[[내역]:[코스트 센터]],2,0) -> #N/A | G20: =VLOOKUP(표9[[#This Row],[Project]],표2[],2,0) -> #N/A | H20: aws_adx_007@adxcorp.kr(495653056399) | I20: =VLOOKUP($H20,AWS!$A:$H,7,0) -> 0 | J20: =VLOOKUP($H20,AWS!$A:$H,8,0) -> 0 | N20: 4392 | O20: 10885 | P20: 5102 | Q20: 5212 | R20: 5091 | S20: 4994 | T20: 5153 | U20: 4869 | V20: 5036 | W20: =ROUND(표9[[#This Row],[Apr 2026 (USD or KRW)]],0) -> 0 | Y20: =표9[[#This Row],[Apr 2027(KRW)]]-표9[[#This Row],[Mar 2026(KRW)]] -> -5036 | Z20: =IF(V20=0,"",(W20-V20)/V20) -> -1 | AA20: =VLOOKUP(표9[[#This Row],[Team]],표1[],3,0) -> #N/A
A21: =VLOOKUP($H21,AWS!$A:$H,2,0) -> AWS | B21: =VLOOKUP($H21,AWS!$A:$H,3,0) -> Neptune | C21: =VLOOKUP($H21,AWS!$A:$H,4,0) -> Neptune | D21: =VLOOKUP($H21,AWS!$A:$H,5,0) -> 0 | E21: =VLOOKUP($H21,AWS!$A:$H,6,0) -> 0 | F21: =VLOOKUP(표9[[#This Row],[Team]],표1[[내역]:[코스트 센터]],2,0) -> #N/A | G21: =VLOOKUP(표9[[#This Row],[Project]],표2[],2,0) -> #N/A | H21: aws_adx_008@adxcorp.kr(126271033811) | I21: =VLOOKUP($H21,AWS!$A:$H,7,0) -> 0 | J21: =VLOOKUP($H21,AWS!$A:$H,8,0) -> 0 | O21: 43207 | P21: 1990105 | Q21: 2536230 | R21: 4860583 | S21: 5393691 | T21: 2881278 | U21: 2400417 | V21: 4925923 | W21: =ROUND(표9[[#This Row],[Apr 2026 (USD or KRW)]],0) -> 0 | Y21: =표9[[#This Row],[Apr 2027(KRW)]]-표9[[#This Row],[Mar 2026(KRW)]] -> -4925923 | Z21: =IF(V21=0,"",(W21-V21)/V21) -> -1 | AA21: =VLOOKUP(표9[[#This Row],[Team]],표1[],3,0) -> #N/A
A22: =VLOOKUP($H22,AWS!$A:$H,2,0) -> AWS | B22: =VLOOKUP($H22,AWS!$A:$H,3,0) -> KRAFTON HQ | C22: =VLOOKUP($H22,AWS!$A:$H,4,0) -> KRAFTON HQ | D22: =VLOOKUP($H22,AWS!$A:$H,5,0) -> IT Dept. | E22: =VLOOKUP($H22,AWS!$A:$H,6,0) -> OVERHEAD/OTHERS | F22: =VLOOKUP(표9[[#This Row],[Team]],표1[[내역]:[코스트 센터]],2,0) -> 100036 | G22: =VLOOKUP(표9[[#This Row],[Project]],표2[],2,0) -> I100099999 | H22: aws_bcp_prd@bluehole.net(439802505510) | I22: =VLOOKUP($H22,AWS!$A:$H,8,0) -> 김승훈 | J22: =VLOOKUP($H22,AWS!$A:$H,8,0) -> 김승훈 | L22: 5134845 | M22: 5039340 | N22: 5308753 | O22: 5447553 | P22: 5572764 | Q22: 6727361 | R22: 7513091 | S22: 13408344 | T22: 14033032 | U22: 13099289 | V22: 15925469 | W22: =ROUND(표9[[#This Row],[Apr 2026 (USD or KRW)]],0) -> 0 | Y22: =표9[[#This Row],[Apr 2027(KRW)]]-표9[[#This Row],[Mar 2026(KRW)]] -> -15925469 | Z22: =IF(V22=0,"",(W22-V22)/V22) -> -1 | AA22: =VLOOKUP(표9[[#This Row],[Team]],표1[],3,0) -> 1000
A23: =VLOOKUP($H23,AWS!$A:$H,2,0) -> AWS | B23: =VLOOKUP($H23,AWS!$A:$H,3,0) -> KRAFTON HQ | C23: =VLOOKUP($H23,AWS!$A:$H,4,0) -> KRAFTON HQ | D23: =VLOOKUP($H23,AWS!$A:$H,5,0) -> Global Subsidiary Management Team | E23: =VLOOKUP($H23,AWS!$A:$H,6,0) -> OVERHEAD/OTHERS | F23: =VLOOKUP(표9[[#This Row],[Team]],표1[[내역]:[코스트 센터]],2,0) -> 101712 | G23: =VLOOKUP(표9[[#This Row],[Project]],표2[],2,0) -> I100099999 | H23: AWS_between.dev@krafton.com(616709738515) | I23: =VLOOKUP($H23,AWS!$A:$H,8,0) -> 김재현 | J23: =VLOOKUP($H23,AWS!$A:$H,8,0) -> 김재현 | L23: 799019 | M23: 792837 | N23: 939615 | O23: 1327074 | P23: 1391627 | Q23: 1497582 | R23: 1515281 | S23: 1595865 | T23: 1116148 | U23: 134854 | V23: 139070 | W23: =ROUND(표9[[#This Row],[Apr 2026 (USD or KRW)]],0) -> 0 | Y23: =표9[[#This Row],[Apr 2027(KRW)]]-표9[[#This Row],[Mar 2026(KRW)]] -> -139070 | Z23: =IF(V23=0,"",(W23-V23)/V23) -> -1 | AA23: =VLOOKUP(표9[[#This Row],[Team]],표1[],3,0) -> 1000
A24: =VLOOKUP($H24,AWS!$A:$H,2,0) -> AWS | B24: =VLOOKUP($H24,AWS!$A:$H,3,0) -> KRAFTON HQ | C24: =VLOOKUP($H24,AWS!$A:$H,4,0) -> SDS | D24: =VLOOKUP($H24,AWS!$A:$H,5,0) -> Striking Distance Studios | E24: =VLOOKUP($H24,AWS!$A:$H,6,0) -> The Callisto Protocol | F24: =VLOOKUP(표9[[#This Row],[Team]],표1[[내역]:[코스트 센터]],2,0) -> 100561 | G24: =VLOOKUP(표9[[#This Row],[Project]],표2[],2,0) -> P100010013 | H24: AWS_blackbox-dev@sds.com(659459735321) | I24: =VLOOKUP($H24,AWS!$A:$H,8,0) -> Jordan Yerkes | J24: =VLOOKUP($H24,AWS!$A:$H,8,0) -> Jordan Yerkes | L24: 4067515 | M24: 5393574 | S24: 0 | T24: 0 | U24: 0 | V24: 0 | W24: =ROUND(표9[[#This Row],[Apr 2026 (USD or KRW)]],0) -> 0 | Y24: =표9[[#This Row],[Apr 2027(KRW)]]-표9[[#This Row],[Mar 2026(KRW)]] -> 0 | Z24: =IF(V24=0,"",(W24-V24)/V24) | AA24: =VLOOKUP(표9[[#This Row],[Team]],표1[],3,0) -> 1000
A25: =VLOOKUP($H25,AWS!$A:$H,2,0) -> AWS | B25: =VLOOKUP($H25,AWS!$A:$H,3,0) -> KRAFTON HQ | C25: =VLOOKUP($H25,AWS!$A:$H,4,0) -> InZOI Studio | D25: =VLOOKUP($H25,AWS!$A:$H,5,0) -> inZOI Server Team | E25: =VLOOKUP($H25,AWS!$A:$H,6,0) -> inZOI | F25: =VLOOKUP(표9[[#This Row],[Team]],표1[[내역]:[코스트 센터]],2,0) -> #N/A | G25: =VLOOKUP(표9[[#This Row],[Project]],표2[],2,0) -> P100010055 | H25: aws_blue@bluehole.net(611812385851) | I25: =VLOOKUP($H25,AWS!$A:$H,8,0) -> 조재욱 | J25: =VLOOKUP($H25,AWS!$A:$H,8,0) -> 조재욱 | L25: 831954 | M25: 819863 | N25: 1055148 | O25: 1457941 | P25: 1458274 | Q25: 1496773 | R25: 1510606 | S25: 1884390 | T25: 2078934 | U25: 1849540 | V25: 2470019 | W25: =ROUND(표9[[#This Row],[Apr 2026 (USD or KRW)]],0) -> 0 | Y25: =표9[[#This Row],[Apr 2027(KRW)]]-표9[[#This Row],[Mar 2026(KRW)]] -> -2470019 | Z25: =IF(V25=0,"",(W25-V25)/V25) -> -1 | AA25: =VLOOKUP(표9[[#This Row],[Team]],표1[],3,0) -> #N/A
A26: =VLOOKUP($H26,AWS!$A:$H,2,0) -> AWS | B26: =VLOOKUP($H26,AWS!$A:$H,3,0) -> KRAFTON HQ | C26: =VLOOKUP($H26,AWS!$A:$H,4,0) -> KRAFTON HQ | D26: =VLOOKUP($H26,AWS!$A:$H,5,0) -> Data Engineering Dept. | E26: =VLOOKUP($H26,AWS!$A:$H,6,0) -> OVERHEAD/OTHERS | F26: =VLOOKUP(표9[[#This Row],[Team]],표1[[내역]:[코스트 센터]],2,0) -> 100212 | G26: =VLOOKUP(표9[[#This Row],[Project]],표2[],2,0) -> I100099999 | H26: AWS_data-tech@krafton.com(272510915182) | I26: =VLOOKUP($H26,AWS!$A:$H,8,0) -> 김시훈 | J26: =VLOOKUP($H26,AWS!$A:$H,8,0) -> 김시훈 | K26: v | L26: 307937120 | M26: 346814364 | N26: 2998736452 | O26: 408151249 | P26: 437260317 | Q26: 545351157 | R26: 547726239 | S26: 3310004714 | T26: 567365183 | U26: 1032195117 | V26: 1173899035 | W26: =ROUND(표9[[#This Row],[Apr 2026 (USD or KRW)]],0) -> 0 | Y26: =표9[[#This Row],[Apr 2027(KRW)]]-표9[[#This Row],[Mar 2026(KRW)]] -> -1173899035 | Z26: =IF(V26=0,"",(W26-V26)/V26) -> -1 | AA26: =VLOOKUP(표9[[#This Row],[Team]],표1[],3,0) -> 1000
A27: =VLOOKUP($H27,AWS!$A:$H,2,0) -> AWS | B27: =VLOOKUP($H27,AWS!$A:$H,3,0) -> Research | C27: =VLOOKUP($H27,AWS!$A:$H,4,0) -> Research | D27: =VLOOKUP($H27,AWS!$A:$H,5,0) -> AI research center | E27: =VLOOKUP($H27,AWS!$A:$H,6,0) -> OVERHEAD/OTHERS | F27: =VLOOKUP(표9[[#This Row],[Team]],표1[[내역]:[코스트 센터]],2,0) -> 100677 | G27: =VLOOKUP(표9[[#This Row],[Project]],표2[],2,0) -> I100099999 | H27: aws_de_mturk@krafton.com(036022206166) | I27: =VLOOKUP($H27,AWS!$A:$H,8,0) -> 김범수 | J27: =VLOOKUP($H27,AWS!$A:$H,8,0) -> 김범수 | L27: 6535 | M27: 14339 | N27: 5980 | O27: 11207 | P27: 8576 | Q27: 9012 | R27: 9819 | S27: 1937257 | T27: 1917819 | U27: 3078092 | V27: 3596090 | W27: =ROUND(표9[[#This Row],[Apr 2026 (USD or KRW)]],0) -> 0 | Y27: =표9[[#This Row],[Apr 2027(KRW)]]-표9[[#This Row],[Mar 2026(KRW)]] -> -3596090 | Z27: =IF(V27=0,"",(W27-V27)/V27) -> -1 | AA27: =VLOOKUP(표9[[#This Row],[Team]],표1[],3,0) -> 1000
A28: =VLOOKUP($H28,AWS!$A:$H,2,0) -> AWS | B28: =VLOOKUP($H28,AWS!$A:$H,3,0) -> Risingwings | C28: =VLOOKUP($H28,AWS!$A:$H,4,0) -> Risingwings | D28: =VLOOKUP($H28,AWS!$A:$H,5,0) -> RW Tech Support Dept. | E28: =VLOOKUP($H28,AWS!$A:$H,6,0) -> 0 | F28: =VLOOKUP(표9[[#This Row],[Team]],표1[[내역]:[코스트 센터]],2,0) -> #N/A | G28: =VLOOKUP(표9[[#This Row],[Project]],표2[],2,0) -> #N/A | H28: AWS_defensederby@risingwings.com(183323689126) | I28: =VLOOKUP($H28,AWS!$A:$H,7,0) -> 허지웅 | J28: =VLOOKUP($H28,AWS!$A:$H,8,0) -> 허지웅 | L28: 105729 | M28: 113452 | N28: 105347 | O28: 126266 | P28: 5287 | S28: 0 | T28: 0 | U28: 0 | V28: 0 | W28: =ROUND(표9[[#This Row],[Apr 2026 (USD or KRW)]],0) -> 0 | Y28: =표9[[#This Row],[Apr 2027(KRW)]]-표9[[#This Row],[Mar 2026(KRW)]] -> 0 | Z28: =IF(V28=0,"",(W28-V28)/V28) | AA28: =VLOOKUP(표9[[#This Row],[Team]],표1[],3,0) -> #N/A
A29: =VLOOKUP($H29,AWS!$A:$H,2,0) -> AWS | B29: =VLOOKUP($H29,AWS!$A:$H,3,0) -> Research | C29: =VLOOKUP($H29,AWS!$A:$H,4,0) -> Research | D29: =VLOOKUP($H29,AWS!$A:$H,5,0) -> ML Sys & Ops Team | E29: =VLOOKUP($H29,AWS!$A:$H,6,0) -> DEEP LEARNING | F29: =VLOOKUP(표9[[#This Row],[Team]],표1[[내역]:[코스트 센터]],2,0) -> 100810 | G29: =VLOOKUP(표9[[#This Row],[Project]],표2[],2,0) -> I100090817 | H29: AWS_DLD_dev@bluehole.net(171503962539) | I29: =VLOOKUP($H29,AWS!$A:$H,8,0) -> 김지윤 | J29: =VLOOKUP($H29,AWS!$A:$H,8,0) -> 김지윤 | K29: v | L29: 4468067 | M29: 3980672 | N29: 4538114 | O29: 5204950 | P29: 5155923 | Q29: 5363119 | R29: 5440702 | S29: 5415029 | T29: 5187691 | U29: 3957122 | V29: 4330547 | W29: =ROUND(표9[[#This Row],[Apr 2026 (USD or KRW)]],0) -> 0 | Y29: =표9[[#This Row],[Apr 2027(KRW)]]-표9[[#This Row],[Mar 2026(KRW)]] -> -4330547 | Z29: =IF(V29=0,"",(W29-V29)/V29) -> -1 | AA29: =VLOOKUP(표9[[#This Row],[Team]],표1[],3,0) -> 1000
A30: =VLOOKUP($H30,AWS!$A:$H,2,0) -> AWS | B30: =VLOOKUP($H30,AWS!$A:$H,3,0) -> Dreamotion | C30: =VLOOKUP($H30,AWS!$A:$H,4,0) -> Dreamotion | D30: =VLOOKUP($H30,AWS!$A:$H,5,0) -> Project MLP Team | E30: =VLOOKUP($H30,AWS!$A:$H,6,0) -> Road to Valor: Empire | F30: =VLOOKUP(표9[[#This Row],[Team]],표1[[내역]:[코스트 센터]],2,0) -> #N/A | G30: =VLOOKUP(표9[[#This Row],[Project]],표2[],2,0) -> #N/A | H30: AWS_Dreamotion-Empire@krafton.com(828925677153) | I30: =VLOOKUP($H30,AWS!$A:$H,7,0) -> 류성중 | J30: =VLOOKUP($H30,AWS!$A:$H,8,0) -> 류성중 | L30: 991576 | M30: 954507 | N30: 1187771 | O30: 989785 | P30: 971495 | Q30: 1265010 | R30: 1261521 | S30: 1246848 | T30: 1135164 | U30: 988449 | V30: 1151781 | W30: =ROUND(표9[[#This Row],[Apr 2026 (USD or KRW)]],0) -> 0 | Y30: =표9[[#This Row],[Apr 2027(KRW)]]-표9[[#This Row],[Mar 2026(KRW)]] -> -1151781 | Z30: =IF(V30=0,"",(W30-V30)/V30) -> -1 | AA30: =VLOOKUP(표9[[#This Row],[Team]],표1[],3,0) -> #N/A
A31: =VLOOKUP($H31,AWS!$A:$H,2,0) -> AWS | B31: =VLOOKUP($H31,AWS!$A:$H,3,0) -> Dreamotion | C31: =VLOOKUP($H31,AWS!$A:$H,4,0) -> Dreamotion | D31: =VLOOKUP($H31,AWS!$A:$H,5,0) -> Project MLP Team | E31: =VLOOKUP($H31,AWS!$A:$H,6,0) -> GunStrider: Tap Strike | F31: =VLOOKUP(표9[[#This Row],[Team]],표1[[내역]:[코스트 센터]],2,0) -> #N/A | G31: =VLOOKUP(표9[[#This Row],[Project]],표2[],2,0) -> #N/A | H31: AWS_Dreamotion-GunStrider@krafton.com(286067354613) | I31: =VLOOKUP($H31,AWS!$A:$H,7,0) -> 류성중 | J31: =VLOOKUP($H31,AWS!$A:$H,8,0) -> 류성중 | L31: 83727 | M31: 87910 | N31: 81718 | O31: 88431 | P31: 89268 | Q31: 89355 | R31: 96054 | S31: 87995 | T31: 84221 | U31: 76625 | V31: 107386 | W31: =ROUND(표9[[#This Row],[Apr 2026 (USD or KRW)]],0) -> 0 | Y31: =표9[[#This Row],[Apr 2027(KRW)]]-표9[[#This Row],[Mar 2026(KRW)]] -> -107386 | Z31: =IF(V31=0,"",(W31-V31)/V31) -> -1 | AA31: =VLOOKUP(표9[[#This Row],[Team]],표1[],3,0) -> #N/A
A32: =VLOOKUP($H32,AWS!$A:$H,2,0) -> AWS | B32: =VLOOKUP($H32,AWS!$A:$H,3,0) -> Dreamotion | C32: =VLOOKUP($H32,AWS!$A:$H,4,0) -> Dreamotion | D32: =VLOOKUP($H32,AWS!$A:$H,5,0) -> Project MLP Team | E32: =VLOOKUP($H32,AWS!$A:$H,6,0) -> Road to valor : world war2 | F32: =VLOOKUP(표9[[#This Row],[Team]],표1[[내역]:[코스트 센터]],2,0) -> #N/A | G32: =VLOOKUP(표9[[#This Row],[Project]],표2[],2,0) -> #N/A | H32: AWS_Dreamotion-RoadToValor@krafton.com(531219453947) | I32: =VLOOKUP($H32,AWS!$A:$H,7,0) -> 류성중 | J32: =VLOOKUP($H32,AWS!$A:$H,8,0) -> 류성중 | L32: 1568594 | M32: 1449646 | N32: 1606994 | O32: 1539701 | P32: 1404477 | Q32: 1613721 | R32: 1610654 | S32: 1589427 | T32: 1488166 | U32: 1366984 | V32: 1478086 | W32: =ROUND(표9[[#This Row],[Apr 2026 (USD or KRW)]],0) -> 0 | Y32: =표9[[#This Row],[Apr 2027(KRW)]]-표9[[#This Row],[Mar 2026(KRW)]] -> -1478086 | Z32: =IF(V32=0,"",(W32-V32)/V32) -> -1 | AA32: =VLOOKUP(표9[[#This Row],[Team]],표1[],3,0) -> #N/A
A33: =VLOOKUP($H33,AWS!$A:$H,2,0) -> AWS | B33: =VLOOKUP($H33,AWS!$A:$H,3,0) -> Dreamotion | C33: =VLOOKUP($H33,AWS!$A:$H,4,0) -> Dreamotion | D33: =VLOOKUP($H33,AWS!$A:$H,5,0) -> Project MLP Team | E33: =VLOOKUP($H33,AWS!$A:$H,6,0) -> Ronin: The Last Samurai | F33: =VLOOKUP(표9[[#This Row],[Team]],표1[[내역]:[코스트 센터]],2,0) -> #N/A | G33: =VLOOKUP(표9[[#This Row],[Project]],표2[],2,0) -> #N/A | H33: AWS_Dreamotion-Ronin@krafton.com(071872665424) | I33: =VLOOKUP($H33,AWS!$A:$H,7,0) -> 류성중 | J33: =VLOOKUP($H33,AWS!$A:$H,8,0) -> 류성중 | L33: 1115503 | M33: 1075700 | N33: 1302948 | O33: 1104698 | P33: 1085000 | Q33: 1376322 | R33: 1376876 | S33: 1367556 | T33: 1248339 | U33: 1104470 | V33: 1266915 | W33: =ROUND(표9[[#This Row],[Apr 2026 (USD or KRW)]],0) -> 0 | Y33: =표9[[#This Row],[Apr 2027(KRW)]]-표9[[#This Row],[Mar 2026(KRW)]] -> -1266915 | Z33: =IF(V33=0,"",(W33-V33)/V33) -> -1 | AA33: =VLOOKUP(표9[[#This Row],[Team]],표1[],3,0) -> #N/A
A34: =VLOOKUP($H34,AWS!$A:$H,2,0) -> AWS | B34: =VLOOKUP($H34,AWS!$A:$H,3,0) -> KRAFTON HQ | C34: =VLOOKUP($H34,AWS!$A:$H,4,0) -> KRAFTON HQ | D34: =VLOOKUP($H34,AWS!$A:$H,5,0) -> Security Dept. | E34: =VLOOKUP($H34,AWS!$A:$H,6,0) -> OVERHEAD/OTHERS | F34: =VLOOKUP(표9[[#This Row],[Team]],표1[[내역]:[코스트 센터]],2,0) -> 101451 | G34: =VLOOKUP(표9[[#This Row],[Project]],표2[],2,0) -> I100099999 | H34: aws_engineering_security@bluehole.net(635942867251) | I34: =VLOOKUP($H34,AWS!$A:$H,8,0) -> 홍준화 | J34: =VLOOKUP($H34,AWS!$A:$H,8,0) -> 홍준화 | K34: v | L34: 2555506 | M34: 2534955 | N34: 2522685 | O34: 2604888 | P34: 3294806 | Q34: 3017838 | R34: 2282260 | S34: 2303702 | T34: 2848630 | U34: 3687339 | V34: 6340867 | W34: =ROUND(표9[[#This Row],[Apr 2026 (USD or KRW)]],0) -> 0 | Y34: =표9[[#This Row],[Apr 2027(KRW)]]-표9[[#This Row],[Mar 2026(KRW)]] -> -6340867 | Z34: =IF(V34=0,"",(W34-V34)/V34) -> -1 | AA34: =VLOOKUP(표9[[#This Row],[Team]],표1[],3,0) -> 1000
A35: =VLOOKUP($H35,AWS!$A:$H,2,0) -> AWS | B35: =VLOOKUP($H35,AWS!$A:$H,3,0) -> KRAFTON HQ | C35: =VLOOKUP($H35,AWS!$A:$H,4,0) -> KRAFTON HQ | D35: =VLOOKUP($H35,AWS!$A:$H,5,0) -> DevData Engineering Team | E35: =VLOOKUP($H35,AWS!$A:$H,6,0) -> BATTLEGROUNDS_PC/CONSOLE | F35: =VLOOKUP(표9[[#This Row],[Team]],표1[[내역]:[코스트 센터]],2,0) -> 101721 | G35: =VLOOKUP(표9[[#This Row],[Project]],표2[],2,0) -> P100010012 | H35: aws_esports_streaming@bluehole.net(559478286890) | I35: =VLOOKUP($H35,AWS!$A:$H,8,0) -> 안연주 | J35: =VLOOKUP($H35,AWS!$A:$H,8,0) -> 안연주 | L35: 2817722 | M35: 2727336 | N35: 2845993 | O35: 2883454 | P35: 3008796 | Q35: 2956316 | R35: 2739119 | S35: 3008046 | T35: 3093269 | U35: 2983882 | V35: 3672617 | W35: =ROUND(표9[[#This Row],[Apr 2026 (USD or KRW)]],0) -> 0 | Y35: =표9[[#This Row],[Apr 2027(KRW)]]-표9[[#This Row],[Mar 2026(KRW)]] -> -3672617 | Z35: =IF(V35=0,"",(W35-V35)/V35) -> -1 | AA35: =VLOOKUP(표9[[#This Row],[Team]],표1[],3,0) -> 1000
A36: =VLOOKUP($H36,AWS!$A:$H,2,0) -> AWS | B36: =VLOOKUP($H36,AWS!$A:$H,3,0) -> BLUEHOLE | C36: =VLOOKUP($H36,AWS!$A:$H,4,0) -> BLUEHOLE | D36: =VLOOKUP($H36,AWS!$A:$H,5,0) -> [N/A] AB Unit | E36: =VLOOKUP($H36,AWS!$A:$H,6,0) -> Dark and Darker_Mobile | F36: =VLOOKUP(표9[[#This Row],[Team]],표1[[내역]:[코스트 센터]],2,0) -> 110099 | G36: =VLOOKUP(표9[[#This Row],[Project]],표2[],2,0) -> P100030073 | H36: AWS_FF@bluehole.net(257405109560) | I36: =VLOOKUP($H36,AWS!$A:$H,8,0) -> 이민재 | J36: =VLOOKUP($H36,AWS!$A:$H,8,0) -> 이민재 | L36: 42095789 | M36: 45747688 | N36: 42442625 | O36: 38897801 | P36: 34960534 | Q36: 37665835 | R36: 34825214 | S36: 37528129 | T36: 33286868 | U36: 6640088 | V36: 7603373 | W36: =ROUND(표9[[#This Row],[Apr 2026 (USD or KRW)]],0) -> 0 | Y36: =표9[[#This Row],[Apr 2027(KRW)]]-표9[[#This Row],[Mar 2026(KRW)]] -> -7603373 | Z36: =IF(V36=0,"",(W36-V36)/V36) -> -1 | AA36: =VLOOKUP(표9[[#This Row],[Team]],표1[],3,0) -> 1100
A37: =VLOOKUP($H37,AWS!$A:$H,2,0) -> AWS | B37: =VLOOKUP($H37,AWS!$A:$H,3,0) -> KRAFTON HQ | C37: =VLOOKUP($H37,AWS!$A:$H,4,0) -> KRAFTON HQ | D37: =VLOOKUP($H37,AWS!$A:$H,5,0) -> Data Engineering Dept. | E37: =VLOOKUP($H37,AWS!$A:$H,6,0) -> OVERHEAD/OTHERS | F37: =VLOOKUP(표9[[#This Row],[Team]],표1[[내역]:[코스트 센터]],2,0) -> 100212 | G37: =VLOOKUP(표9[[#This Row],[Project]],표2[],2,0) -> I100099999 | H37: aws_gamesight@bluehole.net(171101943282) | I37: =VLOOKUP($H37,AWS!$A:$H,8,0) -> 김시훈 | J37: =VLOOKUP($H37,AWS!$A:$H,8,0) -> 김시훈 | K37: v | L37: 8195128 | M37: 8153395 | N37: 8860559 | O37: 8606579 | P37: 6658898 | Q37: 6363951 | R37: 6407382 | S37: 6319086 | T37: 6012372 | U37: 5550141 | V37: 6396490 | W37: =ROUND(표9[[#This Row],[Apr 2026 (USD or KRW)]],0) -> 0 | Y37: =표9[[#This Row],[Apr 2027(KRW)]]-표9[[#This Row],[Mar 2026(KRW)]] -> -6396490 | Z37: =IF(V37=0,"",(W37-V37)/V37) -> -1 | AA37: =VLOOKUP(표9[[#This Row],[Team]],표1[],3,0) -> 1000
A38: =VLOOKUP($H38,AWS!$A:$H,2,0) -> AWS | B38: =VLOOKUP($H38,AWS!$A:$H,3,0) -> KRAFTON HQ | C38: =VLOOKUP($H38,AWS!$A:$H,4,0) -> PUBG STUDIO | D38: =VLOOKUP($H38,AWS!$A:$H,5,0) -> [N/A] IN Publishing Production Team_HQ | E38: =VLOOKUP($H38,AWS!$A:$H,6,0) -> BULLET ECHO | F38: =VLOOKUP(표9[[#This Row],[Team]],표1[[내역]:[코스트 센터]],2,0) -> 101716 | G38: =VLOOKUP(표9[[#This Row],[Project]],표2[],2,0) -> P100030851 | H38: aws_india_publishing@bluehole.net(397907563279) | I38: =VLOOKUP($H38,AWS!$A:$H,8,0) -> 박지현 | J38: =VLOOKUP($H38,AWS!$A:$H,8,0) -> 박지현 | L38: 6193 | M38: 14057 | N38: 5893 | O38: 11055 | P38: 8537 | Q38: 9001 | R38: 9888 | S38: 8685 | T38: 10668 | U38: 9183 | V38: 3764 | W38: =ROUND(표9[[#This Row],[Apr 2026 (USD or KRW)]],0) -> 0 | Y38: =표9[[#This Row],[Apr 2027(KRW)]]-표9[[#This Row],[Mar 2026(KRW)]] -> -3764 | Z38: =IF(V38=0,"",(W38-V38)/V38) -> -1 | AA38: =VLOOKUP(표9[[#This Row],[Team]],표1[],3,0) -> 1000
A39: =VLOOKUP($H39,AWS!$A:$H,2,0) -> AWS | B39: =VLOOKUP($H39,AWS!$A:$H,3,0) -> KRAFTON HQ | C39: =VLOOKUP($H39,AWS!$A:$H,4,0) -> KRAFTON HQ | D39: =VLOOKUP($H39,AWS!$A:$H,5,0) -> IT Platform Engineering Team | E39: =VLOOKUP($H39,AWS!$A:$H,6,0) -> OVERHEAD/OTHERS | F39: =VLOOKUP(표9[[#This Row],[Team]],표1[[내역]:[코스트 센터]],2,0) -> 100024 | G39: =VLOOKUP(표9[[#This Row],[Project]],표2[],2,0) -> I100099999 | H39: aws_it-dev-ot-01@krafton.com(585980862501) | I39: =VLOOKUP($H39,AWS!$A:$H,8,0) -> 김주한 | J39: =VLOOKUP($H39,AWS!$A:$H,8,0) -> 김주한 | K39: v | S39: 252601 | T39: 432633 | U39: 90580 | V39: 3452 | W39: =ROUND(표9[[#This Row],[Apr 2026 (USD or KRW)]],0) -> 0 | Y39: =표9[[#This Row],[Apr 2027(KRW)]]-표9[[#This Row],[Mar 2026(KRW)]] -> -3452 | Z39: =IF(V39=0,"",(W39-V39)/V39) -> -1 | AA39: =VLOOKUP(표9[[#This Row],[Team]],표1[],3,0) -> 1000
A40: =VLOOKUP($H40,AWS!$A:$H,2,0) -> AWS | B40: =VLOOKUP($H40,AWS!$A:$H,3,0) -> KRAFTON HQ | C40: =VLOOKUP($H40,AWS!$A:$H,4,0) -> KRAFTON HQ | D40: =VLOOKUP($H40,AWS!$A:$H,5,0) -> IT Platform Engineering Team | E40: =VLOOKUP($H40,AWS!$A:$H,6,0) -> OVERHEAD/OTHERS | F40: =VLOOKUP(표9[[#This Row],[Team]],표1[[내역]:[코스트 센터]],2,0) -> 100024 | G40: =VLOOKUP(표9[[#This Row],[Project]],표2[],2,0) -> I100099999 | H40: aws_it-dev-ot-02@krafton.com(997525377919) | I40: =VLOOKUP($H40,AWS!$A:$H,8,0) -> 김주한 | J40: =VLOOKUP($H40,AWS!$A:$H,8,0) -> 김주한 | K40: v | S40: 167431 | T40: 465435 | U40: 274896 | V40: 51198 | W40: =ROUND(표9[[#This Row],[Apr 2026 (USD or KRW)]],0) -> 0 | Y40: =표9[[#This Row],[Apr 2027(KRW)]]-표9[[#This Row],[Mar 2026(KRW)]] -> -51198 | Z40: =IF(V40=0,"",(W40-V40)/V40) -> -1 | AA40: =VLOOKUP(표9[[#This Row],[Team]],표1[],3,0) -> 1000
A41: =VLOOKUP($H41,AWS!$A:$H,2,0) -> AWS | B41: =VLOOKUP($H41,AWS!$A:$H,3,0) -> KRAFTON HQ | C41: =VLOOKUP($H41,AWS!$A:$H,4,0) -> KRAFTON HQ | D41: =VLOOKUP($H41,AWS!$A:$H,5,0) -> IT Platform Engineering Team | E41: =VLOOKUP($H41,AWS!$A:$H,6,0) -> OVERHEAD/OTHERS | F41: =VLOOKUP(표9[[#This Row],[Team]],표1[[내역]:[코스트 센터]],2,0) -> 100024 | G41: =VLOOKUP(표9[[#This Row],[Project]],표2[],2,0) -> I100099999 | H41: aws_it-dev-ot-03@krafton.com(794383793399) | I41: =VLOOKUP($H41,AWS!$A:$H,8,0) -> 김주한 | J41: =VLOOKUP($H41,AWS!$A:$H,8,0) -> 김주한 | K41: v | S41: 94509 | T41: 473328 | U41: 492975 | V41: 39542 | W41: =ROUND(표9[[#This Row],[Apr 2026 (USD or KRW)]],0) -> 0 | Y41: =표9[[#This Row],[Apr 2027(KRW)]]-표9[[#This Row],[Mar 2026(KRW)]] -> -39542 | Z41: =IF(V41=0,"",(W41-V41)/V41) -> -1 | AA41: =VLOOKUP(표9[[#This Row],[Team]],표1[],3,0) -> 1000
A42: =VLOOKUP($H42,AWS!$A:$H,2,0) -> AWS | B42: =VLOOKUP($H42,AWS!$A:$H,3,0) -> KRAFTON HQ | C42: =VLOOKUP($H42,AWS!$A:$H,4,0) -> KRAFTON HQ | D42: =VLOOKUP($H42,AWS!$A:$H,5,0) -> IT Platform Engineering Team | E42: =VLOOKUP($H42,AWS!$A:$H,6,0) -> OVERHEAD/OTHERS | F42: =VLOOKUP(표9[[#This Row],[Team]],표1[[내역]:[코스트 센터]],2,0) -> 100024 | G42: =VLOOKUP(표9[[#This Row],[Project]],표2[],2,0) -> I100099999 | H42: aws_it-dev-ot-04@krafton.com(252497419944) | I42: =VLOOKUP($H42,AWS!$A:$H,8,0) -> 김주한 | J42: =VLOOKUP($H42,AWS!$A:$H,8,0) -> 김주한 | K42: v | S42: 175726 | T42: 999907 | U42: 866113 | V42: 1125 | W42: =ROUND(표9[[#This Row],[Apr 2026 (USD or KRW)]],0) -> 0 | Y42: =표9[[#This Row],[Apr 2027(KRW)]]-표9[[#This Row],[Mar 2026(KRW)]] -> -1125 | Z42: =IF(V42=0,"",(W42-V42)/V42) -> -1 | AA42: =VLOOKUP(표9[[#This Row],[Team]],표1[],3,0) -> 1000
A43: =VLOOKUP($H43,AWS!$A:$H,2,0) -> AWS | B43: =VLOOKUP($H43,AWS!$A:$H,3,0) -> KRAFTON HQ | C43: =VLOOKUP($H43,AWS!$A:$H,4,0) -> KRAFTON HQ | D43: =VLOOKUP($H43,AWS!$A:$H,5,0) -> Data Engineering Dept. | E43: =VLOOKUP($H43,AWS!$A:$H,6,0) -> OVERHEAD/OTHERS | F43: =VLOOKUP(표9[[#This Row],[Team]],표1[[내역]:[코스트 센터]],2,0) -> 100212 | G43: =VLOOKUP(표9[[#This Row],[Project]],표2[],2,0) -> I100099999 | H43: aws_krafton_ded@bluehole.net(333537382729) | I43: =VLOOKUP($H43,AWS!$A:$H,8,0) -> 김시훈 | J43: =VLOOKUP($H43,AWS!$A:$H,8,0) -> 김시훈 | K43: v | L43: 8811025 | M43: 8416881 | N43: 9154650 | O43: 9848766 | P43: 9558762 | Q43: 10799380 | R43: 10620630 | S43: 10857476 | T43: 9001074 | U43: 10267576 | V43: 15194049 | W43: =ROUND(표9[[#This Row],[Apr 2026 (USD or KRW)]],0) -> 0 | Y43: =표9[[#This Row],[Apr 2027(KRW)]]-표9[[#This Row],[Mar 2026(KRW)]] -> -15194049 | Z43: =IF(V43=0,"",(W43-V43)/V43) -> -1 | AA43: =VLOOKUP(표9[[#This Row],[Team]],표1[],3,0) -> 1000
A44: =VLOOKUP($H44,AWS!$A:$H,2,0) -> AWS | B44: =VLOOKUP($H44,AWS!$A:$H,3,0) -> KRAFTON HQ | C44: =VLOOKUP($H44,AWS!$A:$H,4,0) -> KRAFTON HQ | D44: =VLOOKUP($H44,AWS!$A:$H,5,0) -> KOS Engineering Dept. | E44: =VLOOKUP($H44,AWS!$A:$H,6,0) -> GPP | F44: =VLOOKUP(표9[[#This Row],[Team]],표1[[내역]:[코스트 센터]],2,0) -> 100025 | G44: =VLOOKUP(표9[[#This Row],[Project]],표2[],2,0) -> I100090813 | H44: aws_krafton_id@bluehole.net(853221784203) | I44: =VLOOKUP($H44,AWS!$A:$H,8,0) -> 신근우 | J44: =VLOOKUP($H44,AWS!$A:$H,8,0) -> 신근우 | L44: 62954383 | M44: 44294844 | N44: 50179558 | O44: 55992370 | P44: 63412696 | Q44: 66946988 | R44: 65622863 | S44: 71243757 | T44: 65973314 | U44: 53607916 | V44: 65843939 | W44: =ROUND(표9[[#This Row],[Apr 2026 (USD or KRW)]],0) -> 0 | Y44: =표9[[#This Row],[Apr 2027(KRW)]]-표9[[#This Row],[Mar 2026(KRW)]] -> -65843939 | Z44: =IF(V44=0,"",(W44-V44)/V44) -> -1 | AA44: =VLOOKUP(표9[[#This Row],[Team]],표1[],3,0) -> 1000
A45: =VLOOKUP($H45,AWS!$A:$H,2,0) -> AWS | B45: =VLOOKUP($H45,AWS!$A:$H,3,0) -> Research | C45: =VLOOKUP($H45,AWS!$A:$H,4,0) -> Research | D45: =VLOOKUP($H45,AWS!$A:$H,5,0) -> AI Product Dev Chapter Dept. | E45: =VLOOKUP($H45,AWS!$A:$H,6,0) -> DEEP LEARNING | F45: =VLOOKUP(표9[[#This Row],[Team]],표1[[내역]:[코스트 센터]],2,0) -> 102159 | G45: =VLOOKUP(표9[[#This Row],[Project]],표2[],2,0) -> I100090817 | H45: aws_krafton-service-dev-project@bluehole.net(921970894603) | I45: =VLOOKUP($H45,AWS!$A:$H,8,0) -> 박준규 | J45: =VLOOKUP($H45,AWS!$A:$H,8,0) -> 박준규 | L45: 14525020 | M45: 15729050 | N45: 17535570 | O45: 17842263 | P45: 18912195 | Q45: 19650581 | R45: 17815676 | S45: 20659940 | T45: 21967984 | U45: 22633853 | V45: 34700138 | W45: =ROUND(표9[[#This Row],[Apr 2026 (USD or KRW)]],0) -> 0 | Y45: =표9[[#This Row],[Apr 2027(KRW)]]-표9[[#This Row],[Mar 2026(KRW)]] -> -34700138 | Z45: =IF(V45=0,"",(W45-V45)/V45) -> -1 | AA45: =VLOOKUP(표9[[#This Row],[Team]],표1[],3,0) -> 1000
A46: =VLOOKUP($H46,AWS!$A:$H,2,0) -> AWS | B46: =VLOOKUP($H46,AWS!$A:$H,3,0) -> KRAFTON HQ | C46: =VLOOKUP($H46,AWS!$A:$H,4,0) -> KRAFTON HQ | D46: =VLOOKUP($H46,AWS!$A:$H,5,0) -> Data Engineering Dept. | E46: =VLOOKUP($H46,AWS!$A:$H,6,0) -> OVERHEAD/OTHERS | F46: =VLOOKUP(표9[[#This Row],[Team]],표1[[내역]:[코스트 센터]],2,0) -> 100212 | G46: =VLOOKUP(표9[[#This Row],[Project]],표2[],2,0) -> I100099999 | H46: aws_kraftonde-sensitive@krafton.com(226547056751) | I46: =VLOOKUP($H46,AWS!$A:$H,8,0) -> 김시훈 | J46: =VLOOKUP($H46,AWS!$A:$H,8,0) -> 김시훈 | K46: v | L46: 15849268 | M46: 15374256 | N46: 22077166 | O46: 16352942 | P46: 14594241 | Q46: 11522792 | R46: 12934575 | S46: 11283907 | T46: 11418594 | U46: 10614802 | V46: 11584204 | W46: =ROUND(표9[[#This Row],[Apr 2026 (USD or KRW)]],0) -> 0 | Y46: =표9[[#This Row],[Apr 2027(KRW)]]-표9[[#This Row],[Mar 2026(KRW)]] -> -11584204 | Z46: =IF(V46=0,"",(W46-V46)/V46) -> -1 | AA46: =VLOOKUP(표9[[#This Row],[Team]],표1[],3,0) -> 1000
A47: =VLOOKUP($H47,AWS!$A:$H,2,0) -> AWS | B47: =VLOOKUP($H47,AWS!$A:$H,3,0) -> KRAFTON HQ | C47: =VLOOKUP($H47,AWS!$A:$H,4,0) -> Mad Glory | D47: =VLOOKUP($H47,AWS!$A:$H,5,0) -> Valor Art Dept. | E47: =VLOOKUP($H47,AWS!$A:$H,6,0) -> Valor_Console | F47: =VLOOKUP(표9[[#This Row],[Team]],표1[[내역]:[코스트 센터]],2,0) -> 100762 | G47: =VLOOKUP(표9[[#This Row],[Project]],표2[],2,0) -> P100020081 | H47: aws_na_devops@bluehole.net(367916776138) | I47: =VLOOKUP($H47,AWS!$A:$H,8,0) -> Arthur Low (AJ) | J47: =VLOOKUP($H47,AWS!$A:$H,8,0) -> Arthur Low (AJ) | L47: 7654818 | M47: 6913775 | N47: 10378012 | O47: 16392501 | P47: 19757718 | Q47: 19787353 | R47: 14566944 | S47: 17775376 | T47: 18442442 | U47: 16378922 | V47: 19993451 | W47: =ROUND(표9[[#This Row],[Apr 2026 (USD or KRW)]],0) -> 0 | Y47: =표9[[#This Row],[Apr 2027(KRW)]]-표9[[#This Row],[Mar 2026(KRW)]] -> -19993451 | Z47: =IF(V47=0,"",(W47-V47)/V47) -> -1 | AA47: =VLOOKUP(표9[[#This Row],[Team]],표1[],3,0) -> 1000
A48: =VLOOKUP($H48,AWS!$A:$H,2,0) -> AWS | B48: =VLOOKUP($H48,AWS!$A:$H,3,0) -> KRAFTON HQ | C48: =VLOOKUP($H48,AWS!$A:$H,4,0) -> KRAFTON HQ | D48: =VLOOKUP($H48,AWS!$A:$H,5,0) -> KOS Engineering Dept. | E48: =VLOOKUP($H48,AWS!$A:$H,6,0) -> GPP | F48: =VLOOKUP(표9[[#This Row],[Team]],표1[[내역]:[코스트 센터]],2,0) -> 100025 | G48: =VLOOKUP(표9[[#This Row],[Project]],표2[],2,0) -> I100090813 | H48: AWS_napubtech-prod@bluehole.net(088833367732) | I48: =VLOOKUP($H48,AWS!$A:$H,8,0) -> 신근우 | J48: =VLOOKUP($H48,AWS!$A:$H,8,0) -> 신근우 | L48: 16239086 | M48: 14014268 | N48: 16069905 | O48: 15756664 | P48: 14705559 | Q48: 15585459 | R48: 15858055 | S48: 17363473 | T48: 14639135 | U48: 12405001 | V48: 14586392 | W48: =ROUND(표9[[#This Row],[Apr 2026 (USD or KRW)]],0) -> 0 | Y48: =표9[[#This Row],[Apr 2027(KRW)]]-표9[[#This Row],[Mar 2026(KRW)]] -> -14586392 | Z48: =IF(V48=0,"",(W48-V48)/V48) -> -1 | AA48: =VLOOKUP(표9[[#This Row],[Team]],표1[],3,0) -> 1000
A49: =VLOOKUP($H49,AWS!$A:$H,2,0) -> AWS | B49: =VLOOKUP($H49,AWS!$A:$H,3,0) -> KRAFTON HQ | C49: =VLOOKUP($H49,AWS!$A:$H,4,0) -> KRAFTON HQ | D49: =VLOOKUP($H49,AWS!$A:$H,5,0) -> KOS Engineering Dept. | E49: =VLOOKUP($H49,AWS!$A:$H,6,0) -> GPP | F49: =VLOOKUP(표9[[#This Row],[Team]],표1[[내역]:[코스트 센터]],2,0) -> 100025 | G49: =VLOOKUP(표9[[#This Row],[Project]],표2[],2,0) -> I100090813 | H49: AWS_napubtech-stage@bluehole.net(510906392559) | I49: =VLOOKUP($H49,AWS!$A:$H,8,0) -> 신근우 | J49: =VLOOKUP($H49,AWS!$A:$H,8,0) -> 신근우 | L49: 20962 | M49: 24950 | N49: 16035 | O49: 21296 | P49: 18446 | Q49: 18544 | R49: 19483 | S49: 9129 | T49: 0 | U49: 0 | V49: 0 | W49: =ROUND(표9[[#This Row],[Apr 2026 (USD or KRW)]],0) -> 0 | Y49: =표9[[#This Row],[Apr 2027(KRW)]]-표9[[#This Row],[Mar 2026(KRW)]] -> 0 | Z49: =IF(V49=0,"",(W49-V49)/V49) | AA49: =VLOOKUP(표9[[#This Row],[Team]],표1[],3,0) -> 1000
A50: =VLOOKUP($H50,AWS!$A:$H,2,0) -> AWS | B50: =VLOOKUP($H50,AWS!$A:$H,3,0) -> Neptune | C50: =VLOOKUP($H50,AWS!$A:$H,4,0) -> Neptune | D50: =VLOOKUP($H50,AWS!$A:$H,5,0) -> 0 | E50: =VLOOKUP($H50,AWS!$A:$H,6,0) -> 0 | F50: =VLOOKUP(표9[[#This Row],[Team]],표1[[내역]:[코스트 센터]],2,0) -> #N/A | G50: =VLOOKUP(표9[[#This Row],[Project]],표2[],2,0) -> #N/A | H50: aws_neptunez_001@neptunecompany.kr(225171097108) | I50: =VLOOKUP($H50,AWS!$A:$H,7,0) -> 0 | J50: =VLOOKUP($H50,AWS!$A:$H,8,0) -> 0 | N50: 2393615 | O50: 2224132 | P50: 2247661 | Q50: 2419923 | R50: 2414398 | S50: 2459171 | T50: 2362541 | U50: 2103906 | V50: 2412256 | W50: =ROUND(표9[[#This Row],[Apr 2026 (USD or KRW)]],0) -> 0 | Y50: =표9[[#This Row],[Apr 2027(KRW)]]-표9[[#This Row],[Mar 2026(KRW)]] -> -2412256 | Z50: =IF(V50=0,"",(W50-V50)/V50) -> -1 | AA50: =VLOOKUP(표9[[#This Row],[Team]],표1[],3,0) -> #N/A
A51: =VLOOKUP($H51,AWS!$A:$H,2,0) -> AWS | B51: =VLOOKUP($H51,AWS!$A:$H,3,0) -> Neptune | C51: =VLOOKUP($H51,AWS!$A:$H,4,0) -> Neptune | D51: =VLOOKUP($H51,AWS!$A:$H,5,0) -> 0 | E51: =VLOOKUP($H51,AWS!$A:$H,6,0) -> 0 | F51: =VLOOKUP(표9[[#This Row],[Team]],표1[[내역]:[코스트 센터]],2,0) -> #N/A | G51: =VLOOKUP(표9[[#This Row],[Project]],표2[],2,0) -> #N/A | H51: aws_neptunez_002@neptunecompany.kr(992306882093) | I51: =VLOOKUP($H51,AWS!$A:$H,7,0) -> 0 | J51: =VLOOKUP($H51,AWS!$A:$H,8,0) -> 0 | N51: 43983 | O51: 50701 | P51: 45451 | Q51: 47304 | R51: 47421 | S51: 47468 | T51: 46733 | U51: 45755 | V51: 49475 | W51: =ROUND(표9[[#This Row],[Apr 2026 (USD or KRW)]],0) -> 0 | Y51: =표9[[#This Row],[Apr 2027(KRW)]]-표9[[#This Row],[Mar 2026(KRW)]] -> -49475 | Z51: =IF(V51=0,"",(W51-V51)/V51) -> -1 | AA51: =VLOOKUP(표9[[#This Row],[Team]],표1[],3,0) -> #N/A
A52: =VLOOKUP($H52,AWS!$A:$H,2,0) -> AWS | B52: =VLOOKUP($H52,AWS!$A:$H,3,0) -> Neptune | C52: =VLOOKUP($H52,AWS!$A:$H,4,0) -> Neptune | D52: =VLOOKUP($H52,AWS!$A:$H,5,0) -> 0 | E52: =VLOOKUP($H52,AWS!$A:$H,6,0) -> 0 | F52: =VLOOKUP(표9[[#This Row],[Team]],표1[[내역]:[코스트 센터]],2,0) -> #N/A | G52: =VLOOKUP(표9[[#This Row],[Project]],표2[],2,0) -> #N/A | H52: aws_neptunez_003@neptunecompany.kr(470771986881) | I52: =VLOOKUP($H52,AWS!$A:$H,7,0) -> 0 | J52: =VLOOKUP($H52,AWS!$A:$H,8,0) -> 0 | N52: 708774 | O52: 707098 | P52: 689832 | Q52: 743266 | R52: 736703 | S52: 748435 | T52: 701507 | U52: 620618 | V52: 687530 | W52: =ROUND(표9[[#This Row],[Apr 2026 (USD or KRW)]],0) -> 0 | Y52: =표9[[#This Row],[Apr 2027(KRW)]]-표9[[#This Row],[Mar 2026(KRW)]] -> -687530 | Z52: =IF(V52=0,"",(W52-V52)/V52) -> -1 | AA52: =VLOOKUP(표9[[#This Row],[Team]],표1[],3,0) -> #N/A
A53: =VLOOKUP($H53,AWS!$A:$H,2,0) -> AWS | B53: =VLOOKUP($H53,AWS!$A:$H,3,0) -> Neptune | C53: =VLOOKUP($H53,AWS!$A:$H,4,0) -> Neptune | D53: =VLOOKUP($H53,AWS!$A:$H,5,0) -> 0 | E53: =VLOOKUP($H53,AWS!$A:$H,6,0) -> 0 | F53: =VLOOKUP(표9[[#This Row],[Team]],표1[[내역]:[코스트 센터]],2,0) -> #N/A | G53: =VLOOKUP(표9[[#This Row],[Project]],표2[],2,0) -> #N/A | H53: aws_neptunez_006@neptunecompany.kr(115255558787) | I53: =VLOOKUP($H53,AWS!$A:$H,7,0) -> 0 | J53: =VLOOKUP($H53,AWS!$A:$H,8,0) -> 0 | N53: 6659 | O53: 19074 | P53: 9966 | Q53: 10237 | R53: 9923 | S53: 156338 | T53: 233436 | U53: 145962 | V53: 264590 | W53: =ROUND(표9[[#This Row],[Apr 2026 (USD or KRW)]],0) -> 0 | Y53: =표9[[#This Row],[Apr 2027(KRW)]]-표9[[#This Row],[Mar 2026(KRW)]] -> -264590 | Z53: =IF(V53=0,"",(W53-V53)/V53) -> -1 | AA53: =VLOOKUP(표9[[#This Row],[Team]],표1[],3,0) -> #N/A
A54: =VLOOKUP($H54,AWS!$A:$H,2,0) -> AWS | B54: =VLOOKUP($H54,AWS!$A:$H,3,0) -> Neptune | C54: =VLOOKUP($H54,AWS!$A:$H,4,0) -> Neptune | D54: =VLOOKUP($H54,AWS!$A:$H,5,0) -> 0 | E54: =VLOOKUP($H54,AWS!$A:$H,6,0) -> 0 | F54: =VLOOKUP(표9[[#This Row],[Team]],표1[[내역]:[코스트 센터]],2,0) -> #N/A | G54: =VLOOKUP(표9[[#This Row],[Project]],표2[],2,0) -> #N/A | H54: aws_neptunez_007@neptunecompany.kr(619193641492) | I54: =VLOOKUP($H54,AWS!$A:$H,7,0) -> 0 | J54: =VLOOKUP($H54,AWS!$A:$H,8,0) -> 0 | N54: 10719927 | O54: 9616153 | P54: 8620189 | Q54: 10422163 | R54: 10184786 | S54: 10757638 | T54: 10336035 | U54: 9380767 | V54: 11252794 | W54: =ROUND(표9[[#This Row],[Apr 2026 (USD or KRW)]],0) -> 0 | Y54: =표9[[#This Row],[Apr 2027(KRW)]]-표9[[#This Row],[Mar 2026(KRW)]] -> -11252794 | Z54: =IF(V54=0,"",(W54-V54)/V54) -> -1 | AA54: =VLOOKUP(표9[[#This Row],[Team]],표1[],3,0) -> #N/A
A55: =VLOOKUP($H55,AWS!$A:$H,2,0) -> AWS | B55: =VLOOKUP($H55,AWS!$A:$H,3,0) -> Neptune | C55: =VLOOKUP($H55,AWS!$A:$H,4,0) -> Neptune | D55: =VLOOKUP($H55,AWS!$A:$H,5,0) -> 0 | E55: =VLOOKUP($H55,AWS!$A:$H,6,0) -> 0 | F55: =VLOOKUP(표9[[#This Row],[Team]],표1[[내역]:[코스트 센터]],2,0) -> #N/A | G55: =VLOOKUP(표9[[#This Row],[Project]],표2[],2,0) -> #N/A | H55: aws_neptunez_008@neptunecompany.kr(490136080242) | I55: =VLOOKUP($H55,AWS!$A:$H,7,0) -> 0 | J55: =VLOOKUP($H55,AWS!$A:$H,8,0) -> 0 | N55: 4696747 | O55: 1856183 | P55: 4683881 | Q55: 1927214 | R55: 1922466 | S55: 2024021 | T55: 11168121 | U55: 1807656 | V55: 2099874 | W55: =ROUND(표9[[#This Row],[Apr 2026 (USD or KRW)]],0) -> 0 | Y55: =표9[[#This Row],[Apr 2027(KRW)]]-표9[[#This Row],[Mar 2026(KRW)]] -> -2099874 | Z55: =IF(V55=0,"",(W55-V55)/V55) -> -1 | AA55: =VLOOKUP(표9[[#This Row],[Team]],표1[],3,0) -> #N/A
A56: =VLOOKUP($H56,AWS!$A:$H,2,0) -> AWS | B56: =VLOOKUP($H56,AWS!$A:$H,3,0) -> Neptune | C56: =VLOOKUP($H56,AWS!$A:$H,4,0) -> Neptune | D56: =VLOOKUP($H56,AWS!$A:$H,5,0) -> 0 | E56: =VLOOKUP($H56,AWS!$A:$H,6,0) -> 0 | F56: =VLOOKUP(표9[[#This Row],[Team]],표1[[내역]:[코스트 센터]],2,0) -> #N/A | G56: =VLOOKUP(표9[[#This Row],[Project]],표2[],2,0) -> #N/A | H56: aws_neptunez_009@neptunecompany.kr(566155726079) | I56: =VLOOKUP($H56,AWS!$A:$H,7,0) -> 0 | J56: =VLOOKUP($H56,AWS!$A:$H,8,0) -> 0 | N56: 1882623 | O56: 1907472 | P56: 1889046 | Q56: 1932963 | R56: 1981456 | S56: 1952861 | T56: 22386598 | U56: 1919682 | V56: 2062173 | W56: =ROUND(표9[[#This Row],[Apr 2026 (USD or KRW)]],0) -> 0 | Y56: =표9[[#This Row],[Apr 2027(KRW)]]-표9[[#This Row],[Mar 2026(KRW)]] -> -2062173 | Z56: =IF(V56=0,"",(W56-V56)/V56) -> -1 | AA56: =VLOOKUP(표9[[#This Row],[Team]],표1[],3,0) -> #N/A
A57: =VLOOKUP($H57,AWS!$A:$H,2,0) -> AWS | B57: =VLOOKUP($H57,AWS!$A:$H,3,0) -> Neptune | C57: =VLOOKUP($H57,AWS!$A:$H,4,0) -> Neptune | D57: =VLOOKUP($H57,AWS!$A:$H,5,0) -> 0 | E57: =VLOOKUP($H57,AWS!$A:$H,6,0) -> 0 | F57: =VLOOKUP(표9[[#This Row],[Team]],표1[[내역]:[코스트 센터]],2,0) -> #N/A | G57: =VLOOKUP(표9[[#This Row],[Project]],표2[],2,0) -> #N/A | H57: aws_neptunez_010@neptunecompany.kr(061838255935) | I57: =VLOOKUP($H57,AWS!$A:$H,7,0) -> 0 | J57: =VLOOKUP($H57,AWS!$A:$H,8,0) -> 0 | N57: 6117985 | O57: 6165927 | P57: 5994083 | Q57: 6308585 | R57: 6330290 | S57: 6350407 | T57: 6267648 | U57: 6601501 | V57: 9965451 | W57: =ROUND(표9[[#This Row],[Apr 2026 (USD or KRW)]],0) -> 0 | Y57: =표9[[#This Row],[Apr 2027(KRW)]]-표9[[#This Row],[Mar 2026(KRW)]] -> -9965451 | Z57: =IF(V57=0,"",(W57-V57)/V57) -> -1 | AA57: =VLOOKUP(표9[[#This Row],[Team]],표1[],3,0) -> #N/A
A58: =VLOOKUP($H58,AWS!$A:$H,2,0) -> AWS | B58: =VLOOKUP($H58,AWS!$A:$H,3,0) -> Neptune | C58: =VLOOKUP($H58,AWS!$A:$H,4,0) -> Neptune | D58: =VLOOKUP($H58,AWS!$A:$H,5,0) -> 0 | E58: =VLOOKUP($H58,AWS!$A:$H,6,0) -> 0 | F58: =VLOOKUP(표9[[#This Row],[Team]],표1[[내역]:[코스트 센터]],2,0) -> #N/A | G58: =VLOOKUP(표9[[#This Row],[Project]],표2[],2,0) -> #N/A | H58: aws_neptunez_011@neptunecompany.kr(026090535674) | I58: =VLOOKUP($H58,AWS!$A:$H,7,0) -> 0 | J58: =VLOOKUP($H58,AWS!$A:$H,8,0) -> 0 | N58: 67784 | O58: 76989 | P58: 68021 | Q58: 68041 | R58: 66366 | S58: 66982 | T58: 64505 | U58: 58502 | V58: 63383 | W58: =ROUND(표9[[#This Row],[Apr 2026 (USD or KRW)]],0) -> 0 | Y58: =표9[[#This Row],[Apr 2027(KRW)]]-표9[[#This Row],[Mar 2026(KRW)]] -> -63383 | Z58: =IF(V58=0,"",(W58-V58)/V58) -> -1 | AA58: =VLOOKUP(표9[[#This Row],[Team]],표1[],3,0) -> #N/A
A59: =VLOOKUP($H59,AWS!$A:$H,2,0) -> AWS | B59: =VLOOKUP($H59,AWS!$A:$H,3,0) -> Neptune | C59: =VLOOKUP($H59,AWS!$A:$H,4,0) -> Neptune | D59: =VLOOKUP($H59,AWS!$A:$H,5,0) -> 0 | E59: =VLOOKUP($H59,AWS!$A:$H,6,0) -> 0 | F59: =VLOOKUP(표9[[#This Row],[Team]],표1[[내역]:[코스트 센터]],2,0) -> #N/A | G59: =VLOOKUP(표9[[#This Row],[Project]],표2[],2,0) -> #N/A | H59: aws_neptunez_013@neptunecompany.kr(418272792542) | I59: =VLOOKUP($H59,AWS!$A:$H,7,0) -> 0 | J59: =VLOOKUP($H59,AWS!$A:$H,8,0) -> 0 | N59: 1461696 | O59: 1195494 | P59: 1165929 | Q59: 1075621 | R59: 673113 | S59: 672933 | T59: 651714 | U59: 609933 | V59: 672638 | W59: =ROUND(표9[[#This Row],[Apr 2026 (USD or KRW)]],0) -> 0 | Y59: =표9[[#This Row],[Apr 2027(KRW)]]-표9[[#This Row],[Mar 2026(KRW)]] -> -672638 | Z59: =IF(V59=0,"",(W59-V59)/V59) -> -1 | AA59: =VLOOKUP(표9[[#This Row],[Team]],표1[],3,0) -> #N/A
A60: =VLOOKUP($H60,AWS!$A:$H,2,0) -> AWS | B60: =VLOOKUP($H60,AWS!$A:$H,3,0) -> Neptune | C60: =VLOOKUP($H60,AWS!$A:$H,4,0) -> Neptune | D60: =VLOOKUP($H60,AWS!$A:$H,5,0) -> 0 | E60: =VLOOKUP($H60,AWS!$A:$H,6,0) -> 0 | F60: =VLOOKUP(표9[[#This Row],[Team]],표1[[내역]:[코스트 센터]],2,0) -> #N/A | G60: =VLOOKUP(표9[[#This Row],[Project]],표2[],2,0) -> #N/A | H60: aws_neptunez_014@neptunecompany.kr(050451361628) | I60: =VLOOKUP($H60,AWS!$A:$H,7,0) -> 0 | J60: =VLOOKUP($H60,AWS!$A:$H,8,0) -> 0 | N60: 85058 | O60: 184594 | P60: 185569 | Q60: 204224 | R60: 215941 | S60: 196261 | T60: 190910 | U60: 179280 | V60: 191178 | W60: =ROUND(표9[[#This Row],[Apr 2026 (USD or KRW)]],0) -> 0 | Y60: =표9[[#This Row],[Apr 2027(KRW)]]-표9[[#This Row],[Mar 2026(KRW)]] -> -191178 | Z60: =IF(V60=0,"",(W60-V60)/V60) -> -1 | AA60: =VLOOKUP(표9[[#This Row],[Team]],표1[],3,0) -> #N/A
A61: =VLOOKUP($H61,AWS!$A:$H,2,0) -> AWS | B61: =VLOOKUP($H61,AWS!$A:$H,3,0) -> Neptune | C61: =VLOOKUP($H61,AWS!$A:$H,4,0) -> Neptune | D61: =VLOOKUP($H61,AWS!$A:$H,5,0) -> 0 | E61: =VLOOKUP($H61,AWS!$A:$H,6,0) -> 0 | F61: =VLOOKUP(표9[[#This Row],[Team]],표1[[내역]:[코스트 센터]],2,0) -> #N/A | G61: =VLOOKUP(표9[[#This Row],[Project]],표2[],2,0) -> #N/A | H61: aws_neptunez_015@neptunecompany.kr(112554631631) | I61: =VLOOKUP($H61,AWS!$A:$H,7,0) -> 0 | J61: =VLOOKUP($H61,AWS!$A:$H,8,0) -> 0 | N61: 102146 | O61: 487316 | P61: 481770 | Q61: 451285 | R61: 2329481 | S61: 1254770 | T61: 669575 | U61: 4790372 | V61: 1277839 | W61: =ROUND(표9[[#This Row],[Apr 2026 (USD or KRW)]],0) -> 0 | Y61: =표9[[#This Row],[Apr 2027(KRW)]]-표9[[#This Row],[Mar 2026(KRW)]] -> -1277839 | Z61: =IF(V61=0,"",(W61-V61)/V61) -> -1 | AA61: =VLOOKUP(표9[[#This Row],[Team]],표1[],3,0) -> #N/A
A62: =VLOOKUP($H62,AWS!$A:$H,2,0) -> AWS | B62: =VLOOKUP($H62,AWS!$A:$H,3,0) -> Neptune | C62: =VLOOKUP($H62,AWS!$A:$H,4,0) -> Neptune | D62: =VLOOKUP($H62,AWS!$A:$H,5,0) -> 0 | E62: =VLOOKUP($H62,AWS!$A:$H,6,0) -> 0 | F62: =VLOOKUP(표9[[#This Row],[Team]],표1[[내역]:[코스트 센터]],2,0) -> #N/A | G62: =VLOOKUP(표9[[#This Row],[Project]],표2[],2,0) -> #N/A | H62: aws_neptunez_016@neptunecompany.kr(904331955654) | I62: =VLOOKUP($H62,AWS!$A:$H,7,0) -> 0 | J62: =VLOOKUP($H62,AWS!$A:$H,8,0) -> 0 | P62: 43206 | Q62: 134536 | R62: 139827 | S62: 145072 | T62: 146677 | U62: 181822 | V62: 312363 | W62: =ROUND(표9[[#This Row],[Apr 2026 (USD or KRW)]],0) -> 0 | Y62: =표9[[#This Row],[Apr 2027(KRW)]]-표9[[#This Row],[Mar 2026(KRW)]] -> -312363 | Z62: =IF(V62=0,"",(W62-V62)/V62) -> -1 | AA62: =VLOOKUP(표9[[#This Row],[Team]],표1[],3,0) -> #N/A
A63: =VLOOKUP($H63,AWS!$A:$H,2,0) -> AWS | B63: =VLOOKUP($H63,AWS!$A:$H,3,0) -> Neptune | C63: =VLOOKUP($H63,AWS!$A:$H,4,0) -> Neptune | D63: =VLOOKUP($H63,AWS!$A:$H,5,0) -> 0 | E63: =VLOOKUP($H63,AWS!$A:$H,6,0) -> 0 | F63: =VLOOKUP(표9[[#This Row],[Team]],표1[[내역]:[코스트 센터]],2,0) -> #N/A | G63: =VLOOKUP(표9[[#This Row],[Project]],표2[],2,0) -> #N/A | H63: aws_neptunez_017@neptunecompany.kr(048148187150) | J63: =VLOOKUP($H63,AWS!$A:$H,8,0) -> 0 | T63: 22081 | U63: 72433 | V63: 129765 | W63: =ROUND(표9[[#This Row],[Apr 2026 (USD or KRW)]],0) -> 0 | Y63: =표9[[#This Row],[Apr 2027(KRW)]]-표9[[#This Row],[Mar 2026(KRW)]] -> -129765 | Z63: =IF(V63=0,"",(W63-V63)/V63) -> -1 | AA63: =VLOOKUP(표9[[#This Row],[Team]],표1[],3,0) -> #N/A
A64: =VLOOKUP($H64,AWS!$A:$H,2,0) -> AWS | B64: =VLOOKUP($H64,AWS!$A:$H,3,0) -> Neptune | C64: =VLOOKUP($H64,AWS!$A:$H,4,0) -> Neptune | D64: =VLOOKUP($H64,AWS!$A:$H,5,0) -> 0 | E64: =VLOOKUP($H64,AWS!$A:$H,6,0) -> 0 | F64: =VLOOKUP(표9[[#This Row],[Team]],표1[[내역]:[코스트 센터]],2,0) -> #N/A | G64: =VLOOKUP(표9[[#This Row],[Project]],표2[],2,0) -> #N/A | H64: aws_neptunez_018@neptunecompany.kr(187383762797) | I64: =VLOOKUP($H64,AWS!$A:$H,7,0) -> 0 | J64: =VLOOKUP($H64,AWS!$A:$H,8,0) -> 0 | U64: 10870 | V64: 58593 | W64: =ROUND(표9[[#This Row],[Apr 2026 (USD or KRW)]],0) -> 0 | Y64: =표9[[#This Row],[Apr 2027(KRW)]]-표9[[#This Row],[Mar 2026(KRW)]] -> -58593 | Z64: =IF(V64=0,"",(W64-V64)/V64) -> -1 | AA64: =VLOOKUP(표9[[#This Row],[Team]],표1[],3,0) -> #N/A
A65: =VLOOKUP($H65,AWS!$A:$H,2,0) -> AWS | B65: =VLOOKUP($H65,AWS!$A:$H,3,0) -> OVERDARE | C65: =VLOOKUP($H65,AWS!$A:$H,4,0) -> OVERDARE | D65: =VLOOKUP($H65,AWS!$A:$H,5,0) -> SBX Platform Team | E65: =VLOOKUP($H65,AWS!$A:$H,6,0) -> OVERHEAD/OTHERS | F65: =VLOOKUP(표9[[#This Row],[Team]],표1[[내역]:[코스트 센터]],2,0) -> #N/A | G65: =VLOOKUP(표9[[#This Row],[Project]],표2[],2,0) -> I100099999 | H65: aws_nft_sbx_central@bluehole.net(768255055847) | I65: =VLOOKUP($H65,AWS!$A:$H,7,0) -> 이제우 | J65: =VLOOKUP($H65,AWS!$A:$H,8,0) -> 이제우 | L65: 17173427 | M65: 14722787 | N65: 16560861 | O65: 153771001 | P65: 15029004 | Q65: 15643639 | R65: 15361494 | S65: 14754268 | T65: 13537216 | U65: 10831839 | V65: 12843327 | W65: =ROUND(표9[[#This Row],[Apr 2026 (USD or KRW)]],0) -> 0 | Y65: =표9[[#This Row],[Apr 2027(KRW)]]-표9[[#This Row],[Mar 2026(KRW)]] -> -12843327 | Z65: =IF(V65=0,"",(W65-V65)/V65) -> -1 | AA65: =VLOOKUP(표9[[#This Row],[Team]],표1[],3,0) -> #N/A
A66: =VLOOKUP($H66,AWS!$A:$H,2,0) -> AWS | B66: =VLOOKUP($H66,AWS!$A:$H,3,0) -> OVERDARE | C66: =VLOOKUP($H66,AWS!$A:$H,4,0) -> OVERDARE | D66: =VLOOKUP($H66,AWS!$A:$H,5,0) -> OVDR Platform Engineering Team | E66: =VLOOKUP($H66,AWS!$A:$H,6,0) -> OVERHEAD/OTHERS | F66: =VLOOKUP(표9[[#This Row],[Team]],표1[[내역]:[코스트 센터]],2,0) -> 460005 | G66: =VLOOKUP(표9[[#This Row],[Project]],표2[],2,0) -> I100099999 | H66: aws_nft_sbx_dev@bluehole.net(833221979697) | I66: =VLOOKUP($H66,AWS!$A:$H,7,0) -> 이제우 | J66: =VLOOKUP($H66,AWS!$A:$H,8,0) -> 이제우 | L66: 5150060 | M66: 4942369 | N66: 6144990 | O66: 6043126 | P66: 6479336 | Q66: 6665285 | R66: 6204265 | S66: 6157569 | T66: 6727043 | U66: 4641130 | V66: 7097831 | W66: =ROUND(표9[[#This Row],[Apr 2026 (USD or KRW)]],0) -> 0 | Y66: =표9[[#This Row],[Apr 2027(KRW)]]-표9[[#This Row],[Mar 2026(KRW)]] -> -7097831 | Z66: =IF(V66=0,"",(W66-V66)/V66) -> -1 | AA66: =VLOOKUP(표9[[#This Row],[Team]],표1[],3,0) -> 4600
A67: =VLOOKUP($H67,AWS!$A:$H,2,0) -> AWS | B67: =VLOOKUP($H67,AWS!$A:$H,3,0) -> Neptune | C67: =VLOOKUP($H67,AWS!$A:$H,4,0) -> Neptune | D67: =VLOOKUP($H67,AWS!$A:$H,5,0) -> 0 | E67: =VLOOKUP($H67,AWS!$A:$H,6,0) -> 0 | F67: =VLOOKUP(표9[[#This Row],[Team]],표1[[내역]:[코스트 센터]],2,0) -> #N/A | G67: =VLOOKUP(표9[[#This Row],[Project]],표2[],2,0) -> #N/A | H67: aws_nimbleneuron_001@nimbleneuron.com(286122363201) | I67: =VLOOKUP($H67,AWS!$A:$H,7,0) -> 0 | J67: =VLOOKUP($H67,AWS!$A:$H,8,0) -> 0 | N67: 99247972 | O67: 100760033 | P67: 76062119 | Q67: 88483326 | R67: 94636395 | S67: 92578957 | T67: 93492141 | U67: 90426830 | V67: 102337466 | W67: =ROUND(표9[[#This Row],[Apr 2026 (USD or KRW)]],0) -> 0 | Y67: =표9[[#This Row],[Apr 2027(KRW)]]-표9[[#This Row],[Mar 2026(KRW)]] -> -102337466 | Z67: =IF(V67=0,"",(W67-V67)/V67) -> -1 | AA67: =VLOOKUP(표9[[#This Row],[Team]],표1[],3,0) -> #N/A
A68: =VLOOKUP($H68,AWS!$A:$H,2,0) -> AWS | B68: =VLOOKUP($H68,AWS!$A:$H,3,0) -> Neptune | C68: =VLOOKUP($H68,AWS!$A:$H,4,0) -> Neptune | D68: =VLOOKUP($H68,AWS!$A:$H,5,0) -> 0 | E68: =VLOOKUP($H68,AWS!$A:$H,6,0) -> 0 | F68: =VLOOKUP(표9[[#This Row],[Team]],표1[[내역]:[코스트 센터]],2,0) -> #N/A | G68: =VLOOKUP(표9[[#This Row],[Project]],표2[],2,0) -> #N/A | H68: aws_nimbleneuron_002@nimbleneuron.com(662873093770) | I68: =VLOOKUP($H68,AWS!$A:$H,7,0) -> 0 | J68: =VLOOKUP($H68,AWS!$A:$H,8,0) -> 0 | N68: 2385378 | O68: 1942929 | P68: 1751954 | Q68: 2469498 | R68: 1930848 | S68: 2286334 | T68: 2554566 | U68: 2070064 | V68: 2124815 | W68: =ROUND(표9[[#This Row],[Apr 2026 (USD or KRW)]],0) -> 0 | Y68: =표9[[#This Row],[Apr 2027(KRW)]]-표9[[#This Row],[Mar 2026(KRW)]] -> -2124815 | Z68: =IF(V68=0,"",(W68-V68)/V68) -> -1 | AA68: =VLOOKUP(표9[[#This Row],[Team]],표1[],3,0) -> #N/A
A69: =VLOOKUP($H69,AWS!$A:$H,2,0) -> AWS | B69: =VLOOKUP($H69,AWS!$A:$H,3,0) -> KRAFTON HQ | C69: =VLOOKUP($H69,AWS!$A:$H,4,0) -> PUBG STUDIO | D69: =VLOOKUP($H69,AWS!$A:$H,5,0) -> Black Budget Div. | E69: =VLOOKUP($H69,AWS!$A:$H,6,0) -> BLACK BUDGET | F69: =VLOOKUP(표9[[#This Row],[Team]],표1[[내역]:[코스트 센터]],2,0) -> 100829 | G69: =VLOOKUP(표9[[#This Row],[Project]],표2[],2,0) -> P100010048 | H69: aws_pbb_dev@bluehole.net(634885311994) | I69: =VLOOKUP($H69,AWS!$A:$H,8,0) -> 조원빈 | J69: =VLOOKUP($H69,AWS!$A:$H,8,0) -> 조원빈 | K69: v | L69: 36341246 | M69: 37748146 | N69: 45437913 | O69: 41810910 | P69: 36774849 | Q69: 42905643 | R69: 46810584 | S69: 68389359 | T69: 51534106 | U69: 47075699 | V69: 61773111 | W69: =ROUND(표9[[#This Row],[Apr 2026 (USD or KRW)]],0) -> 0 | Y69: =표9[[#This Row],[Apr 2027(KRW)]]-표9[[#This Row],[Mar 2026(KRW)]] -> -61773111 | Z69: =IF(V69=0,"",(W69-V69)/V69) -> -1 | AA69: =VLOOKUP(표9[[#This Row],[Team]],표1[],3,0) -> 1000
A70: =VLOOKUP($H70,AWS!$A:$H,2,0) -> AWS | B70: =VLOOKUP($H70,AWS!$A:$H,3,0) -> KRAFTON HQ | C70: =VLOOKUP($H70,AWS!$A:$H,4,0) -> PUBG STUDIO | D70: =VLOOKUP($H70,AWS!$A:$H,5,0) -> IT Dept. | E70: =VLOOKUP($H70,AWS!$A:$H,6,0) -> BLACK BUDGET | F70: =VLOOKUP(표9[[#This Row],[Team]],표1[[내역]:[코스트 센터]],2,0) -> 100036 | G70: =VLOOKUP(표9[[#This Row],[Project]],표2[],2,0) -> P100010048 | H70: aws_pbb_it@krafton.com(767398044467) | I70: =VLOOKUP($H70,AWS!$A:$H,8,0) -> 이윤슬 | J70: =VLOOKUP($H70,AWS!$A:$H,8,0) -> 이윤슬 | L70: 4867850 | M70: 10264584 | N70: 10601108 | O70: 20686391 | P70: 20956881 | Q70: 21975460 | R70: 22546217 | S70: 22059201 | T70: 21880021 | U70: 21741135 | V70: 23879504 | W70: =ROUND(표9[[#This Row],[Apr 2026 (USD or KRW)]],0) -> 0 | Y70: =표9[[#This Row],[Apr 2027(KRW)]]-표9[[#This Row],[Mar 2026(KRW)]] -> -23879504 | Z70: =IF(V70=0,"",(W70-V70)/V70) -> -1 | AA70: =VLOOKUP(표9[[#This Row],[Team]],표1[],3,0) -> 1000
A71: =VLOOKUP($H71,AWS!$A:$H,2,0) -> AWS | B71: =VLOOKUP($H71,AWS!$A:$H,3,0) -> KRAFTON HQ | C71: =VLOOKUP($H71,AWS!$A:$H,4,0) -> SDS | D71: =VLOOKUP($H71,AWS!$A:$H,5,0) -> Striking Distance Studios | E71: =VLOOKUP($H71,AWS!$A:$H,6,0) -> The Callisto Protocol | F71: =VLOOKUP(표9[[#This Row],[Team]],표1[[내역]:[코스트 센터]],2,0) -> 100561 | G71: =VLOOKUP(표9[[#This Row],[Project]],표2[],2,0) -> P100010013 | H71: AWS_Phoenix-Build@sds.com(245762466130) | I71: =VLOOKUP($H71,AWS!$A:$H,8,0) -> Jordan Yerkes | J71: =VLOOKUP($H71,AWS!$A:$H,8,0) -> Jordan Yerkes | L71: 1749001 | M71: 1676890 | N71: 1741987 | O71: 1688595 | P71: 1640992 | Q71: 1704249 | R71: 1724642 | S71: 1276463 | T71: 0 | U71: 0 | V71: 0 | W71: =ROUND(표9[[#This Row],[Apr 2026 (USD or KRW)]],0) -> 0 | Y71: =표9[[#This Row],[Apr 2027(KRW)]]-표9[[#This Row],[Mar 2026(KRW)]] -> 0 | Z71: =IF(V71=0,"",(W71-V71)/V71) | AA71: =VLOOKUP(표9[[#This Row],[Team]],표1[],3,0) -> 1000
A72: =VLOOKUP($H72,AWS!$A:$H,2,0) -> AWS | B72: =VLOOKUP($H72,AWS!$A:$H,3,0) -> KRAFTON HQ | C72: =VLOOKUP($H72,AWS!$A:$H,4,0) -> SDS | D72: =VLOOKUP($H72,AWS!$A:$H,5,0) -> Striking Distance Studios | E72: =VLOOKUP($H72,AWS!$A:$H,6,0) -> The Callisto Protocol | F72: =VLOOKUP(표9[[#This Row],[Team]],표1[[내역]:[코스트 센터]],2,0) -> 100561 | G72: =VLOOKUP(표9[[#This Row],[Project]],표2[],2,0) -> P100010013 | H72: AWS_Phoenix-Dev@sds.com(596361038250) | I72: =VLOOKUP($H72,AWS!$A:$H,8,0) -> Jordan Yerkes | J72: =VLOOKUP($H72,AWS!$A:$H,8,0) -> Jordan Yerkes | L72: 421074 | M72: 403501 | N72: 422217 | O72: 433785 | P72: 418167 | Q72: 438034 | R72: 441884 | S72: 241385 | T72: 0 | U72: 0 | V72: 0 | W72: =ROUND(표9[[#This Row],[Apr 2026 (USD or KRW)]],0) -> 0 | Y72: =표9[[#This Row],[Apr 2027(KRW)]]-표9[[#This Row],[Mar 2026(KRW)]] -> 0 | Z72: =IF(V72=0,"",(W72-V72)/V72) | AA72: =VLOOKUP(표9[[#This Row],[Team]],표1[],3,0) -> 1000
A73: =VLOOKUP($H73,AWS!$A:$H,2,0) -> AWS | B73: =VLOOKUP($H73,AWS!$A:$H,3,0) -> KRAFTON HQ | C73: =VLOOKUP($H73,AWS!$A:$H,4,0) -> SDS | D73: =VLOOKUP($H73,AWS!$A:$H,5,0) -> Striking Distance Studios | E73: =VLOOKUP($H73,AWS!$A:$H,6,0) -> The Callisto Protocol | F73: =VLOOKUP(표9[[#This Row],[Team]],표1[[내역]:[코스트 센터]],2,0) -> 100561 | G73: =VLOOKUP(표9[[#This Row],[Project]],표2[],2,0) -> P100010013 | H73: AWS_Phoenix-Live@sds.com(452304306221) | I73: =VLOOKUP($H73,AWS!$A:$H,8,0) -> Jordan Yerkes | J73: =VLOOKUP($H73,AWS!$A:$H,8,0) -> Jordan Yerkes | L73: 464019 | M73: 442939 | N73: 462346 | O73: 477250 | P73: 459921 | Q73: 480817 | R73: 485882 | S73: 344447 | T73: 0 | U73: 0 | V73: 0 | W73: =ROUND(표9[[#This Row],[Apr 2026 (USD or KRW)]],0) -> 0 | Y73: =표9[[#This Row],[Apr 2027(KRW)]]-표9[[#This Row],[Mar 2026(KRW)]] -> 0 | Z73: =IF(V73=0,"",(W73-V73)/V73) | AA73: =VLOOKUP(표9[[#This Row],[Team]],표1[],3,0) -> 1000
A74: =VLOOKUP($H74,AWS!$A:$H,2,0) -> AWS | B74: =VLOOKUP($H74,AWS!$A:$H,3,0) -> KRAFTON HQ | C74: =VLOOKUP($H74,AWS!$A:$H,4,0) -> SDS | D74: =VLOOKUP($H74,AWS!$A:$H,5,0) -> Striking Distance Studios | E74: =VLOOKUP($H74,AWS!$A:$H,6,0) -> The Callisto Protocol | F74: =VLOOKUP(표9[[#This Row],[Team]],표1[[내역]:[코스트 센터]],2,0) -> 100561 | G74: =VLOOKUP(표9[[#This Row],[Project]],표2[],2,0) -> P100010013 | H74: AWS_Phoenix-Prod@sds.com(878436247507) | I74: =VLOOKUP($H74,AWS!$A:$H,8,0) -> Jordan Yerkes | J74: =VLOOKUP($H74,AWS!$A:$H,8,0) -> Jordan Yerkes | L74: 17111 | M74: 5497 | N74: 5587 | O74: 11651 | P74: 8717 | Q74: 9143 | R74: 9956 | S74: 6891 | T74: 0 | U74: 0 | V74: 0 | W74: =ROUND(표9[[#This Row],[Apr 2026 (USD or KRW)]],0) -> 0 | Y74: =표9[[#This Row],[Apr 2027(KRW)]]-표9[[#This Row],[Mar 2026(KRW)]] -> 0 | Z74: =IF(V74=0,"",(W74-V74)/V74) | AA74: =VLOOKUP(표9[[#This Row],[Team]],표1[],3,0) -> 1000
A75: =VLOOKUP($H75,AWS!$A:$H,2,0) -> AWS | B75: =VLOOKUP($H75,AWS!$A:$H,3,0) -> KRAFTON HQ | C75: =VLOOKUP($H75,AWS!$A:$H,4,0) -> KRAFTON HQ | D75: =VLOOKUP($H75,AWS!$A:$H,5,0) -> Game Security Engineering Dept. | E75: =VLOOKUP($H75,AWS!$A:$H,6,0) -> BATTLEGROUNDS_PC/CONSOLE | F75: =VLOOKUP(표9[[#This Row],[Team]],표1[[내역]:[코스트 센터]],2,0) -> 100415 | G75: =VLOOKUP(표9[[#This Row],[Project]],표2[],2,0) -> P100010012 | H75: aws_pubg_anticheat_service@bluehole.net(843438412681) | I75: =VLOOKUP($H75,AWS!$A:$H,8,0) -> 황범석 | J75: =VLOOKUP($H75,AWS!$A:$H,8,0) -> 황범석 | K75: v | L75: 58517804 | M75: 58986691 | N75: 66751810 | O75: 69921937 | P75: 64748446 | Q75: 68843344 | R75: 68664593 | S75: 71296717 | T75: 73708695 | U75: 63509523 | V75: 82532834 | W75: =ROUND(표9[[#This Row],[Apr 2026 (USD or KRW)]],0) -> 0 | Y75: =표9[[#This Row],[Apr 2027(KRW)]]-표9[[#This Row],[Mar 2026(KRW)]] -> -82532834 | Z75: =IF(V75=0,"",(W75-V75)/V75) -> -1 | AA75: =VLOOKUP(표9[[#This Row],[Team]],표1[],3,0) -> 1000
A76: =VLOOKUP($H76,AWS!$A:$H,2,0) -> AWS | B76: =VLOOKUP($H76,AWS!$A:$H,3,0) -> KRAFTON HQ | C76: =VLOOKUP($H76,AWS!$A:$H,4,0) -> KRAFTON HQ | D76: =VLOOKUP($H76,AWS!$A:$H,5,0) -> Platform Dept. | E76: =VLOOKUP($H76,AWS!$A:$H,6,0) -> BATTLEGROUNDS_PC/CONSOLE | F76: =VLOOKUP(표9[[#This Row],[Team]],표1[[내역]:[코스트 센터]],2,0) -> 100355 | G76: =VLOOKUP(표9[[#This Row],[Project]],표2[],2,0) -> P100010012 | H76: aws_pubg_platform@bluehole.net(017103636613) | I76: =VLOOKUP($H76,AWS!$A:$H,8,0) -> 최준석 | J76: =VLOOKUP($H76,AWS!$A:$H,8,0) -> 최준석 | L76: 4752091 | M76: 4466014 | N76: 4570841 | O76: 4437309 | P76: 4379762 | Q76: 4801060 | R76: 5447512 | S76: 5817327 | T76: 5718803 | U76: 5370644 | V76: 6520159 | W76: =ROUND(표9[[#This Row],[Apr 2026 (USD or KRW)]],0) -> 0 | Y76: =표9[[#This Row],[Apr 2027(KRW)]]-표9[[#This Row],[Mar 2026(KRW)]] -> -6520159 | Z76: =IF(V76=0,"",(W76-V76)/V76) -> -1 | AA76: =VLOOKUP(표9[[#This Row],[Team]],표1[],3,0) -> 1000
A77: =VLOOKUP($H77,AWS!$A:$H,2,0) -> AWS | B77: =VLOOKUP($H77,AWS!$A:$H,3,0) -> KRAFTON HQ | C77: =VLOOKUP($H77,AWS!$A:$H,4,0) -> KRAFTON HQ | D77: =VLOOKUP($H77,AWS!$A:$H,5,0) -> Game Security Engineering Dept. | E77: =VLOOKUP($H77,AWS!$A:$H,6,0) -> OVERHEAD/OTHERS | F77: =VLOOKUP(표9[[#This Row],[Team]],표1[[내역]:[코스트 센터]],2,0) -> 100415 | G77: =VLOOKUP(표9[[#This Row],[Project]],표2[],2,0) -> I100099999 | H77: aws_pubg-anticheat@bluehole.net(480544169436) | I77: =VLOOKUP($H77,AWS!$A:$H,8,0) -> 황범석 | J77: =VLOOKUP($H77,AWS!$A:$H,8,0) -> 황범석 | K77: v | L77: 1377783 | M77: 1342159 | N77: 1540954 | O77: 1580684 | P77: 1592223 | Q77: 1654932 | R77: 3777389 | S77: 5182210 | T77: 4797217 | U77: 4049411 | V77: 2419881 | W77: =ROUND(표9[[#This Row],[Apr 2026 (USD or KRW)]],0) -> 0 | Y77: =표9[[#This Row],[Apr 2027(KRW)]]-표9[[#This Row],[Mar 2026(KRW)]] -> -2419881 | Z77: =IF(V77=0,"",(W77-V77)/V77) -> -1 | AA77: =VLOOKUP(표9[[#This Row],[Team]],표1[],3,0) -> 1000
A78: =VLOOKUP($H78,AWS!$A:$H,2,0) -> AWS | B78: =VLOOKUP($H78,AWS!$A:$H,3,0) -> KRAFTON HQ | C78: =VLOOKUP($H78,AWS!$A:$H,4,0) -> PUBG STUDIO | D78: =VLOOKUP($H78,AWS!$A:$H,5,0) -> MS DevOps Team | E78: =VLOOKUP($H78,AWS!$A:$H,6,0) -> OVERHEAD/OTHERS | F78: =VLOOKUP(표9[[#This Row],[Team]],표1[[내역]:[코스트 센터]],2,0) -> 100774 | G78: =VLOOKUP(표9[[#This Row],[Project]],표2[],2,0) -> I100099999 | H78: aws_pubg-arc-project@pubg.com(730335195506) | I78: =VLOOKUP($H78,AWS!$A:$H,8,0) -> 최보성 | J78: =VLOOKUP($H78,AWS!$A:$H,8,0) -> 최보성 | K78: v | L78: 18680493 | M78: 16088647 | N78: 15572834 | O78: 38703979 | P78: 13157917 | Q78: 11536552 | R78: 11479617 | S78: 14547767 | T78: 13646510 | U78: 6455869 | V78: 7077408 | W78: =ROUND(표9[[#This Row],[Apr 2026 (USD or KRW)]],0) -> 0 | Y78: =표9[[#This Row],[Apr 2027(KRW)]]-표9[[#This Row],[Mar 2026(KRW)]] -> -7077408 | Z78: =IF(V78=0,"",(W78-V78)/V78) -> -1 | AA78: =VLOOKUP(표9[[#This Row],[Team]],표1[],3,0) -> 1000
A79: =VLOOKUP($H79,AWS!$A:$H,2,0) -> AWS | B79: =VLOOKUP($H79,AWS!$A:$H,3,0) -> KRAFTON HQ | C79: =VLOOKUP($H79,AWS!$A:$H,4,0) -> PUBG STUDIO | D79: =VLOOKUP($H79,AWS!$A:$H,5,0) -> PUBG PC&Console Dev Div. | E79: =VLOOKUP($H79,AWS!$A:$H,6,0) -> BATTLEGROUNDS_PC/CONSOLE | F79: =VLOOKUP(표9[[#This Row],[Team]],표1[[내역]:[코스트 센터]],2,0) -> 100414 | G79: =VLOOKUP(표9[[#This Row],[Project]],표2[],2,0) -> P100010012 | H79: AWS_pubg-dev@pubg.com(423068853949) | I79: =VLOOKUP($H79,AWS!$A:$H,8,0) -> 최준석 | J79: =VLOOKUP($H79,AWS!$A:$H,8,0) -> 최준석 | L79: 312515855 | M79: 329158611 | N79: 404531909 | O79: 403926585 | P79: 467304989 | Q79: 526362766 | R79: 601252156 | S79: 688362735 | T79: 557711188 | U79: 492471628 | V79: 595148736 | W79: =ROUND(표9[[#This Row],[Apr 2026 (USD or KRW)]],0) -> 0 | Y79: =표9[[#This Row],[Apr 2027(KRW)]]-표9[[#This Row],[Mar 2026(KRW)]] -> -595148736 | Z79: =IF(V79=0,"",(W79-V79)/V79) -> -1 | AA79: =VLOOKUP(표9[[#This Row],[Team]],표1[],3,0) -> 1000
A80: =VLOOKUP($H80,AWS!$A:$H,2,0) -> AWS | B80: =VLOOKUP($H80,AWS!$A:$H,3,0) -> KRAFTON HQ | C80: =VLOOKUP($H80,AWS!$A:$H,4,0) -> PUBG STUDIO | D80: =VLOOKUP($H80,AWS!$A:$H,5,0) -> Platform Dept. | E80: =VLOOKUP($H80,AWS!$A:$H,6,0) -> BATTLEGROUNDS_PC/CONSOLE | F80: =VLOOKUP(표9[[#This Row],[Team]],표1[[내역]:[코스트 센터]],2,0) -> 100355 | G80: =VLOOKUP(표9[[#This Row],[Project]],표2[],2,0) -> P100010012 | H80: aws_pubg-devops@bluehole.net(974771722734) | I80: =VLOOKUP($H80,AWS!$A:$H,8,0) -> 최준석 | J80: =VLOOKUP($H80,AWS!$A:$H,8,0) -> 최준석 | L80: 23582306 | M80: 22009625 | N80: 23519917 | O80: 23654972 | P80: 23464410 | Q80: 26023327 | R80: 26218175 | S80: 28490889 | T80: 25774592 | U80: 23049305 | V80: 27776004 | W80: =ROUND(표9[[#This Row],[Apr 2026 (USD or KRW)]],0) -> 0 | Y80: =표9[[#This Row],[Apr 2027(KRW)]]-표9[[#This Row],[Mar 2026(KRW)]] -> -27776004 | Z80: =IF(V80=0,"",(W80-V80)/V80) -> -1 | AA80: =VLOOKUP(표9[[#This Row],[Team]],표1[],3,0) -> 1000
A81: =VLOOKUP($H81,AWS!$A:$H,2,0) -> AWS | B81: =VLOOKUP($H81,AWS!$A:$H,3,0) -> KRAFTON HQ | C81: =VLOOKUP($H81,AWS!$A:$H,4,0) -> PUBG STUDIO | D81: =VLOOKUP($H81,AWS!$A:$H,5,0) -> PUBG PC&Console Dev Div. | E81: =VLOOKUP($H81,AWS!$A:$H,6,0) -> BATTLEGROUNDS_PC/CONSOLE | F81: =VLOOKUP(표9[[#This Row],[Team]],표1[[내역]:[코스트 센터]],2,0) -> 100414 | G81: =VLOOKUP(표9[[#This Row],[Project]],표2[],2,0) -> P100010012 | H81: AWS_pubg-Esports@pubg.com(054649872353) | I81: =VLOOKUP($H81,AWS!$A:$H,8,0) -> 최준석 | J81: =VLOOKUP($H81,AWS!$A:$H,8,0) -> 최준석 | L81: 45853707 | M81: 42158618 | N81: 45045851 | O81: 44344802 | P81: 43448123 | Q81: 47003015 | R81: 45493075 | S81: 48448779 | T81: 45265114 | U81: 35569694 | V81: 37856008 | W81: =ROUND(표9[[#This Row],[Apr 2026 (USD or KRW)]],0) -> 0 | Y81: =표9[[#This Row],[Apr 2027(KRW)]]-표9[[#This Row],[Mar 2026(KRW)]] -> -37856008 | Z81: =IF(V81=0,"",(W81-V81)/V81) -> -1 | AA81: =VLOOKUP(표9[[#This Row],[Team]],표1[],3,0) -> 1000
A82: =VLOOKUP($H82,AWS!$A:$H,2,0) -> AWS | B82: =VLOOKUP($H82,AWS!$A:$H,3,0) -> KRAFTON HQ | C82: =VLOOKUP($H82,AWS!$A:$H,4,0) -> KRAFTON HQ | D82: =VLOOKUP($H82,AWS!$A:$H,5,0) -> Service DevOps Team | E82: =VLOOKUP($H82,AWS!$A:$H,6,0) -> BATTLEGROUNDS_PC/CONSOLE | F82: =VLOOKUP(표9[[#This Row],[Team]],표1[[내역]:[코스트 센터]],2,0) -> 100033 | G82: =VLOOKUP(표9[[#This Row],[Project]],표2[],2,0) -> P100010012 | H82: AWS_PUBG-F2Pweblive@pubg.com(033775294411) | I82: =VLOOKUP($H82,AWS!$A:$H,8,0) -> 엄기성 | J82: =VLOOKUP($H82,AWS!$A:$H,8,0) -> 엄기성 | L82: 9905226 | M82: 8724022 | N82: 13378227 | O82: 11374059 | P82: 12672283 | Q82: 12429577 | R82: 10968733 | S82: 15230796 | T82: 10181633 | U82: 7423344 | V82: 8620454 | W82: =ROUND(표9[[#This Row],[Apr 2026 (USD or KRW)]],0) -> 0 | Y82: =표9[[#This Row],[Apr 2027(KRW)]]-표9[[#This Row],[Mar 2026(KRW)]] -> -8620454 | Z82: =IF(V82=0,"",(W82-V82)/V82) -> -1 | AA82: =VLOOKUP(표9[[#This Row],[Team]],표1[],3,0) -> 1000
A83: =VLOOKUP($H83,AWS!$A:$H,2,0) -> AWS | B83: =VLOOKUP($H83,AWS!$A:$H,3,0) -> KRAFTON HQ | C83: =VLOOKUP($H83,AWS!$A:$H,4,0) -> PUBG STUDIO | D83: =VLOOKUP($H83,AWS!$A:$H,5,0) -> Data Engineering Dept. | E83: =VLOOKUP($H83,AWS!$A:$H,6,0) -> BATTLEGROUNDS_PC/CONSOLE | F83: =VLOOKUP(표9[[#This Row],[Team]],표1[[내역]:[코스트 센터]],2,0) -> 100212 | G83: =VLOOKUP(표9[[#This Row],[Project]],표2[],2,0) -> P100010012 | H83: AWS_pubg-Gcoin@pubg.com(804173125569) | I83: =VLOOKUP($H83,AWS!$A:$H,8,0) -> 김시훈 | J83: =VLOOKUP($H83,AWS!$A:$H,8,0) -> 김시훈 | K83: v | L83: 46980600 | M83: 46614275 | N83: 44201032 | O83: 44813477 | P83: 44567698 | Q83: 46351173 | R83: 46981230 | S83: 46822296 | T83: 46386799 | U83: 44982288 | V83: 49193633 | W83: =ROUND(표9[[#This Row],[Apr 2026 (USD or KRW)]],0) -> 0 | Y83: =표9[[#This Row],[Apr 2027(KRW)]]-표9[[#This Row],[Mar 2026(KRW)]] -> -49193633 | Z83: =IF(V83=0,"",(W83-V83)/V83) -> -1 | AA83: =VLOOKUP(표9[[#This Row],[Team]],표1[],3,0) -> 1000
A84: =VLOOKUP($H84,AWS!$A:$H,2,0) -> AWS | B84: =VLOOKUP($H84,AWS!$A:$H,3,0) -> KRAFTON HQ | C84: =VLOOKUP($H84,AWS!$A:$H,4,0) -> PUBG STUDIO | D84: =VLOOKUP($H84,AWS!$A:$H,5,0) -> PUBG PC&Console Dev Div. | E84: =VLOOKUP($H84,AWS!$A:$H,6,0) -> BATTLEGROUNDS_PC/CONSOLE | F84: =VLOOKUP(표9[[#This Row],[Team]],표1[[내역]:[코스트 센터]],2,0) -> 100414 | G84: =VLOOKUP(표9[[#This Row],[Project]],표2[],2,0) -> P100010012 | H84: AWS_pubg-playground@pubg.com(338204589111) | I84: =VLOOKUP($H84,AWS!$A:$H,8,0) -> 최준석 | J84: =VLOOKUP($H84,AWS!$A:$H,8,0) -> 최준석 | L84: 10975803 | M84: 11894295 | N84: 9013930 | O84: 6221276 | P84: 5782838 | Q84: 5417598 | R84: 3794818 | S84: 3784720 | T84: 3625689 | U84: 6225816 | V84: 3617606 | W84: =ROUND(표9[[#This Row],[Apr 2026 (USD or KRW)]],0) -> 0 | Y84: =표9[[#This Row],[Apr 2027(KRW)]]-표9[[#This Row],[Mar 2026(KRW)]] -> -3617606 | Z84: =IF(V84=0,"",(W84-V84)/V84) -> -1 | AA84: =VLOOKUP(표9[[#This Row],[Team]],표1[],3,0) -> 1000
A85: =VLOOKUP($H85,AWS!$A:$H,2,0) -> AWS | B85: =VLOOKUP($H85,AWS!$A:$H,3,0) -> KRAFTON HQ | C85: =VLOOKUP($H85,AWS!$A:$H,4,0) -> KRAFTON HQ | D85: =VLOOKUP($H85,AWS!$A:$H,5,0) -> Service DevOps Team | E85: =VLOOKUP($H85,AWS!$A:$H,6,0) -> BATTLEGROUNDS_MOBILE | F85: =VLOOKUP(표9[[#This Row],[Team]],표1[[내역]:[코스트 센터]],2,0) -> 100033 | G85: =VLOOKUP(표9[[#This Row],[Project]],표2[],2,0) -> P100030012 | H85: AWS_PUBGM-Esports-Live@krafton.com(633237459216) | I85: =VLOOKUP($H85,AWS!$A:$H,8,0) -> 엄기성 | J85: =VLOOKUP($H85,AWS!$A:$H,8,0) -> 엄기성 | L85: 10423391 | M85: 9764556 | N85: 10328787 | O85: 10327030 | P85: 10369678 | Q85: 10827077 | R85: 8600317 | S85: 8758181 | T85: 8411288 | U85: 7355445 | V85: 8749873 | W85: =ROUND(표9[[#This Row],[Apr 2026 (USD or KRW)]],0) -> 0 | Y85: =표9[[#This Row],[Apr 2027(KRW)]]-표9[[#This Row],[Mar 2026(KRW)]] -> -8749873 | Z85: =IF(V85=0,"",(W85-V85)/V85) -> -1 | AA85: =VLOOKUP(표9[[#This Row],[Team]],표1[],3,0) -> 1000
A86: =VLOOKUP($H86,AWS!$A:$H,2,0) -> AWS | B86: =VLOOKUP($H86,AWS!$A:$H,3,0) -> ReLu Games | C86: =VLOOKUP($H86,AWS!$A:$H,4,0) -> ReLu Games | D86: =VLOOKUP($H86,AWS!$A:$H,5,0) -> ReLU Dev Dept. | E86: =VLOOKUP($H86,AWS!$A:$H,6,0) -> OVERHEAD/OTHERS | F86: =VLOOKUP(표9[[#This Row],[Team]],표1[[내역]:[코스트 센터]],2,0) -> #N/A | G86: =VLOOKUP(표9[[#This Row],[Project]],표2[],2,0) -> I100099999 | H86: aws_relugames@bluehole.net(309943519623) | I86: =VLOOKUP($H86,AWS!$A:$H,7,0) -> 오준석 | J86: =VLOOKUP($H86,AWS!$A:$H,8,0) -> 오준석 | L86: 2631381 | M86: 3755918 | N86: 3283790 | O86: 3361723 | P86: 3316128 | Q86: 4121836 | R86: 4631290 | S86: 4520208 | T86: 4127065 | U86: 3489944 | V86: 4321971 | W86: =ROUND(표9[[#This Row],[Apr 2026 (USD or KRW)]],0) -> 0 | Y86: =표9[[#This Row],[Apr 2027(KRW)]]-표9[[#This Row],[Mar 2026(KRW)]] -> -4321971 | Z86: =IF(V86=0,"",(W86-V86)/V86) -> -1 | AA86: =VLOOKUP(표9[[#This Row],[Team]],표1[],3,0) -> #N/A
A87: =VLOOKUP($H87,AWS!$A:$H,2,0) -> AWS | B87: =VLOOKUP($H87,AWS!$A:$H,3,0) -> Risingwings | C87: =VLOOKUP($H87,AWS!$A:$H,4,0) -> Risingwings | D87: =VLOOKUP($H87,AWS!$A:$H,5,0) -> RW Tech Support Dept. | E87: =VLOOKUP($H87,AWS!$A:$H,6,0) -> 0 | F87: =VLOOKUP(표9[[#This Row],[Team]],표1[[내역]:[코스트 센터]],2,0) -> #N/A | G87: =VLOOKUP(표9[[#This Row],[Project]],표2[],2,0) -> #N/A | H87: AWS_RF-global@risingwings.com(260910532074) | I87: =VLOOKUP($H87,AWS!$A:$H,7,0) -> 허지웅 | J87: =VLOOKUP($H87,AWS!$A:$H,8,0) -> 허지웅 | L87: 58056 | M87: 67117 | N87: 57527 | O87: 73685 | P87: 71744 | Q87: 73193 | R87: 71790 | S87: 67361 | T87: 69635 | U87: 67109 | V87: 68685 | W87: =ROUND(표9[[#This Row],[Apr 2026 (USD or KRW)]],0) -> 0 | Y87: =표9[[#This Row],[Apr 2027(KRW)]]-표9[[#This Row],[Mar 2026(KRW)]] -> -68685 | Z87: =IF(V87=0,"",(W87-V87)/V87) -> -1 | AA87: =VLOOKUP(표9[[#This Row],[Team]],표1[],3,0) -> #N/A
A88: =VLOOKUP($H88,AWS!$A:$H,2,0) -> AWS | B88: =VLOOKUP($H88,AWS!$A:$H,3,0) -> KRAFTON HQ | C88: =VLOOKUP($H88,AWS!$A:$H,4,0) -> SDS | D88: =VLOOKUP($H88,AWS!$A:$H,5,0) -> Striking Distance Studios | E88: =VLOOKUP($H88,AWS!$A:$H,6,0) -> The Callisto Protocol | F88: =VLOOKUP(표9[[#This Row],[Team]],표1[[내역]:[코스트 센터]],2,0) -> 100561 | G88: =VLOOKUP(표9[[#This Row],[Project]],표2[],2,0) -> P100010013 | H88: AWS_SDS-DevOps@sds.com(290246912864) | I88: =VLOOKUP($H88,AWS!$A:$H,8,0) -> Jordan Yerkes | J88: =VLOOKUP($H88,AWS!$A:$H,8,0) -> Jordan Yerkes | L88: 13038481 | M88: 12588478 | N88: 13305868 | O88: 9888008 | P88: 9120766 | Q88: 10123189 | R88: 9726249 | S88: 9985811 | T88: 11357403 | U88: 9111993 | V88: 9069298 | W88: =ROUND(표9[[#This Row],[Apr 2026 (USD or KRW)]],0) -> 0 | Y88: =표9[[#This Row],[Apr 2027(KRW)]]-표9[[#This Row],[Mar 2026(KRW)]] -> -9069298 | Z88: =IF(V88=0,"",(W88-V88)/V88) -> -1 | AA88: =VLOOKUP(표9[[#This Row],[Team]],표1[],3,0) -> 1000
A89: =VLOOKUP($H89,AWS!$A:$H,2,0) -> AWS | B89: =VLOOKUP($H89,AWS!$A:$H,3,0) -> KRAFTON HQ | C89: =VLOOKUP($H89,AWS!$A:$H,4,0) -> SDS | D89: =VLOOKUP($H89,AWS!$A:$H,5,0) -> Striking Distance Studios | E89: =VLOOKUP($H89,AWS!$A:$H,6,0) -> The Callisto Protocol | F89: =VLOOKUP(표9[[#This Row],[Team]],표1[[내역]:[코스트 센터]],2,0) -> 100561 | G89: =VLOOKUP(표9[[#This Row],[Project]],표2[],2,0) -> P100010013 | H89: AWS_SDS-Infra@sds.com(375608835244) | I89: =VLOOKUP($H89,AWS!$A:$H,8,0) -> Jordan Yerkes | J89: =VLOOKUP($H89,AWS!$A:$H,8,0) -> Jordan Yerkes | L89: 13893 | M89: 7081 | N89: 7161 | O89: 13590 | P89: 11093 | Q89: 11591 | R89: 11711 | S89: 10696 | T89: 12673 | U89: 10998 | V89: 9759 | W89: =ROUND(표9[[#This Row],[Apr 2026 (USD or KRW)]],0) -> 0 | Y89: =표9[[#This Row],[Apr 2027(KRW)]]-표9[[#This Row],[Mar 2026(KRW)]] -> -9759 | Z89: =IF(V89=0,"",(W89-V89)/V89) -> -1 | AA89: =VLOOKUP(표9[[#This Row],[Team]],표1[],3,0) -> 1000
A90: =VLOOKUP($H90,AWS!$A:$H,2,0) -> AWS | B90: =VLOOKUP($H90,AWS!$A:$H,3,0) -> KRAFTON HQ | C90: =VLOOKUP($H90,AWS!$A:$H,4,0) -> SDS | D90: =VLOOKUP($H90,AWS!$A:$H,5,0) -> Striking Distance Studios | E90: =VLOOKUP($H90,AWS!$A:$H,6,0) -> The Callisto Protocol | F90: =VLOOKUP(표9[[#This Row],[Team]],표1[[내역]:[코스트 센터]],2,0) -> 100561 | G90: =VLOOKUP(표9[[#This Row],[Project]],표2[],2,0) -> P100010013 | H90: aws_sds-security@bluehole.net(667131346962) | I90: =VLOOKUP($H90,AWS!$A:$H,8,0) -> Jordan Yerkes | J90: =VLOOKUP($H90,AWS!$A:$H,8,0) -> Jordan Yerkes | L90: 6643 | M90: 5374 | N90: 5561 | O90: 17179 | P90: 9089 | Q90: 9017 | R90: 9846 | S90: 8701 | T90: 10665 | U90: 9201 | V90: 7963 | W90: =ROUND(표9[[#This Row],[Apr 2026 (USD or KRW)]],0) -> 0 | Y90: =표9[[#This Row],[Apr 2027(KRW)]]-표9[[#This Row],[Mar 2026(KRW)]] -> -7963 | Z90: =IF(V90=0,"",(W90-V90)/V90) -> -1 | AA90: =VLOOKUP(표9[[#This Row],[Team]],표1[],3,0) -> 1000
A91: =VLOOKUP($H91,AWS!$A:$H,2,0) -> AWS | B91: =VLOOKUP($H91,AWS!$A:$H,3,0) -> KRAFTON HQ | C91: =VLOOKUP($H91,AWS!$A:$H,4,0) -> SDS | D91: =VLOOKUP($H91,AWS!$A:$H,5,0) -> Striking Distance Studios | E91: =VLOOKUP($H91,AWS!$A:$H,6,0) -> The Callisto Protocol | F91: =VLOOKUP(표9[[#This Row],[Team]],표1[[내역]:[코스트 센터]],2,0) -> 100561 | G91: =VLOOKUP(표9[[#This Row],[Project]],표2[],2,0) -> P100010013 | H91: AWS_SDS-VDI@sds.com(956486919325) | I91: =VLOOKUP($H91,AWS!$A:$H,8,0) -> Jordan Yerkes | J91: =VLOOKUP($H91,AWS!$A:$H,8,0) -> Jordan Yerkes | L91: 12405 | M91: 5522 | N91: 5587 | O91: 3201 | S91: 0 | T91: 0 | U91: 0 | V91: 0 | W91: =ROUND(표9[[#This Row],[Apr 2026 (USD or KRW)]],0) -> 0 | Y91: =표9[[#This Row],[Apr 2027(KRW)]]-표9[[#This Row],[Mar 2026(KRW)]] -> 0 | Z91: =IF(V91=0,"",(W91-V91)/V91) | AA91: =VLOOKUP(표9[[#This Row],[Team]],표1[],3,0) -> 1000
A92: =VLOOKUP($H92,AWS!$A:$H,2,0) -> AWS | B92: =VLOOKUP($H92,AWS!$A:$H,3,0) -> KRAFTON HQ | C92: =VLOOKUP($H92,AWS!$A:$H,4,0) -> SDS | D92: =VLOOKUP($H92,AWS!$A:$H,5,0) -> Striking Distance Studios | E92: =VLOOKUP($H92,AWS!$A:$H,6,0) -> The Callisto Protocol | F92: =VLOOKUP(표9[[#This Row],[Team]],표1[[내역]:[코스트 센터]],2,0) -> 100561 | G92: =VLOOKUP(표9[[#This Row],[Project]],표2[],2,0) -> P100010013 | H92: AWS_SDS-WebHost@sds.com(137191863862) | I92: =VLOOKUP($H92,AWS!$A:$H,8,0) -> Jordan Yerkes | J92: =VLOOKUP($H92,AWS!$A:$H,8,0) -> Jordan Yerkes | L92: 134200 | M92: 120638 | N92: 125729 | O92: 135435 | P92: 129388 | Q92: 135730 | R92: 136614 | S92: 102900 | T92: 0 | U92: 0 | V92: 0 | W92: =ROUND(표9[[#This Row],[Apr 2026 (USD or KRW)]],0) -> 0 | Y92: =표9[[#This Row],[Apr 2027(KRW)]]-표9[[#This Row],[Mar 2026(KRW)]] -> 0 | Z92: =IF(V92=0,"",(W92-V92)/V92) | AA92: =VLOOKUP(표9[[#This Row],[Team]],표1[],3,0) -> 1000
A93: =VLOOKUP($H93,AWS!$A:$H,2,0) -> AWS | B93: =VLOOKUP($H93,AWS!$A:$H,3,0) -> KRAFTON HQ | C93: =VLOOKUP($H93,AWS!$A:$H,4,0) -> Montreal Studio | D93: =VLOOKUP($H93,AWS!$A:$H,5,0) -> PGY_Art Cell | E93: =VLOOKUP($H93,AWS!$A:$H,6,0) -> STUDIO M | F93: =VLOOKUP(표9[[#This Row],[Team]],표1[[내역]:[코스트 센터]],2,0) -> 101695 | G93: =VLOOKUP(표9[[#This Row],[Project]],표2[],2,0) -> I100090821 | H93: aws_studio_m@bluehole.net(827588337044) | I93: =VLOOKUP($H93,AWS!$A:$H,8,0) -> Julien Copin | J93: =VLOOKUP($H93,AWS!$A:$H,8,0) -> Julien Copin | K93: v | L93: 3335034 | M93: 3265803 | N93: 3354486 | O93: 3340268 | P93: 3307884 | Q93: 3427707 | R93: 3507599 | S93: 3449608 | T93: 3603187 | U93: 3771584 | V93: 4056006 | W93: =ROUND(표9[[#This Row],[Apr 2026 (USD or KRW)]],0) -> 0 | Y93: =표9[[#This Row],[Apr 2027(KRW)]]-표9[[#This Row],[Mar 2026(KRW)]] -> -4056006 | Z93: =IF(V93=0,"",(W93-V93)/V93) -> -1 | AA93: =VLOOKUP(표9[[#This Row],[Team]],표1[],3,0) -> 1000
A94: =VLOOKUP($H94,AWS!$A:$H,2,0) -> AWS | B94: =VLOOKUP($H94,AWS!$A:$H,3,0) -> KRAFTON HQ | C94: =VLOOKUP($H94,AWS!$A:$H,4,0) -> KRAFTON HQ | D94: =VLOOKUP($H94,AWS!$A:$H,5,0) -> IT Dept. | E94: =VLOOKUP($H94,AWS!$A:$H,6,0) -> OVERHEAD/OTHERS | F94: =VLOOKUP(표9[[#This Row],[Team]],표1[[내역]:[코스트 센터]],2,0) -> 100036 | G94: =VLOOKUP(표9[[#This Row],[Project]],표2[],2,0) -> I100099999 | H94: aws_tech_network@bluehole.net(413470838121) | I94: =VLOOKUP($H94,AWS!$A:$H,8,0) -> 이승호 | J94: =VLOOKUP($H94,AWS!$A:$H,8,0) -> 이승호 | K94: v | L94: 14850702 | M94: 15778691 | N94: 27581289 | O94: 24716749 | P94: 22664091 | Q94: 24526518 | R94: 26033511 | S94: 20516105 | T94: 17738555 | U94: 19670533 | V94: 26702852 | W94: =ROUND(표9[[#This Row],[Apr 2026 (USD or KRW)]],0) -> 0 | Y94: =표9[[#This Row],[Apr 2027(KRW)]]-표9[[#This Row],[Mar 2026(KRW)]] -> -26702852 | Z94: =IF(V94=0,"",(W94-V94)/V94) -> -1 | AA94: =VLOOKUP(표9[[#This Row],[Team]],표1[],3,0) -> 1000
A95: =VLOOKUP($H95,AWS!$A:$H,2,0) -> AWS | B95: =VLOOKUP($H95,AWS!$A:$H,3,0) -> KRAFTON HQ | C95: =VLOOKUP($H95,AWS!$A:$H,4,0) -> SDS | D95: =VLOOKUP($H95,AWS!$A:$H,5,0) -> Striking Distance Studios | E95: =VLOOKUP($H95,AWS!$A:$H,6,0) -> The Callisto Protocol | F95: =VLOOKUP(표9[[#This Row],[Team]],표1[[내역]:[코스트 센터]],2,0) -> 100561 | G95: =VLOOKUP(표9[[#This Row],[Project]],표2[],2,0) -> P100010013 | H95: AWS_Titan-Build@sds.com(025476091557) | I95: =VLOOKUP($H95,AWS!$A:$H,8,0) -> Jordan Yerkes | J95: =VLOOKUP($H95,AWS!$A:$H,8,0) -> Jordan Yerkes | L95: 550617 | M95: 524156 | N95: 587536 | O95: 347848 | S95: 0 | T95: 0 | U95: 0 | V95: 0 | W95: =ROUND(표9[[#This Row],[Apr 2026 (USD or KRW)]],0) -> 0 | Y95: =표9[[#This Row],[Apr 2027(KRW)]]-표9[[#This Row],[Mar 2026(KRW)]] -> 0 | Z95: =IF(V95=0,"",(W95-V95)/V95) | AA95: =VLOOKUP(표9[[#This Row],[Team]],표1[],3,0) -> 1000
A96: =VLOOKUP($H96,AWS!$A:$H,2,0) -> AWS | B96: =VLOOKUP($H96,AWS!$A:$H,3,0) -> KRAFTON HQ | C96: =VLOOKUP($H96,AWS!$A:$H,4,0) -> SDS | D96: =VLOOKUP($H96,AWS!$A:$H,5,0) -> Striking Distance Studios | E96: =VLOOKUP($H96,AWS!$A:$H,6,0) -> The Callisto Protocol | F96: =VLOOKUP(표9[[#This Row],[Team]],표1[[내역]:[코스트 센터]],2,0) -> 100561 | G96: =VLOOKUP(표9[[#This Row],[Project]],표2[],2,0) -> P100010013 | H96: AWS_Titan-Dev@sds.com(948684412557) | I96: =VLOOKUP($H96,AWS!$A:$H,8,0) -> Jordan Yerkes | J96: =VLOOKUP($H96,AWS!$A:$H,8,0) -> Jordan Yerkes | L96: 4841717 | M96: 4607294 | N96: 5439464 | O96: 1337526 | S96: 0 | T96: 0 | U96: 0 | V96: 0 | W96: =ROUND(표9[[#This Row],[Apr 2026 (USD or KRW)]],0) -> 0 | Y96: =표9[[#This Row],[Apr 2027(KRW)]]-표9[[#This Row],[Mar 2026(KRW)]] -> 0 | Z96: =IF(V96=0,"",(W96-V96)/V96) | AA96: =VLOOKUP(표9[[#This Row],[Team]],표1[],3,0) -> 1000
A97: =VLOOKUP($H97,AWS!$A:$H,2,0) -> AWS | B97: =VLOOKUP($H97,AWS!$A:$H,3,0) -> KRAFTON HQ | C97: =VLOOKUP($H97,AWS!$A:$H,4,0) -> SDS | D97: =VLOOKUP($H97,AWS!$A:$H,5,0) -> Striking Distance Studios | E97: =VLOOKUP($H97,AWS!$A:$H,6,0) -> The Callisto Protocol | F97: =VLOOKUP(표9[[#This Row],[Team]],표1[[내역]:[코스트 센터]],2,0) -> 100561 | G97: =VLOOKUP(표9[[#This Row],[Project]],표2[],2,0) -> P100010013 | H97: AWS_Titan-Live@sds.com(668355933448) | I97: =VLOOKUP($H97,AWS!$A:$H,8,0) -> Jordan Yerkes | J97: =VLOOKUP($H97,AWS!$A:$H,8,0) -> Jordan Yerkes | L97: 12501 | M97: 5492 | N97: 5577 | O97: 3206 | S97: 0 | T97: 0 | U97: 0 | V97: 0 | W97: =ROUND(표9[[#This Row],[Apr 2026 (USD or KRW)]],0) -> 0 | Y97: =표9[[#This Row],[Apr 2027(KRW)]]-표9[[#This Row],[Mar 2026(KRW)]] -> 0 | Z97: =IF(V97=0,"",(W97-V97)/V97) | AA97: =VLOOKUP(표9[[#This Row],[Team]],표1[],3,0) -> 1000
A98: =VLOOKUP($H98,AWS!$A:$H,2,0) -> AWS | B98: =VLOOKUP($H98,AWS!$A:$H,3,0) -> KRAFTON HQ | C98: =VLOOKUP($H98,AWS!$A:$H,4,0) -> SDS | D98: =VLOOKUP($H98,AWS!$A:$H,5,0) -> Striking Distance Studios | E98: =VLOOKUP($H98,AWS!$A:$H,6,0) -> The Callisto Protocol | F98: =VLOOKUP(표9[[#This Row],[Team]],표1[[내역]:[코스트 센터]],2,0) -> 100561 | G98: =VLOOKUP(표9[[#This Row],[Project]],표2[],2,0) -> P100010013 | H98: AWS_Titan-Prod@sds.com(498442523516) | I98: =VLOOKUP($H98,AWS!$A:$H,8,0) -> Jordan Yerkes | J98: =VLOOKUP($H98,AWS!$A:$H,8,0) -> Jordan Yerkes | L98: 22913 | M98: 17208 | N98: 17469 | O98: 10288 | S98: 0 | T98: 0 | U98: 0 | V98: 0 | W98: =ROUND(표9[[#This Row],[Apr 2026 (USD or KRW)]],0) -> 0 | Y98: =표9[[#This Row],[Apr 2027(KRW)]]-표9[[#This Row],[Mar 2026(KRW)]] -> 0 | Z98: =IF(V98=0,"",(W98-V98)/V98) | AA98: =VLOOKUP(표9[[#This Row],[Team]],표1[],3,0) -> 1000
A99: =VLOOKUP($H99,AWS!$A:$H,2,0) -> AWS | B99: =VLOOKUP($H99,AWS!$A:$H,3,0) -> KRAFTON HQ | C99: =VLOOKUP($H99,AWS!$A:$H,4,0) -> Vector North | D99: =VLOOKUP($H99,AWS!$A:$H,5,0) -> Vector North Unit | E99: =VLOOKUP($H99,AWS!$A:$H,6,0) -> OVERHEAD/OTHERS | F99: =VLOOKUP(표9[[#This Row],[Team]],표1[[내역]:[코스트 센터]],2,0) -> 101214 | G99: =VLOOKUP(표9[[#This Row],[Project]],표2[],2,0) -> I100099999 | H99: aws_vn_dev@bluehole.net(182073802933) | I99: =VLOOKUP($H99,AWS!$A:$H,8,0) -> Petr Matoušek | J99: =VLOOKUP($H99,AWS!$A:$H,8,0) -> Petr Matoušek | L99: 2615779 | M99: 3700931 | N99: 5504323 | O99: 5175438 | P99: 4171430 | Q99: 4336445 | R99: 3641808 | S99: 0 | T99: 0 | U99: 0 | V99: 0 | W99: =ROUND(표9[[#This Row],[Apr 2026 (USD or KRW)]],0) -> 0 | Y99: =표9[[#This Row],[Apr 2027(KRW)]]-표9[[#This Row],[Mar 2026(KRW)]] -> 0 | Z99: =IF(V99=0,"",(W99-V99)/V99) | AA99: =VLOOKUP(표9[[#This Row],[Team]],표1[],3,0) -> 1000
A100: =VLOOKUP($H100,AWS!$A:$H,2,0) -> AWS | B100: =VLOOKUP($H100,AWS!$A:$H,3,0) -> OVERDARE | C100: =VLOOKUP($H100,AWS!$A:$H,4,0) -> OVERDARE | D100: =VLOOKUP($H100,AWS!$A:$H,5,0) -> OVDR Tech Div. | E100: =VLOOKUP($H100,AWS!$A:$H,6,0) -> OVERHEAD/OTHERS | F100: =VLOOKUP(표9[[#This Row],[Team]],표1[[내역]:[코스트 센터]],2,0) -> 460121 | G100: =VLOOKUP(표9[[#This Row],[Project]],표2[],2,0) -> I100099999 | H100: aws_web3_dev@bluehole.net(295140746614) | I100: =VLOOKUP($H100,AWS!$A:$H,7,0) -> 이상헌 | J100: =VLOOKUP($H100,AWS!$A:$H,8,0) -> 이상헌 | L100: 767744 | M100: 915459 | N100: 793575 | O100: 484858 | P100: 274589 | Q100: 288580 | R100: 301905 | S100: 300920 | T100: 260857 | U100: 313583 | V100: 256171 | W100: =ROUND(표9[[#This Row],[Apr 2026 (USD or KRW)]],0) -> 0 | Y100: =표9[[#This Row],[Apr 2027(KRW)]]-표9[[#This Row],[Mar 2026(KRW)]] -> -256171 | Z100: =IF(V100=0,"",(W100-V100)/V100) -> -1 | AA100: =VLOOKUP(표9[[#This Row],[Team]],표1[],3,0) -> 4600
...

Sheet Pivot by CW
A1: Please don't change this sheet and data. If necessary, contact Yunseul Lee via Slack 1:1 DM.
A2: Pivot (Cost per Cloud Provider)
A3: 행 레이블 | B3: 합계 : Mar 2026(KRW)
A4: Akamai | B4: 504766397
A5: KRAFTON HQ | B5: 504766397
A6: AWS | B6: 5793090939
A7: BLUEHOLE | B7: 17336978
A8: KRAFTON HQ | B8: 3837743597
A9: Research | B9: 79749506
A10: DLD | B10: 1858260858
A11: Azure | B11: 4420285606
A12: BLUEHOLE | B12: 24498736
A13: KRAFTON HQ | B13: 4241412983
A14: Research | B14: 154373887
A15: Datadog | B15: 347293612
... A22: 총합계 | B22: 1.2238995e+10
A31: Entity | B31: (다중 항목)
A33: 행 레이블 | B33: 합계 : July 2025(KRW) | C33: 합계 : Aug 2025(KRW) | D33: 합계 : Sep 2025(KRW) | E33: 합계 : Oct 2025(KRW) | F33: 합계 : Nov 2025(KRW) | G33: 합계 : Dec 2025(KRW) | H33: 합계 : Jan 2026(KRW) | I33: 합계 : Feb 2026(KRW) | J33: 합계 : Mar 2026(KRW) | K33: SUM | L33: =SUM(L34:L37) -> 3841286474 | M33: =SUM(L66,L69,L90,L99,L106,L116,L118,L122) -> #REF!
A34: BLUEHOLE | B34: 76512173 | C34: 71845839 | D34: 68077618 | E34: 72894895 | F34: 68822600 | G34: 73450500 | H34: 68330496 | I34: 39758714 | J34: 0 | K34: KRAFTON | L34: =SUM(J35:J43,J45:J54,J56:J59) -> 0 | M34: =SUM(L66,L69,L90,L99,L106,L116,L118) -> 2.4429155e+10
A35: Flyway Games | H35: 149904 | I35: 0 | J35: 0 | K35: RESEARCH | L35: =GETPIVOTDATA("합계 : Feb 2026(KRW)",$A$33,"Studio","Research") -> 222950439 | M35: =M122 -> 63576.28
A36: KRAFTON America | B36: 4680739 | C36: 4769599 | D36: 4503085 | E36: 4681703 | F36: 3056075 | G36: 4894166 | H36: 4845201 | I36: 146371 | J36: 0 | K36: DLD | L36: =GETPIVOTDATA("합계 : Feb 2026(KRW)",$A$33,"Studio","DLD") -> 3578577321
A37: KRAFTON HQ | B37: 8929736489 | C37: 5873437065 | D37: 5886019140 | E37: 5.9878105e+09 | F37: 6733154391 | G37: 9017495476 | H37: 5818565835 | I37: 5883691161 | J37: 0 | K37: BLUEHOLE | L37: =GETPIVOTDATA("합계 : Feb 2026(KRW)",$A$33,"Studio","BLUEHOLE") -> 39758714
A38: Mad Glory | B38: 10378012 | C38: 16438773 | D38: 20227398 | E38: 21665822 | F38: 19223375 | G38: 23491836 | H38: 23596073 | I38: 21690710 | J38: 0
A39: OVERDARE | B39: 31558871 | C39: 32141643 | D39: 40572449 | E39: 46471422 | F39: 33916708 | G39: 54902746 | H39: 59291320 | I39: 2493 | J39: 0
A40: Montreal Studio | B40: 3354486 | C40: 3340268 | D40: 3307884 | E40: 3427707 | F40: 3507599 | G40: 3449608 | H40: 3603187 | I40: 3771584 | J40: 0
A41: PUBG NewState | B41: 151058066 | C41: 147805535 | D41: 136755797 | E41: 1.4868654e+08 | F41: 149106806 | G41: 147568021 | H41: 133703152 | I41: 114052539 | J41: 0
A42: PUBG STUDIO | B42: 2725470596 | C42: 2646114816 | D42: 2646577566 | E42: 2.8537828e+09 | F42: 2.8757888e+09 | G42: 3115138625 | H42: 3023196236 | I42: 2562048571 | J42: 0
A43: ReLu Games | C43: 42 | D43: 23 | E43: 406.202 | F43: 8243 | G43: 11205 | H43: 4009 | I43: 0 | J43: 0
A44: Research | B44: 237452954 | C44: 182822172 | D44: 199077426 | E44: 1.8560827e+08 | F44: 195563752 | G44: 203029290 | H44: 221748189 | I44: 222950439 | J44: 0
A45: SDS | B45: 59390196 | C45: 50621161 | D45: 47395192 | E45: 51245023 | F45: 48741047 | G45: 43067663 | H45: 42252384 | I45: 29119948 | J45: 0
A46: KRAFTON CHINA | B46: 0 | C46: 0 | D46: 0 | E46: 0 | F46: 0 | G46: 0 | H46: 0 | I46: 0 | J46: 0
A47: KRAFTON EUROPE B.V. | B47: 6 | C47: 6 | D47: 54 | E47: 1370.9384 | F47: 738 | G47: 247 | H47: 211 | I47: 246 | J47: 0
A48: InZOI Studio | B48: 1378863 | C48: 1790717 | D48: 1770163 | E48: 1832858.6 | F48: 1731820 | G48: 2238136 | H48: 2290139 | I48: 1858983 | J48: 0
A49: 5Minlab | C49: 4644 | D49: 6003 | E49: 9917.1099 | F49: 53909 | G49: 186029 | H49: 268711 | I49: 129914 | J49: 0
A50: Tango Gameworks | B50: 852610 | C50: 859209 | D50: 819580 | E50: 875797 | F50: 865537 | G50: 913051 | H50: 863269 | I50: 766731 | J50: 0
A51: Nautilus | H51: 13362 | I51: 1435706 | J51: 0
A52: Vector North | B52: 5506954 | C52: 5176171 | D52: 4171477 | E52: 4336485.6 | F52: 3641829 | G52: 0 | H52: 0 | I52: 0 | J52: 0
A53: Omnicraftlabs | C53: 808 | D53: 14506 | E53: 16318 | F53: 12535 | G53: 13166 | H53: 13112 | I53: 11112 | J53: 0
A54: OCL GW Server Team | C54: 808 | D54: 14506 | E54: 16318 | F54: 12535 | G54: 13166 | H54: 13112 | I54: 11112 | J54: 0
A55: GW | C55: 808 | D55: 14506 | E55: 16318 | F55: 12535 | G55: 13166 | H55: 13112 | I55: 11112 | J55: 0
A56: KRAFTON India | D56: 0 | E56: 12032 | F56: 184044 | G56: 223311 | H56: 246622 | I56: 1620872 | J56: 0
A57: DLD | C57: 14007 | D57: 7274281183 | E57: 708782514 | F57: 873132036 | G57: 981513185 | H57: 1246271540 | I57: 3578577321 | J57: 0
A58: KRAFTON Montreal | G58: 7065 | H58: 18151 | I58: 20331 | J58: 0
A59: JofSoft | G59: 13387 | H59: 4422 | I59: 6985 | J59: 0
A60: NineB | H60: 370274 | I60: 1789499 | J60: 0
A61: OliveTree Games | F61: 19309 | G61: 210145 | H61: 250984 | I61: 796456 | J61: 0
A62: 총합계 | B62: 12237331015 | C62: 9037182475 | D62: 16333576544 | E62: 1.0092142e+10 | F62: 1.1010531e+10 | G62: 13671816858 | H62: 10649896783 | I62: 12464246686 | J62: 0 | M62: =GETPIVOTDATA("합계 : Feb 2026(KRW)",$A$65)-L122 -> #REF!
A63: Entity | B63: (다중 항목)
A65: 행 레이블 | B65: 합계 : July 2025(KRW) | C65: 합계 : Aug 2025(KRW) | D65: 합계 : Sep 2025(KRW) | E65: 합계 : Oct 2025(KRW) | F65: 합계 : Nov 2025(KRW) | G65: 합계 : Dec 2025(KRW) | H65: 합계 : Jan 2026(KRW) | I65: 합계 : Feb 2026(KRW) | J65: 합계 : Mar 2026(KRW)
A66: Akamai | B66: 974563484 | C66: 740535918 | D66: 949642261 | E66: 650926203 | F66: 916280001 | G66: 669160974 | H66: 894789092 | I66: 429920311 | J66: 504766397 | K66: KRAFTON | L66: =GETPIVOTDATA("합계 : Mar 2026(KRW)",$A$65,"Provider","Akamai") -> 504766397
A67: KRAFTON HQ | B67: 968344851 | C67: 733951290 | D67: 944443949 | E67: 644277143 | F67: 909473492 | G67: 663356159 | H67: 888242646 | I67: 424453663 | J67: 499174858
A68: PUBG NewState | B68: 6218633 | C68: 6584628 | D68: 5198312 | E68: 6649060 | F68: 6806509 | G68: 5804815 | H68: 6546446 | I68: 5466648 | J68: 5591539
A69: AWS | B69: 6294935396 | C69: 3260806399 | D69: 10558514935 | E69: 4385145295 | F69: 4773388052 | G69: 7098320553 | H69: 4490681671 | I69: 6662124053 | J69: 5793090939 | K69: SUM | L69: =SUM(L70:L73) -> 5793090939
A70: BLUEHOLE | B70: 50399448 | C70: 46819477 | D70: 42868625 | E70: 46741008 | F70: 43309097 | G70: 46584615 | H70: 42134889 | I70: 14687809 | J70: 17336978 | K70: KRAFTON | L70: =SUM(J71:J76,J78:J81,J83:J84,J86:J89) -> 3837743597
A71: KRAFTON America | B71: 23164 | C71: 145340 | D71: 142739 | E71: 145778 | F71: 150607 | G71: 146609 | H71: 147869 | I71: 146182 | J71: 167787 | K71: RESEARCH | L71: =J77 -> 79749506 | R71: =P72-P73 -> 0
A72: KRAFTON HQ | B72: 4207544056 | C72: 1293279739 | D72: 1285894755 | E72: 1547557436 | F72: 1687286199 | G72: 3836070626 | H72: 996029964 | I72: 1298045483 | J72: 1710512563 | K72: DLD | L72: =J85 -> 1858260858
A73: Mad Glory | B73: 10378012 | C73: 16438773 | D73: 20227398 | E73: 21074628 | F73: 18572305 | G73: 22714023 | H73: 22790740 | I73: 20797881 | J73: 26212266 | K73: BLUEHOLE | L73: =J70 -> 17336978
A74: Montreal Studio | B74: 3354486 | C74: 3340268 | D74: 3307884 | E74: 3427707 | F74: 3507599 | G74: 3449608 | H74: 3603187 | I74: 3771584 | J74: 4056006
A75: PUBG NewState | B75: 143600031 | C75: 140024116 | D75: 130476342 | E75: 140904911 | F75: 141237920 | G75: 140700948 | H75: 126100421 | I75: 107580335 | J75: 122411710
A76: PUBG STUDIO | B76: 1737570968 | C76: 1679739040 | D76: 1703069958 | E76: 1832148702 | F76: 1915032516 | G76: 1986639840 | H76: 1947140636 | I76: 1534759678 | J76: 1937266234
A77: Research | B77: 77916618 | C77: 24808411 | D77: 45854461 | E77: 27978220 | F77: 37818078 | G77: 35681118 | H77: 62011411 | I77: 69007423 | J77: 79749506
A78: InZOI Studio | B78: 1055148 | C78: 1471063 | D78: 1465145 | E78: 1505713 | F78: 1520310 | G78: 1893141 | H78: 2089818 | I78: 1858983 | J78: 2478161
A79: SDS | B79: 56736532 | C79: 48690710 | D79: 45920929 | E79: 49638086 | F79: 47098152 | G79: 41553780 | H79: 40600032 | I79: 26440842 | J79: 22141972
A80: Tango Gameworks | B80: 852610 | C80: 859209 | D80: 819580 | E80: 875797 | F80: 865537 | G80: 913051 | H80: 863269 | I80: 766731 | J80: 891036
A81: Nautilus | H81: 13362 | I81: 1435706 | J81: 4175979
A82: Vector North | B82: 5504323 | C82: 5175438 | D82: 4171430 | E82: 4336445 | F82: 3641808 | G82: 0 | H82: 0 | I82: 0 | J82: 0
A83: Omnicraftlabs | C83: 808 | D83: 14506 | E83: 16318 | F83: 12535 | G83: 13166 | H83: 13112 | I83: 11112 | J83: 13060
A84: KRAFTON India | D84: 0 | E84: 12032 | F84: 184044 | G84: 223311 | H84: 245741 | I84: 1620872 | J84: 4849681
A85: DLD | C85: 14007 | D85: 7274281183 | E85: 708782514 | F85: 873132036 | G85: 981513185 | H85: 1246271540 | I85: 3578577321 | J85: 1858260858
A86: JofSoft | G86: 13387 | H86: 4422 | I86: 6985 | J86: 8083
A87: NineB | H87: 370274 | I87: 1789499 | J87: 1360790
A88: OliveTree Games | F88: 19309 | G88: 210145 | H88: 250984 | I88: 796456 | J88: 1161356
A89: Ludo | I89: 23171 | J89: 36913
A90: Azure | B90: 4126725446 | C90: 4223983327 | D90: 4000590094 | E90: 4.1409109e+09 | F90: 3997417018 | G90: 4259775904 | H90: 4131949339 | I90: 4214899261 | J90: 4420285606 | K90: SUM | L90: =SUM(L91:L93) -> 4420285606
A91: BLUEHOLE | B91: 25525204 | C91: 24444617 | D91: 24573297 | E91: 25564274 | F91: 24886365 | G91: 26263143 | H91: 25596193 | I91: 24438009 | J91: 24498736 | K91: KRAFTON | L91: =SUM(J92:J94,J96:J98) -> 4241412983
A92: KRAFTON HQ | B92: 3168680649 | C92: 3275684818 | D92: 3075780316 | E92: 3.1613487e+09 | F92: 3078119958 | G92: 3161903858 | H92: 3126338935 | I92: 3280059979 | J92: 3348614673 | K92: RESEARCH | L92: =GETPIVOTDATA("합계 : Mar 2026(KRW)",$A$65,"Provider","Azure","Studio","Research") -> 154373887
A93: PUBG NewState | B93: 1098924 | C93: 1089382 | D93: 1065483 | E93: 1125954.1 | F93: 1055573 | G93: 1055593 | H93: 1049657 | I93: 998939 | J93: 1051540 | K93: BLUEHOLE | L93: =GETPIVOTDATA("합계 : Mar 2026(KRW)",$A$65,"Provider","Azure","Studio","BLUEHOLE") -> 24498736
A94: PUBG STUDIO | B94: 771884326 | C94: 764750743 | D94: 745947979 | E94: 7.9524054e+08 | F94: 735608710 | G94: 903197826 | H94: 819209414 | I94: 755438741 | J94: 891724377
A95: Research | B95: 159536336 | C95: 158013761 | D95: 153222965 | E95: 1.5763005e+08 | F95: 157745674 | G95: 167348172 | H95: 159736778 | I95: 153943016 | J95: 154373887
A96: KRAFTON EUROPE B.V. | B96: 6 | C96: 6 | D96: 54 | E96: 1370.9384 | F96: 738 | G96: 247 | H96: 211 | I96: 246 | J96: 232
A97: SDS | B97: 1 | D97: 0 | F97: 0 | G97: 0 | H97: 0 | I97: 0 | J97: 0
A98: KRAFTON Montreal | G98: 7065 | H98: 18151 | I98: 20331 | J98: 22161
A99: Datadog | B99: 231039867 | C99: 216672179 | D99: 217718863 | E99: 242606106 | F99: 247624872 | G99: 289113984 | H99: 284855685 | I99: 280443151 | J99: 347293612 | K99: SUM | L99: =SUM(L100:L101) -> 345719160
A100: BLUEHOLE | B100: 587521 | C100: 581745 | D100: 635696 | E100: 589613 | F100: 627138 | G100: 602742 | H100: 599414 | I100: 632896 | J100: 599054 | K100: KRAFTON | L100: =SUM(J100:J104) -> 345086264
A101: KRAFTON HQ | B101: 93093113 | C101: 92176982 | D101: 98037212 | E101: 105744448 | F101: 116879209 | G101: 165409830 | H101: 138627807 | I101: 131221621 | J101: 167286399 | K101: BLUEHOLE | L101: =SUM(GETPIVOTDATA("합계 : Feb 2026(KRW)",$A$65,"Provider","Datadog","Studio","BLUEHOLE")) -> 632896
A102: Mad Glory | E102: 591194 | F102: 651070 | G102: 777813 | H102: 805333 | I102: 892829 | J102: 921321
A103: PUBG NewState | B103: 140478 | C103: 107409 | D103: 15660 | E103: 6611 | F103: 6804 | G103: 6665 | H103: 6628 | I103: 6617 | J103: 7030
A104: PUBG STUDIO | B104: 134565092 | C104: 121875592 | D104: 117556032 | E104: 134067303 | F104: 127817756 | G104: 120803051 | H104: 143164151 | I104: 145010082 | J104: 176272460
A105: SDS | B105: 2653663 | C105: 1930451 | D105: 1474263 | E105: 1606937 | F105: 1642895 | G105: 1513883 | H105: 1652352 | I105: 2679106 | J105: 2207348
A106: GCP | B106: 54180851 | C106: 58787177 | D106: 79184537 | E106: 1.1241661e+08 | F106: 449695943 | G106: 318857559 | H106: 193370171 | I106: 262708856 | J106: 1.126298e+09 | K106: SUM | L106: =SUM(L107:L108) -> 1.126298e+09
A107: Flyway Games | H107: 149904 | I107: 0 | J107: 0 | K107: KRAFTON | L107: =SUM(J107:J109,J111:J116) -> 1.0861189e+09
A108: KRAFTON America | B108: 4657575 | C108: 4624259 | D108: 4360346 | E108: 4535925 | F108: 2905468 | G108: 4747557 | H108: 4697332 | I108: 189 | J108: 3322610 | K108: OVERDARE | L108: =GETPIVOTDATA("합계 : Mar 2026(KRW)",$A$65,"Provider","GCP","Studio","OVERDARE") -> 40179133
A109: KRAFTON HQ | B109: 12910351 | C109: 17609247 | D109: 28453083 | E109: 56354196 | F109: 402442937 | G109: 244119781 | H109: 110970321 | I109: 227456331 | J109: 1.0386128e+09
A110: OVERDARE | B110: 31558871 | C110: 32141643 | D110: 40572449 | E110: 46471422 | F110: 33916708 | G110: 54902746 | H110: 59291320 | I110: 2493 | J110: 40179133
A111: PUBG STUDIO | B111: 4727708 | C111: 4086955 | D111: 5487568 | E111: 4717562.1 | F111: 10157147 | G111: 14545246 | H111: 17787372 | I111: 35119929 | J111: 43317523
A112: ReLu Games | C112: 42 | D112: 23 | E112: 406.202 | F112: 8243 | G112: 11205 | H112: 4009 | I112: 0 | J112: 14680.21
A113: InZOI Studio | B113: 323715 | C113: 319654 | D113: 305018 | E113: 327145.55 | F113: 211510 | G113: 344995 | H113: 200321 | I113: 0 | J113: 27265.65
A114: 5Minlab | C114: 4644 | D114: 6003 | E114: 9917.1099 | F114: 53909 | G114: 186029 | H114: 268711 | I114: 129914 | J114: 823882.64
A115: Vector North | B115: 2631 | C115: 733 | D115: 47 | E115: 40.598697 | F115: 21 | G115: 0 | H115: 0 | I115: 0 | J115: 0
A116: KRAFTON India | H116: 881 | I116: 0 | J116: 124.42 | K116: SUM | L116: =L117 -> 0 | M116: Gemini
...

Sheet Pivot
A3: 행 레이블 | B3: 합계 : Mar 2026(KRW)
A4: Akamai | B4: 504766397
A5: KRAFTON HQ | B5: 504766397
A6: AWS | B6: 5793090939
A7: BLUEHOLE | B7: 17336978
A8: DLD | B8: 1858260858
A9: KRAFTON HQ | B9: 3837743597
A10: Research | B10: 79749506
A11: Azure | B11: 4420285606
A12: BLUEHOLE | B12: 24498736
A13: KRAFTON HQ | B13: 4241412983
A14: Research | B14: 154373887
A15: Datadog | B15: 343643598
... A26: 총합계 | B26: 12910469675
A29: 행 레이블 | B29: 합계 : Apr 2025(KRW) | C29: 합계 : May 2025(KRW) | D29: 합계 : June 2025(KRW) | E29: 합계 : July 2025(KRW) | F29: 합계 : Aug 2025(KRW) | G29: 합계 : Sep 2025(KRW) | H29: 합계 : Oct 2025(KRW) | I29: 합계 : Nov 2025(KRW) | J29: 합계 : Dec 2025(KRW) | K29: 합계 : Jan 2026(KRW) | L29: 합계 : Feb 2026(KRW) | M29: 합계 : Mar 2026(KRW)
A30: BLUEHOLE | B30: 51038109 | C30: 76376626 | D30: 79132451 | E30: 76512173 | F30: 71845839 | G30: 68077618 | H30: 72894895 | I30: 68822600 | J30: 73450500 | K30: 68330496 | L30: 39758714 | M30: 42434768
A31: BLUEHOLE | B31: 51038109 | C31: 76376626 | D31: 79132451 | E31: 76512173 | F31: 71845839 | G31: 68077618 | H31: 72894895 | I31: 68822600 | J31: 73450500 | K31: 68330496 | L31: 39758714 | M31: 42434768
A32: DLD | F32: 14007 | G32: 7274281183 | H32: 708782514 | I32: 873132036 | J32: 981513185 | K32: 1246271540 | L32: 3578577321 | M32: 1858260858
A33: DLD | F33: 14007 | G33: 7274281183 | H33: 708782514 | I33: 873132036 | J33: 981513185 | K33: 1246271540 | L33: 3578577321 | M33: 1858260858
A34: KRAFTON HQ | B34: 4859521709 | C34: 8374385121 | D34: 8101955028 | E34: 11923365888 | F34: 8782500457 | G34: 8792140317 | H34: 9.1248566e+09 | I34: 9.8730128e+09 | J34: 12413823883 | K34: 9113546558 | L34: 8622960212 | M34: 10775650656
A35: 5Minlab | F35: 4644 | G35: 6003 | H35: 9917.1099 | I35: 53909 | J35: 186029 | K35: 268711 | L35: 129914 | M35: 823883
A36: Flyway Games | K36: 149904 | L36: 0 | M36: 0
A37: InZOI Studio | B37: 847662 | C37: 831954 | D37: 1030238 | E37: 1378863 | F37: 1790717 | G37: 1770163 | H37: 1832858.6 | I37: 1731820 | J37: 2238136 | K37: 2290139 | L37: 1858983 | M37: 2505427
A38: JofSoft | J38: 13387 | K38: 4422 | L38: 6985 | M38: 8083
A39: KRAFTON America | B39: 4617164 | C39: 3751157 | D39: 4614580 | E39: 4680739 | F39: 4769599 | G39: 4503085 | H39: 4681703 | I39: 3056075 | J39: 4894166 | K39: 4845201 | L39: 146371 | M39: 3490397
A40: KRAFTON CHINA | B40: 0 | C40: 0 | D40: 7987883 | E40: 0 | F40: 0 | G40: 0 | H40: 0 | I40: 0 | J40: 0 | K40: 0 | L40: 0 | M40: 0
A41: KRAFTON EUROPE B.V. | B41: 0 | C41: 5 | D41: 5 | E41: 6 | F41: 6 | G41: 54 | H41: 1370.9384 | I41: 738 | J41: 247 | K41: 211 | L41: 246 | M41: 232
A42: KRAFTON HQ | B42: 2835777766 | C42: 5518968068 | D42: 5248795558 | E42: 8929736489 | F42: 5873437065 | G42: 5886019140 | H42: 5.9878105e+09 | I42: 6733154391 | J42: 9017495476 | K42: 5818565835 | L42: 5883667990 | M42: 7351033957
A43: KRAFTON India | G43: 0 | H43: 12032 | I43: 184044 | J43: 223311 | K43: 246622 | L43: 1620872 | M43: 4849806
A44: KRAFTON Montreal | J44: 7065 | K44: 18151 | L44: 20331 | M44: 22161
A45: Ludo | L45: 23171 | M45: 36913
A46: Mad Glory | B46: 7595237 | C46: 7654818 | D46: 6913775 | E46: 10378012 | F46: 16438773 | G46: 20227398 | H46: 21665822 | I46: 19223375 | J46: 23491836 | K46: 23596073 | L46: 21690710 | M46: 27133587
A47: Montreal Studio | B47: 7943453 | C47: 3335034 | D47: 3265803 | E47: 3354486 | F47: 3340268 | G47: 3307884 | H47: 3427707 | I47: 3507599 | J47: 3449608 | K47: 3603187 | L47: 3771584 | M47: 4056006
A48: Nautilus | K48: 13362 | L48: 1435706 | M48: 4175979
A49: NineB | K49: 370274 | L49: 1789499 | M49: 1360790
A50: OliveTree Games | I50: 19309 | J50: 210145 | K50: 250984 | L50: 796456 | M50: 1161356
A51: Omnicraftlabs | F51: 808 | G51: 14506 | H51: 16318 | I51: 12535 | J51: 13166 | K51: 13112 | L51: 11112 | M51: 13060
A52: OVERDARE | B52: 29785612 | C52: 18023639 | D52: 24304360 | E52: 31558871 | F52: 32141643 | G52: 40572449 | H52: 46471422 | I52: 33916708 | J52: 54902746 | K52: 59291320 | L52: 2493 | M52: 40179134
A53: PUBG NewState | B53: 166388350 | C53: 157941611 | D53: 146060949 | E53: 151058066 | F53: 147805535 | G53: 136755797 | H53: 1.4868654e+08 | I53: 149106806 | J53: 147568021 | K53: 133703152 | L53: 114052539 | M53: 129061819
A54: PUBG STUDIO | B54: 1718618659 | C54: 2577899498 | D54: 2577406939 | E54: 2725470596 | F54: 2646114816 | G54: 2646577566 | H54: 2.8537828e+09 | I54: 2.8757888e+09 | J54: 3115138625 | K54: 3023196236 | L54: 2562048571 | M54: 3180483030
A55: ReLu Games | F55: 42 | G55: 23 | H55: 406.202 | I55: 8243 | J55: 11205 | K55: 4009 | L55: 0 | M55: 14680
A56: SDS | B56: 85121592 | C56: 82501773 | D56: 77007814 | E56: 59390196 | F56: 50621161 | G56: 47395192 | H56: 51245023 | I56: 48741047 | J56: 43067663 | K56: 42252384 | L56: 29119948 | M56: 24349320
A57: Tango Gameworks | B57: 487422 | C57: 859734 | D57: 863859 | E57: 852610 | F57: 859209 | G57: 819580 | H57: 875797 | I57: 865537 | J57: 913051 | K57: 863269 | L57: 766731 | M57: 891036
A58: Vector North | B58: 2338792 | C58: 2617830 | D58: 3703265 | E58: 5506954 | F58: 5176171 | G58: 4171477 | H58: 4336485.6 | I58: 3641829 | J58: 0 | K58: 0 | L58: 0 | M58: 0
A59: Research | B59: 18188591 | C59: 207739366 | D59: 207150725 | E59: 237452954 | F59: 182822172 | G59: 199077426 | H59: 1.8560827e+08 | I59: 195563752 | J59: 203029290 | K59: 221748189 | L59: 222950439 | M59: 234123393
A60: Research | B60: 18188591 | C60: 207739366 | D60: 207150725 | E60: 237452954 | F60: 182822172 | G60: 199077426 | H60: 1.8560827e+08 | I60: 195563752 | J60: 203029290 | K60: 221748189 | L60: 222950439 | M60: 234123393
A61: 총합계 | B61: 4928748409 | C61: 8658501113 | D61: 8388238204 | E61: 12237331015 | F61: 9037182475 | G61: 16333576544 | H61: 1.0092142e+10 | I61: 1.1010531e+10 | J61: 13671816858 | K61: 10649896783 | L61: 12464246686 | M61: 12910469675
A64: 행 레이블 | B64: 합계 : Apr 2025(KRW) | C64: 합계 : May 2025(KRW) | D64: 합계 : June 2025(KRW) | E64: 합계 : July 2025(KRW) | F64: 합계 : Aug 2025(KRW) | G64: 합계 : Sep 2025(KRW) | H64: 합계 : Oct 2025(KRW) | I64: 합계 : Nov 2025(KRW) | J64: 합계 : Dec 2025(KRW) | K64: 합계 : Jan 2026(KRW) | L64: 합계 : Feb 2026(KRW) | M64: 합계 : Mar 2026(KRW)
A65: Akamai | B65: 487090385 | C65: 767592030 | D65: 596421004 | E65: 974563484 | F65: 740535918 | G65: 949642261 | H65: 650926203 | I65: 916280001 | J65: 669160974 | K65: 894789092 | L65: 429920311 | M65: 504766397
A66: KRAFTON HQ | B66: 487090385 | C66: 767592030 | D66: 596421004 | E66: 974563484 | F66: 740535918 | G66: 949642261 | H66: 650926203 | I66: 916280001 | J66: 669160974 | K66: 894789092 | L66: 429920311 | M66: 504766397
A67: KRAFTON HQ | B67: 480068443 | C67: 761389808 | D67: 590260969 | E67: 968344851 | F67: 733951290 | G67: 944443949 | H67: 644277143 | I67: 909473492 | J67: 663356159 | K67: 888242646 | L67: 424453663 | M67: 499174858
A68: PUBG NewState | B68: 7021942 | C68: 6202222 | D68: 6160035 | E68: 6218633 | F68: 6584628 | G68: 5198312 | H68: 6649060 | I68: 6806509 | J68: 5804815 | K68: 6546446 | L68: 5466648 | M68: 5591539
A69: AWS | B69: 3006025542 | C69: 2940259556 | D69: 3044038748 | E69: 6294935396 | F69: 3260806399 | G69: 10558514935 | H69: 4385145295 | I69: 4773388052 | J69: 7098320553 | K69: 4490681671 | L69: 6662124053 | M69: 5793090939
A70: BLUEHOLE | B70: 50454436 | C70: 49483753 | D70: 53274378 | E70: 50399448 | F70: 46819477 | G70: 42868625 | H70: 46741008 | I70: 43309097 | J70: 46584615 | K70: 42134889 | L70: 14687809 | M70: 17336978
A71: BLUEHOLE | B71: 50454436 | C71: 49483753 | D71: 53274378 | E71: 50399448 | F71: 46819477 | G71: 42868625 | H71: 46741008 | I71: 43309097 | J71: 46584615 | K71: 42134889 | L71: 14687809 | M71: 17336978
A72: DLD | F72: 14007 | G72: 7274281183 | H72: 708782514 | I72: 873132036 | J72: 981513185 | K72: 1246271540 | L72: 3578577321 | M72: 1858260858
A73: DLD | F73: 14007 | G73: 7274281183 | H73: 708782514 | I73: 873132036 | J73: 981513185 | K73: 1246271540 | L73: 3578577321 | M73: 1858260858
A74: KRAFTON HQ | B74: 2937382515 | C74: 2848447969 | D74: 2939415428 | E74: 6166619330 | F74: 3189164504 | G74: 3195510666 | H74: 3601643553 | I74: 3819128841 | J74: 6034541635 | K74: 3140263831 | L74: 2999851500 | M74: 3837743597
A75: InZOI Studio | B75: 847662 | C75: 831954 | D75: 819863 | E75: 1055148 | F75: 1471063 | G75: 1465145 | H75: 1505713 | I75: 1520310 | J75: 1893141 | K75: 2089818 | L75: 1858983 | M75: 2478161
A76: JofSoft | J76: 13387 | K76: 4422 | L76: 6985 | M76: 8083
A77: KRAFTON America | E77: 23164 | F77: 145340 | G77: 142739 | H77: 145778 | I77: 150607 | J77: 146609 | K77: 147869 | L77: 146182 | M77: 167787
A78: KRAFTON HQ | B78: 1164600271 | C78: 1033920507 | D78: 1157612064 | E78: 4207544056 | F78: 1293279739 | G78: 1285894755 | H78: 1547557436 | I78: 1687286199 | J78: 3836070626 | K78: 996029964 | L78: 1298045483 | M78: 1710512563
A79: KRAFTON India | G79: 0 | H79: 12032 | I79: 184044 | J79: 223311 | K79: 245741 | L79: 1620872 | M79: 4849681
A80: Ludo | L80: 23171 | M80: 36913
A81: Mad Glory | B81: 7595237 | C81: 7654818 | D81: 6913775 | E81: 10378012 | F81: 16438773 | G81: 20227398 | H81: 21074628 | I81: 18572305 | J81: 22714023 | K81: 22790740 | L81: 20797881 | M81: 26212266
A82: Montreal Studio | B82: 7943453 | C82: 3335034 | D82: 3265803 | E82: 3354486 | F82: 3340268 | G82: 3307884 | H82: 3427707 | I82: 3507599 | J82: 3449608 | K82: 3603187 | L82: 3771584 | M82: 4056006
A83: Nautilus | K83: 13362 | L83: 1435706 | M83: 4175979
A84: NineB | K84: 370274 | L84: 1789499 | M84: 1360790
A85: OliveTree Games | I85: 19309 | J85: 210145 | K85: 250984 | L85: 796456 | M85: 1161356
A86: Omnicraftlabs | F86: 808 | G86: 14506 | H86: 16318 | I86: 12535 | J86: 13166 | K86: 13112 | L86: 11112 | M86: 13060
A87: PUBG NewState | B87: 159255146 | C87: 150522441 | D87: 138681215 | E87: 143600031 | F87: 140024116 | G87: 130476342 | H87: 140904911 | I87: 141237920 | J87: 140700948 | K87: 126100421 | L87: 107580335 | M87: 122411710
A88: PUBG STUDIO | B88: 1512376130 | C88: 1569306917 | D88: 1553104140 | E88: 1737570968 | F88: 1679739040 | G88: 1703069958 | H88: 1832148702 | I88: 1915032516 | J88: 1986639840 | K88: 1947140636 | L88: 1534759678 | M88: 1937266234
A89: SDS | B89: 81940980 | C89: 79400785 | D89: 74453778 | E89: 56736532 | F89: 48690710 | G89: 45920929 | H89: 49638086 | I89: 47098152 | J89: 41553780 | K89: 40600032 | L89: 26440842 | M89: 22141972
A90: Tango Gameworks | B90: 487422 | C90: 859734 | D90: 863859 | E90: 852610 | F90: 859209 | G90: 819580 | H90: 875797 | I90: 865537 | J90: 913051 | K90: 863269 | L90: 766731 | M90: 891036
A91: Vector North | B91: 2336214 | C91: 2615779 | D91: 3700931 | E91: 5504323 | F91: 5175438 | G91: 4171430 | H91: 4336445 | I91: 3641808 | J91: 0 | K91: 0 | L91: 0 | M91: 0
A92: Research | B92: 18188591 | C92: 42327834 | D92: 51348942 | E92: 77916618 | F92: 24808411 | G92: 45854461 | H92: 27978220 | I92: 37818078 | J92: 35681118 | K92: 62011411 | L92: 69007423 | M92: 79749506
A93: Research | B93: 18188591 | C93: 42327834 | D93: 51348942 | E93: 77916618 | F93: 24808411 | G93: 45854461 | H93: 27978220 | I93: 37818078 | J93: 35681118 | K93: 62011411 | L93: 69007423 | M93: 79749506
A94: Azure | B94: 0 | C94: 4134046202 | D94: 3874487763 | E94: 4126725446 | F94: 4223983327 | G94: 4000590094 | H94: 4.1409109e+09 | I94: 3997417018 | J94: 4259775904 | K94: 4131949339 | L94: 4214899261 | M94: 4420285606
A95: BLUEHOLE | B95: 0 | C95: 26327618 | D95: 25284279 | E95: 25525204 | F95: 24444617 | G95: 24573297 | H95: 25564274 | I95: 24886365 | J95: 26263143 | K95: 25596193 | L95: 24438009 | M95: 24498736
A96: BLUEHOLE | B96: 0 | C96: 26327618 | D96: 25284279 | E96: 25525204 | F96: 24444617 | G96: 24573297 | H96: 25564274 | I96: 24886365 | J96: 26263143 | K96: 25596193 | L96: 24438009 | M96: 24498736
A97: KRAFTON HQ | B97: 0 | C97: 3942307052 | D97: 3693401701 | E97: 3941663906 | F97: 4041524949 | G97: 3822793832 | H97: 3.9577166e+09 | I97: 3814784979 | J97: 4066164589 | K97: 3946616368 | L97: 4036518236 | M97: 4241412983
A98: KRAFTON EUROPE B.V. | B98: 0 | C98: 5 | D98: 5 | E98: 6 | F98: 6 | G98: 54 | H98: 1370.9384 | I98: 738 | J98: 247 | K98: 211 | L98: 246 | M98: 232
A99: KRAFTON HQ | B99: 0 | C99: 3146909888 | D99: 2957988391 | E99: 3168680649 | F99: 3275684818 | G99: 3075780316 | H99: 3.1613487e+09 | I99: 3078119958 | J99: 3161903858 | K99: 3126338935 | L99: 3280059979 | M99: 3348614673
A100: KRAFTON Montreal | J100: 7065 | K100: 18151 | L100: 20331 | M100: 22161
A101: PUBG NewState | B101: 0 | C101: 1110099 | D101: 1081917 | E101: 1098924 | F101: 1089382 | G101: 1065483 | H101: 1125954.1 | I101: 1055573 | J101: 1055593 | K101: 1049657 | L101: 998939 | M101: 1051540
A102: PUBG STUDIO | B102: 0 | C102: 794287060 | D102: 734331388 | E102: 771884326 | F102: 764750743 | G102: 745947979 | H102: 7.9524054e+08 | I102: 735608710 | J102: 903197826 | K102: 819209414 | L102: 755438741 | M102: 891724377
A103: SDS | B103: 0 | C103: 0 | D103: 0 | E103: 1 | G103: 0 | I103: 0 | J103: 0 | K103: 0 | L103: 0 | M103: 0
A104: Research | B104: 0 | C104: 165411532 | D104: 155801783 | E104: 159536336 | F104: 158013761 | G104: 153222965 | H104: 1.5763005e+08 | I104: 157745674 | J104: 167348172 | K104: 159736778 | L104: 153943016 | M104: 154373887
A105: Research | B105: 0 | C105: 165411532 | D105: 155801783 | E105: 159536336 | F105: 158013761 | G105: 153222965 | H105: 1.5763005e+08 | I105: 157745674 | J105: 167348172 | K105: 159736778 | L105: 153943016 | M105: 154373887
A106: Datadog | B106: 261440022 | C106: 239043078 | D106: 308321263 | E106: 231039867 | F106: 216672179 | G106: 217718863 | H106: 242606106 | I106: 247624872 | J106: 289113984 | K106: 284855685 | L106: 280443151 | M106: 343643598
A107: BLUEHOLE | B107: 583673 | C107: 565255 | D107: 573794 | E107: 587521 | F107: 581745 | G107: 635696 | H107: 589613 | I107: 627138 | J107: 602742 | K107: 599414 | L107: 632896 | M107: 599054
A108: BLUEHOLE | B108: 583673 | C108: 565255 | D108: 573794 | E108: 587521 | F108: 581745 | G108: 635696 | H108: 589613 | I108: 627138 | J108: 602742 | K108: 599414 | L108: 632896 | M108: 599054
A109: KRAFTON HQ | B109: 260856349 | C109: 238477823 | D109: 307747469 | E109: 230452346 | F109: 216090434 | G109: 217083167 | H109: 242016493 | I109: 246997734 | J109: 288511242 | K109: 284256271 | L109: 279810255 | M109: 343044544
A110: KRAFTON HQ | B110: 125012667 | C110: 103926995 | D110: 97483312 | E110: 93093113 | F110: 92176982 | G110: 98037212 | H110: 105744448 | I110: 116879209 | J110: 165409830 | K110: 138627807 | L110: 131221621 | M110: 167286392
A111: Mad Glory | H111: 591194 | I111: 651070 | J111: 777813 | K111: 805333 | L111: 892829 | M111: 921321
A112: PUBG NewState | B112: 111262 | C112: 106849 | D112: 137782 | E112: 140478 | F112: 107409 | G112: 15660 | H112: 6611 | I112: 6804 | J112: 6665 | K112: 6628 | L112: 6617 | M112: 7030
A113: PUBG STUDIO | B113: 132551808 | C113: 131342991 | D113: 207572339 | E113: 134565092 | F113: 121875592 | G113: 117556032 | H113: 134067303 | I113: 127817756 | J113: 120803051 | K113: 143164151 | L113: 145010082 | M113: 172622453
A114: SDS | B114: 3180612 | C114: 3100988 | D114: 2554036 | E114: 2653663 | F114: 1930451 | G114: 1474263 | H114: 1606937 | I114: 1642895 | J114: 1513883 | K114: 1652352 | L114: 2679106 | M114: 2207348
A115: GCP | B115: 674517878 | C115: 52358323 | D115: 67592162 | E115: 54180851 | F115: 58787177 | G115: 79184537 | H115: 1.1241661e+08 | I115: 449695943 | J115: 318857559 | K115: 193370171 | L115: 262708856 | M115: 1126298034
A116: KRAFTON HQ | B116: 674517878 | C116: 52358323 | D116: 67592162 | E116: 54180851 | F116: 58787177 | G116: 79184537 | H116: 1.1241661e+08 | I116: 449695943 | J116: 318857559 | K116: 193370171 | L116: 262708856 | M116: 1126298034
...

Sheet ToDo
A1: provider | B1: entity | C1: ID | D1: cost USD | E1: cost KRW (exc VAT) | F1: 과금내역수신여부 | G1: 검수마감 | H1: 세금계산서요청 | I1: 세금계산서수신여부 | J1: 송장헤더 | K1: 송장 항목 | L1: 송장승인제출 | M1: 자회사청구(concur 3.불공제) - 25일경
A2: Akamai | B2: KRAFTON HQ | E2: 429920311 | M2: n/a
A3: AWS | B3: KRAFTON HQ | E3: 2999851500 | F3: V | G3: V | H3: V | I3: V | J3: V | K3: V | L3: V | M3: KRAFTON Americas(146,182원), PUBG Mad Glory(20,797,881원), Montreal Studio(3,771,584원), inZOI(9,443원), SDS(26,440,842원), Tango Gameworks(766,731원), Nautilus(1,435,706원), OmniCraftlabs(11,112원), KRAFTON India(1,620,872원), JofSoft(6,985원), NineB(1,789,499원), OliveTree Games(796,456원) | O3: 7654818
A4: AWS | B4: Research | E4: 69007423 | F4: V | G4: V | H4: V | I4: V | J4: V | K4: V | L4: V | M4: 연구소 비용으로 계산서 분리 | O4: 3335034
A5: AWS | B5: DLD | E5: 3578577321 | M5: 국책과제 비용으로 계산서 분리
A6: AWS | B6: GPU SP 잔금 | M6: 국책과제 비용으로 계산서 분리
A7: AWS | B7: BLUEHOLE | E7: 14687809 | F7: V | G7: V | H7: V | I7: V | J7: V | K7: V | L7: V | M7: n/a | O7: 79400785
A8: Azure | B8: KRAFTON HQ | E8: 4036518236 | F8: V | H8: V | M8: Montreal Studio(20,331원), Krafton Europe B.V.(246원)
A9: Azure | B9: Research | E9: 153943016 | F9: V | H9: V | M9: 연구소 비용으로 계산서 분리
A10: Azure | B10: BLUEHOLE | E10: 24438009 | F10: V | H10: V | M10: n/a
A11: Datadog | B11: KRAFTON HQ | E11: 279810255 | M11: PUBG Mad Glory(892,829원), SDS(2,679,106원)
A12: Datadog | B12: BLUEHOLE | E12: 632896 | M12: n/a
A13: GCP | B13: KRAFTON HQ | E13: 262708856 | F13: V | G13: V | H13: V | I13: V | J13: V | K13: V | L13: V | M13: KRAFTON Americas(189원), OVERDARE KOREA, Inc.(2,493원), 5Minlab(129,914원) | O13: 4614580
A14: GWS | B14: KRAFTON HQ | C14: GWS | E14: =921417+10657674 -> 11579091 | F14: V | G14: V | H14: V | I14: V | J14: V | K14: V | L14: V | M14: KRAFTON JAPAN, Inc.(994,716원), Krafton Americas, Inc(568,409원), PUBG India(532,884원), Krafton Europe B.V.(319,730원), KRAFTON MONTREAL STUDIO, INC.(106,577원), PUBG Madglory(106,577원), Bluehole Studio, Inc.(71,051원), OVERDARE KOREA, Inc.(71,051원), NAUTILUS MOBILE APP PRIVATE LIMITED(35,526원) | N14: =310.5*N16 -> 423366.75
A15: GWS | B15: KRAFTON HQ | C15: Gemini&AI Ultra | E15: 46183254 | F15: V | G15: V | H15: V | I15: V | J15: V | K15: V | L15: V | M15: inZOI Studio, Inc.(2,167,060원), Krafton Americas, Inc.(710,512원), KRAFTON CHINA(177,628원), KRAFTON EUROPE B.V.(497,358원), KRAFTON INDIA(603,935원), KRAFTON MONTREAL STUDIO, INC.(35,526원), OmniCraft Labs, Inc.(994,716원), PUBG Mad Glory, LLC(213,153원), RisingWings, Inc.(1,136,819원), Striking Distance Studios Spain, S.L.(71,051원)
A16: Tencent | B16: KRAFTON HQ | E16: 469289205 | F16: V | H16: V | I16: V | L16: V | N16: 1363.5
A17: Tencent | B17: BLUEHOLE
A18: Yandex | B18: KRAFTON HQ | D18: 63576.28 | E18: 87099504 | F18: V | H18: V | I18: V | L18: V
E19: =SUM(E2:E18) -> 12464246686
D20: yandex 제외(USD) | E20: =SUM(E2:E17) -> 12377147182 | M20: =145778+21074628+3427707+49638086+875797+4336445+12032 -> 79510473
D21: Gemini 제외(SW) | M21: =1505713+16318 -> 1522031
M22: =E3-M20-M21 -> 2918818996
C32: 담당자 | D32: 제품 | E32: 제조사 | F32: Entity | G32: 진행상황 | H32: 금액
C33: 이윤슬 | D33: Akamai | E33: Akamai | F33: 크래프톤 | H33: =SUM(E2:E2) -> 429920311
D34: 메가존클라우드 | E34: Datadog | F34: 크래프톤 | H34: =E11 -> 279810255
F35: Bluehole | H35: =E12 -> 632896
D36: SK | E36: 크래프톤 | F36: 크래프톤 | H36: =E8 -> 4036518236
E37: Research | F37: 크래프톤(Research) | H37: =E9 -> 153943016
E38: Bluehole | F38: Bluehole | H38: =E10 -> 24438009
D39: SK | E39: Tencent | F39: 크래프톤 | H39: =E16 -> 469289205
D40: Iron Hive doo Beograd | E40: Yandex | F40: 크래프톤 | H40: =E18 -> 87099504
D41: GS 네오텍 | E41: AWS | F41: 크래프톤 | H41: =SUM(E3,E5:E5) -> 6578428821
F42: 크래프톤(Research) | H42: =E4 -> 69007423
F43: Bluehole | H43: =E7 -> 14687809
D44: LG CNS | E44: GCP | F44: 크래프톤 | H44: =E13 -> 262708856
E45: GWS | F45: 크래프톤 | H45: =E14 -> 11579091
E46: Gemini | F46: 크래프톤 | H46: =E15 -> 46183254
F47: KRW | H47: =SUM(H33:H46)-H40 -> 12377147182
F48: USD | H48: =D18 -> 63576.28

Sheet Akamai
A1: Please don't change this sheet and data. If necessary, contact Chaewon Jung via Slack 1:1 DM.
A2: Account ID | B2: Provider | C2: Entity | D2: Studio | E2: Team | F2: Project | G2: Owner | H2: Cost verifier | I2: comment | J2: contact verifed?
A3: Dark&DarkerMoblie | B3: Akamai | C3: KRAFTON HQ | D3: KRAFTON HQ | E3: Publishing Tech PM Part | F3: Dark and Darker_Mobile | G3: 김정언 | H3: 김정언 | J3: v
A4: NitroSmash | B4: Akamai | C4: KRAFTON HQ | D4: KRAFTON HQ | E4: Publishing Tech PM Part | F4: OVERHEAD/OTHERS | G4: 김정언 | H4: 김정언
A5: XTRM | B5: Akamai | C5: KRAFTON HQ | D5: PUBG NewState | E5: [N/A]New State Dev Div. | F5: PUBG:NEW STATE | G5: 최진욱 | H5: 김태완 | J5: v
A6: NewStateMobile | B6: Akamai | C6: KRAFTON HQ | D6: PUBG NewState | E6: [N/A]New State Dev Div. | F6: PUBG:NEW STATE | G6: 최진욱 | H6: 김태완
A7: IT Dept | B7: Akamai | C7: KRAFTON HQ | D7: KRAFTON HQ | E7: IT Dept. | F7: OVERHEAD/OTHERS | G7: 백용원 | H7: 백용원
A8: PUBGM Mobile (BGMI) | B8: Akamai | C8: KRAFTON HQ | D8: KRAFTON HQ | E8: BGMI DevOps Team | F8: BATTLEGROUNDS_MOBILE | G8: 이돈현 | H8: 이돈현 | J8: v
A9: @PUBG Mobile | B9: Akamai | C9: KRAFTON HQ | D9: KRAFTON HQ | E9: BGMI DevOps Team | F9: BATTLEGROUNDS_MOBILE_IN | G9: 이돈현 | H9: 이돈현 | J9: v
A10: PUBG India | B10: Akamai | C10: KRAFTON HQ | D10: KRAFTON HQ | E10: BGMI DevOps Team | F10: (2022)BATTLEGROUNDS_MOBILE_IN | G10: 이돈현 | H10: 이돈현
A11: SSL Network Access-Third-party - VIP | B11: Akamai | C11: KRAFTON HQ | D11: KRAFTON HQ | E11: IT Dept. | F11: OVERHEAD/OTHERS | G11: 이윤슬 | H11: 이윤슬 | J11: v
A12: Global Traffic Management | B12: Akamai | C12: KRAFTON HQ | D12: KRAFTON HQ | E12: IT Dept. | F12: OVERHEAD/OTHERS | G12: 이윤슬 | H12: 이윤슬
A13: Protect&Perform SOA with Premium | B13: Akamai | C13: KRAFTON HQ | D13: KRAFTON HQ | E13: IT Dept. | F13: OVERHEAD/OTHERS | G13: 이윤슬 | H13: 이윤슬
A14: GPP Dept | B14: Akamai | C14: KRAFTON HQ | D14: KRAFTON HQ | E14: KOS Engineering Dept. | F14: GPP | G14: 이의석 | H14: 이의석 | J14: v
A15: Migaloo | B15: Akamai | C15: OVERDARE | D15: OVERDARE | E15: OVDR Platform Engineering Team | F15: OVERHEAD/OTHERS | G15: 이제우 | H15: 이제우 | J15: v
A16: PUBG LItePC-Download | B16: Akamai | C16: KRAFTON HQ | D16: PUBG STUDIO | E16: PUBG PC&Console Dev Div. | F16: BATTLEGROUNDS_PC/CONSOLE | G16: 김정헌 | H16: 최준석 | J16: v
A17: PUBG Prod-Live Lobby | B17: Akamai | C17: KRAFTON HQ | D17: PUBG STUDIO | E17: PUBG PC&Console Dev Div. | F17: BATTLEGROUNDS_PC/CONSOLE | G17: 김정헌 | H17: 최준석 | J17: v
A18: PUBG PC/Console | B18: Akamai | C18: KRAFTON HQ | D18: KRAFTON HQ | E18: PUBG PC&Console Dev Div. | F18: BATTLEGROUNDS_PC/CONSOLE | G18: 김정헌 | H18: 최준석
A19: intra platform | B19: Akamai | C19: KRAFTON HQ | D19: KRAFTON HQ | E19: IT Dept. | F19: OVERHEAD/OTHERS | G19: 홍성철 | H19: 홍성철 | J19: v
A20: App & API Protector with Advanced Security Management Plus DSA | B20: Akamai | C20: KRAFTON HQ | D20: KRAFTON HQ | E20: IT Dept. | F20: OVERHEAD/OTHERS | G20: 정채원 | H20: Deleted | J20: v
A21: Bot Manager Premier | B21: Akamai | C21: KRAFTON HQ | D21: KRAFTON HQ | E21: IT Dept. | F21: OVERHEAD/OTHERS | G21: 정채원 | H21: Deleted | J21: v
A22: Cloud Wrapper | B22: Akamai | C22: KRAFTON HQ | D22: KRAFTON HQ | E22: IT Dept. | F22: OVERHEAD/OTHERS | G22: 정채원 | H22: Deleted | J22: v
A23: Global Traffic Management - Standard | B23: Akamai | C23: KRAFTON HQ | D23: KRAFTON HQ | E23: IT Dept. | F23: OVERHEAD/OTHERS | G23: 정채원 | H23: Deleted | J23: v
A24: Protect & Perform SOA with Premium | B24: Akamai | C24: KRAFTON HQ | D24: KRAFTON HQ | E24: IT Dept. | F24: OVERHEAD/OTHERS | G24: 정채원 | H24: Deleted | J24: v
A25: RG rerun (etc) | B25: Akamai | C25: KRAFTON HQ | D25: PUBG STUDIO | E25: PUBG Dev Div. | F25: BATTLEGROUNDS_PC/CONSOLE | G25: 정채원 | H25: Deleted | J25: v
A26: ch-BGMI | B26: Akamai | C26: KRAFTON HQ | D26: KRAFTON HQ | E26: BGMI DevOps Team | F26: BATTLEGROUNDS_MOBILE_IN | G26: 이돈현 | H26: Deleted | J26: v
A27: ch-NEWSTATE | B27: Akamai | C27: KRAFTON HQ | D27: PUBG NewState | E27: [N/A]New State Dev Div. | F27: PUBG:NEW STATE | G27: 최진욱 | H27: Deleted | J27: v
A28: ch-NEWSTATE2 | B28: Akamai | C28: KRAFTON HQ | D28: PUBG NewState | E28: [N/A]New State Dev Div. | F28: PUBG:NEW STATE | G28: 최진욱 | H28: Deleted | J28: v
A29: ch-PUBG | B29: Akamai | C29: KRAFTON HQ | D29: PUBG STUDIO | E29: PUBG PC&Console Dev Div. | F29: BATTLEGROUNDS_PC/CONSOLE | G29: 김정헌 | H29: Deleted | J29: v
A30: ch-OTHERS | B30: Akamai | C30: KRAFTON HQ | D30: KRAFTON HQ | E30: IT Dept. | F30: OVERHEAD/OTHERS | G30: 정채원 | H30: Deleted | J30: v
A31: CH-DD | B31: Akamai | C31: KRAFTON HQ | D31: KRAFTON HQ | E31: Publishing Tech PM Part | F31: Dark and Darker_Mobile | G31: 김정언 | H31: Deleted | J31: v

Sheet AWS
A1: Please don't change this sheet and data. If necessary, contact Chanewon Jung via Slack 1:1 DM.
A2: Account | B2: Provider | C2: Entity | D2: Studio | E2: Team | F2: Project | G2: Owner | H2: Cost verifier | I2: comment | J2: Team code | K2: Project code
A3: aws_ab-anticheat-service@bluehole.net(799954618127) | B3: AWS | C3: KRAFTON HQ | D3: PUBG STUDIO | E3: Game Security Engineering Dept. | F3: Dark and Darker_Mobile | G3: 황범석 | H3: 황범석 | I3: AB 안티치트 서비스용 사용예정 (24년 1분기부터) | J3: =VLOOKUP(표4[[#This Row],[Team]],표1[[내역]:[코스트 센터]],2,0) -> 100415 | K3: =VLOOKUP(표4[[#This Row],[Project]],표2[],2,0) -> P100030073
A4: aws_bcp_prd@bluehole.net(439802505510) | B4: AWS | C4: KRAFTON HQ | D4: KRAFTON HQ | E4: IT Dept. | F4: OVERHEAD/OTHERS | G4: 김승훈 | H4: 김승훈 | J4: =VLOOKUP(표4[[#This Row],[Team]],표1[[내역]:[코스트 센터]],2,0) -> 100036 | K4: =VLOOKUP(표4[[#This Row],[Project]],표2[],2,0) -> I100099999
A5: AWS_blackbox-dev@sds.com(659459735321) | B5: AWS | C5: KRAFTON HQ | D5: SDS | E5: Striking Distance Studios | F5: The Callisto Protocol | G5: Minkz Ngo | H5: Jordan Yerkes | J5: =VLOOKUP(표4[[#This Row],[Team]],표1[[내역]:[코스트 센터]],2,0) -> 100561 | K5: =VLOOKUP(표4[[#This Row],[Project]],표2[],2,0) -> P100010013
A6: aws_blue@bluehole.net(611812385851) | B6: AWS | C6: KRAFTON HQ | D6: InZOI Studio | E6: inZOI Server Team | F6: inZOI | G6: 조재욱 | H6: 조재욱 | I6: 24' 11월 Account Owner 를 이상문님에서 조재욱님으로 변경합니다 25' 1월 GS Credit 적용 시작 예정 | J6: =VLOOKUP(표4[[#This Row],[Team]],표1[[내역]:[코스트 센터]],2,0) -> #N/A | K6: =VLOOKUP(표4[[#This Row],[Project]],표2[],2,0) -> P100010055
A7: aws_cloudtrail_dev@bluehole.net(642623655767) | B7: AWS | C7: KRAFTON HQ | D7: KRAFTON HQ | E7: IT Dept. | F7: OVERHEAD/OTHERS | G7: 염화음 | H7: 유영빈 | I7: 1월 중 삭제 예정 | J7: =VLOOKUP(표4[[#This Row],[Team]],표1[[내역]:[코스트 센터]],2,0) -> 100036 | K7: =VLOOKUP(표4[[#This Row],[Project]],표2[],2,0) -> I100099999
A8: AWS_data-tech@krafton.com(272510915182) | B8: AWS | C8: KRAFTON HQ | D8: KRAFTON HQ | E8: Data Engineering Dept. | F8: OVERHEAD/OTHERS | G8: 염화음 | H8: 김시훈 | I8: https://ask.krafton.com/browse/ASKIT-27917, ASKIT-24823 유영빈님이 담당자 변경요청 | J8: =VLOOKUP(표4[[#This Row],[Team]],표1[[내역]:[코스트 센터]],2,0) -> 100212 | K8: =VLOOKUP(표4[[#This Row],[Project]],표2[],2,0) -> I100099999
A9: aws_de_mturk@krafton.com(036022206166) | B9: AWS | C9: Research | D9: Research | E9: AI research center | F9: OVERHEAD/OTHERS | G9: 김범수 | H9: 김범수 | I9: https://ask.krafton.com/browse/ASKIT-38494 | J9: =VLOOKUP(표4[[#This Row],[Team]],표1[[내역]:[코스트 센터]],2,0) -> 100677 | K9: =VLOOKUP(표4[[#This Row],[Project]],표2[],2,0) -> I100099999
A10: AWS_DLD_dev@bluehole.net(171503962539) | B10: AWS | C10: Research | D10: Research | E10: ML Sys & Ops Team | F10: DEEP LEARNING | G10: 이동기 | H10: 김지윤 | I10: https://ask.krafton.com/browse/ASKIT-29089/https://ask.krafton.com/browse/ASKIT-29089, https://jira.krafton.com/browse/ASKIT-24249 | J10: =VLOOKUP(표4[[#This Row],[Team]],표1[[내역]:[코스트 센터]],2,0) -> 100810 | K10: =VLOOKUP(표4[[#This Row],[Project]],표2[],2,0) -> I100090817
A11: AWS_DLD_Prod@bluehole.net(696280989469) | B11: AWS | C11: Research | D11: Research | E11: Data Engineering Dept. | F11: DEEP LEARNING | G11: 유상규 | H11: 유상규 | I11: 24년1~2월에 비용 많이 증가한다고 함 6/5 close/ 삭제 | J11: =VLOOKUP(표4[[#This Row],[Team]],표1[[내역]:[코스트 센터]],2,0) -> 100212 | K11: =VLOOKUP(표4[[#This Row],[Project]],표2[],2,0) -> I100090817
A12: aws_engineering_security@bluehole.net(635942867251) | B12: AWS | C12: KRAFTON HQ | D12: KRAFTON HQ | E12: Security Dept. | F12: OVERHEAD/OTHERS | G12: 홍준화 | H12: 홍준화 | J12: =VLOOKUP(표4[[#This Row],[Team]],표1[[내역]:[코스트 센터]],2,0) -> 101451 | K12: =VLOOKUP(표4[[#This Row],[Project]],표2[],2,0) -> I100099999
A13: aws_esports_streaming@bluehole.net(559478286890) | B13: AWS | C13: KRAFTON HQ | D13: KRAFTON HQ | E13: DevData Engineering Team | F13: BATTLEGROUNDS_PC/CONSOLE | G13: 안연주 | H13: 안연주 | I13: PUBG e-sports Console 대회용 서비스 | J13: =VLOOKUP(표4[[#This Row],[Team]],표1[[내역]:[코스트 센터]],2,0) -> 101721 | K13: =VLOOKUP(표4[[#This Row],[Project]],표2[],2,0) -> P100010012
A14: AWS_FF@bluehole.net(257405109560) | B14: AWS | C14: BLUEHOLE | D14: BLUEHOLE | E14: [N/A] AB Unit | F14: Dark and Darker_Mobile | G14: 이민재 | H14: 이민재 | I14: 담당자 변경 : 김현철 -> 이민재https://ask.krafton.com/browse/ASKIT-34027 FF는 블루홀(개발)/LIVE는 크래프톤(퍼블리싱)-BGMI팀 | J14: =VLOOKUP(표4[[#This Row],[Team]],표1[[내역]:[코스트 센터]],2,0) -> 110099 | K14: =VLOOKUP(표4[[#This Row],[Project]],표2[],2,0) -> P100030073
A15: aws_gamesight@bluehole.net(171101943282) | B15: AWS | C15: KRAFTON HQ | D15: KRAFTON HQ | E15: Data Engineering Dept. | F15: OVERHEAD/OTHERS | G15: 염화음 | H15: 김시훈 | J15: =VLOOKUP(표4[[#This Row],[Team]],표1[[내역]:[코스트 센터]],2,0) -> 100212 | K15: =VLOOKUP(표4[[#This Row],[Project]],표2[],2,0) -> I100099999
A16: aws_krafton_id@bluehole.net(853221784203) | B16: AWS | C16: KRAFTON HQ | D16: KRAFTON HQ | E16: KOS Engineering Dept. | F16: GPP | G16: 신근우 | H16: 신근우 | I16: aws_krafton_id@bluehole.net(853221784203) -> aws_krafton_id@bluehole.net(853221784203)으로 변경 | J16: =VLOOKUP(표4[[#This Row],[Team]],표1[[내역]:[코스트 센터]],2,0) -> 100025 | K16: =VLOOKUP(표4[[#This Row],[Project]],표2[],2,0) -> I100090813
A17: AWS_India-Esports@pubg.com(132802523425) | B17: AWS | C17: KRAFTON HQ | D17: KRAFTON HQ | E17: Service Devops Team | F17: BATTLEGROUNDS_MOBILE | G17: 양장수 | H17: 양장수 | I17: 24' 5/7 account close 완료 | J17: =VLOOKUP(표4[[#This Row],[Team]],표1[[내역]:[코스트 센터]],2,0) -> 100033 | K17: =VLOOKUP(표4[[#This Row],[Project]],표2[],2,0) -> P100030012
A18: AWS_india_publishing@bluehole.net(397907563279) | B18: AWS | C18: KRAFTON HQ | D18: PUBG STUDIO | E18: [N/A] IN Publishing Production Team_HQ | F18: BULLET ECHO | G18: 박지현 | H18: 박지현 | I18: Amplitude 라이선스 구매용/김종환님이신청은했으나 윤슬님 확인 가능-> 박지연님 | J18: =VLOOKUP(표4[[#This Row],[Team]],표1[[내역]:[코스트 센터]],2,0) -> 101716 | K18: =VLOOKUP(표4[[#This Row],[Project]],표2[],2,0) -> P100030851
A19: aws_krafton_ded@bluehole.net(333537382729) | B19: AWS | C19: KRAFTON HQ | D19: KRAFTON HQ | E19: Data Engineering Dept. | F19: OVERHEAD/OTHERS | G19: 염화음 | H19: 김시훈 | J19: =VLOOKUP(표4[[#This Row],[Team]],표1[[내역]:[코스트 센터]],2,0) -> 100212 | K19: =VLOOKUP(표4[[#This Row],[Project]],표2[],2,0) -> I100099999
A20: aws-krafton-ddm-live@krafton.com(975050331843) | B20: AWS | C20: KRAFTON HQ | D20: KRAFTON HQ | E20: Publishing Tech PM Part | F20: Dark and Darker_Mobile | G20: 김정언 | H20: 김정언 | I20: Bluehole AB(DDM) Live 서비스용 AWS 계정/aws-krafton-ddm-live@krafton.com(975050331843)->aws-krafton-ddm-stg@bluehole.net(975050331843)으로 변경 | J20: =VLOOKUP(표4[[#This Row],[Team]],표1[[내역]:[코스트 센터]],2,0) -> 101269 | K20: =VLOOKUP(표4[[#This Row],[Project]],표2[],2,0) -> P100030073
A21: aws_krafton-service-dev-project@bluehole.net(921970894603) | B21: AWS | C21: Research | D21: Research | E21: AI Product Dev Chapter Dept. | F21: DEEP LEARNING | G21: 권승진 | H21: 박준규 | J21: =VLOOKUP(표4[[#This Row],[Team]],표1[[내역]:[코스트 센터]],2,0) -> 102159 | K21: =VLOOKUP(표4[[#This Row],[Project]],표2[],2,0) -> I100090817
A22: aws_kraftonde-sensitive@krafton.com(226547056751) | B22: AWS | C22: KRAFTON HQ | D22: KRAFTON HQ | E22: Data Engineering Dept. | F22: OVERHEAD/OTHERS | G22: 염화음 | H22: 김시훈 | I22: https://ask.krafton.com/browse/ASKIT-27917, ASKIT-24823 유영빈님이 담당자 변경요청, https://ask.krafton.com/browse/ASKIT-38495 | J22: =VLOOKUP(표4[[#This Row],[Team]],표1[[내역]:[코스트 센터]],2,0) -> 100212 | K22: =VLOOKUP(표4[[#This Row],[Project]],표2[],2,0) -> I100099999
A23: AWS_log@krafton.com(873854150592) | B23: AWS | C23: KRAFTON HQ | D23: KRAFTON HQ | E23: KRAFTON HQ | F23: OVERHEAD/OTHERS | G23: 정채원 | H23: Deleted(25.5) | I23: 25.5.16 삭제완료SDS에서 삭제요청했음. 9/30 - 승훈님 확인 | J23: =VLOOKUP(표4[[#This Row],[Team]],표1[[내역]:[코스트 센터]],2,0) -> 100009 | K23: =VLOOKUP(표4[[#This Row],[Project]],표2[],2,0) -> I100099999
A24: aws_migaloo-data@bluehole.net(231111506266) | B24: AWS | C24: OVERDARE | D24: OVERDARE | E24: OVDR GTM Team | F24: OVERHEAD/OTHERS | G24: Deleted | H24: Deleted | I24: 삭제요청 받았음. 그래서 삭제 예정 | J24: =VLOOKUP(표4[[#This Row],[Team]],표1[[내역]:[코스트 센터]],2,0) -> #N/A | K24: =VLOOKUP(표4[[#This Row],[Project]],표2[],2,0) -> I100099999
A25: aws_na_devops@bluehole.net(367916776138) | B25: AWS | C25: KRAFTON HQ | D25: Mad Glory | E25: Valor Art Dept. | F25: Valor_Console | G25: Arthur Low (AJ) | H25: Arthur Low (AJ) | I25: Please move ownership to rolmstead@pubg.com - this is being used by MadGlory in Madison, not Krafton Americas Inc | J25: =VLOOKUP(표4[[#This Row],[Team]],표1[[내역]:[코스트 센터]],2,0) -> 100762 | K25: =VLOOKUP(표4[[#This Row],[Project]],표2[],2,0) -> P100020081
A26: AWS_napubtech-prod@bluehole.net(088833367732) | B26: AWS | C26: KRAFTON HQ | D26: KRAFTON HQ | E26: KOS Engineering Dept. | F26: GPP | G26: 신근우 | H26: 신근우 | I26: Hiren Chatrola -> 신근우님으로 변경 (24.8.20 신근우님요청) | J26: =VLOOKUP(표4[[#This Row],[Team]],표1[[내역]:[코스트 센터]],2,0) -> 100025 | K26: =VLOOKUP(표4[[#This Row],[Project]],표2[],2,0) -> I100090813
A27: AWS_napubtech-stage@bluehole.net(510906392559) | B27: AWS | C27: KRAFTON HQ | D27: KRAFTON HQ | E27: KOS Engineering Dept. | F27: GPP | G27: 신근우 | H27: 신근우 | I27: Hiren Chatrola -> 신근우님으로 변경 (24.8.20 신근우님요청) | J27: =VLOOKUP(표4[[#This Row],[Team]],표1[[내역]:[코스트 센터]],2,0) -> 100025 | K27: =VLOOKUP(표4[[#This Row],[Project]],표2[],2,0) -> I100090813
A28: aws_nft_sbx_central@bluehole.net(768255055847) | B28: AWS | C28: OVERDARE | D28: OVERDARE | E28: SBX Platform Team | F28: OVERHEAD/OTHERS | G28: 이제우 | H28: 이제우 | J28: =VLOOKUP(표4[[#This Row],[Team]],표1[[내역]:[코스트 센터]],2,0) -> #N/A | K28: =VLOOKUP(표4[[#This Row],[Project]],표2[],2,0) -> I100099999
A29: aws_nft_sbx_dev@bluehole.net(833221979697) | B29: AWS | C29: OVERDARE | D29: OVERDARE | E29: OVDR Platform Engineering Team | F29: OVERHEAD/OTHERS | G29: 이제우 | H29: 이제우 | J29: =VLOOKUP(표4[[#This Row],[Team]],표1[[내역]:[코스트 센터]],2,0) -> 460005 | K29: =VLOOKUP(표4[[#This Row],[Project]],표2[],2,0) -> I100099999
A30: aws_pbb_dev@bluehole.net(634885311994) | B30: AWS | C30: KRAFTON HQ | D30: PUBG STUDIO | E30: Black Budget Div. | F30: BLACK BUDGET | G30: 조원빈 | H30: 조원빈 | J30: =VLOOKUP(표4[[#This Row],[Team]],표1[[내역]:[코스트 센터]],2,0) -> 100829 | K30: =VLOOKUP(표4[[#This Row],[Project]],표2[],2,0) -> P100010048
A31: aws_pbb_it@krafton.com(767398044467) | B31: AWS | C31: KRAFTON HQ | D31: PUBG STUDIO | E31: IT Dept. | F31: BLACK BUDGET | G31: 이윤슬 | H31: 이윤슬 | I31: PBB related systems. Perforce EU, US. ASK-18720. created by Jan 28 2024 | J31: =VLOOKUP(표4[[#This Row],[Team]],표1[[내역]:[코스트 센터]],2,0) -> 100036 | K31: =VLOOKUP(표4[[#This Row],[Project]],표2[],2,0) -> P100010048
A32: AWS_Phoenix-Build@sds.com(245762466130) | B32: AWS | C32: KRAFTON HQ | D32: SDS | E32: Striking Distance Studios | F32: The Callisto Protocol | G32: Minkz Ngo | H32: Jordan Yerkes | J32: =VLOOKUP(표4[[#This Row],[Team]],표1[[내역]:[코스트 센터]],2,0) -> 100561 | K32: =VLOOKUP(표4[[#This Row],[Project]],표2[],2,0) -> P100010013
A33: AWS_Phoenix-Dev@sds.com(596361038250) | B33: AWS | C33: KRAFTON HQ | D33: SDS | E33: Striking Distance Studios | F33: The Callisto Protocol | G33: Minkz Ngo | H33: Jordan Yerkes | J33: =VLOOKUP(표4[[#This Row],[Team]],표1[[내역]:[코스트 센터]],2,0) -> 100561 | K33: =VLOOKUP(표4[[#This Row],[Project]],표2[],2,0) -> P100010013
A34: AWS_Phoenix-Live@sds.com(452304306221) | B34: AWS | C34: KRAFTON HQ | D34: SDS | E34: Striking Distance Studios | F34: The Callisto Protocol | G34: Minkz Ngo | H34: Jordan Yerkes | J34: =VLOOKUP(표4[[#This Row],[Team]],표1[[내역]:[코스트 센터]],2,0) -> 100561 | K34: =VLOOKUP(표4[[#This Row],[Project]],표2[],2,0) -> P100010013
A35: AWS_Phoenix-Prod@sds.com(878436247507) | B35: AWS | C35: KRAFTON HQ | D35: SDS | E35: Striking Distance Studios | F35: The Callisto Protocol | G35: Minkz Ngo | H35: Jordan Yerkes | J35: =VLOOKUP(표4[[#This Row],[Team]],표1[[내역]:[코스트 센터]],2,0) -> 100561 | K35: =VLOOKUP(표4[[#This Row],[Project]],표2[],2,0) -> P100010013
A36: aws_pubg_anticheat_service@bluehole.net(843438412681) | B36: AWS | C36: KRAFTON HQ | D36: KRAFTON HQ | E36: Game Security Engineering Dept. | F36: BATTLEGROUNDS_PC/CONSOLE | G36: 황범석 | H36: 황범석 | I36: PUBG PC/CONSOLE 안티치트 서비스용 사용중입니다. (23년 11월부터 aws_brodev에서 분리) | J36: =VLOOKUP(표4[[#This Row],[Team]],표1[[내역]:[코스트 센터]],2,0) -> 100415 | K36: =VLOOKUP(표4[[#This Row],[Project]],표2[],2,0) -> P100010012
A37: aws_pubg-arc-project@pubg.com(730335195506) | B37: AWS | C37: KRAFTON HQ | D37: PUBG STUDIO | E37: MS DevOps Team | F37: OVERHEAD/OTHERS | G37: 천궁원 | H37: 최보성 | J37: =VLOOKUP(표4[[#This Row],[Team]],표1[[내역]:[코스트 센터]],2,0) -> 100774 | K37: =VLOOKUP(표4[[#This Row],[Project]],표2[],2,0) -> I100099999
A38: aws_pubg_platform@bluehole.net(017103636613) | B38: AWS | C38: KRAFTON HQ | D38: KRAFTON HQ | E38: Platform Dept. | F38: BATTLEGROUNDS_PC/CONSOLE | G38: 김정헌 | H38: 최준석 | J38: =VLOOKUP(표4[[#This Row],[Team]],표1[[내역]:[코스트 센터]],2,0) -> 100355 | K38: =VLOOKUP(표4[[#This Row],[Project]],표2[],2,0) -> P100010012
A39: aws_pubg-anticheat@bluehole.net(480544169436) | B39: AWS | C39: KRAFTON HQ | D39: KRAFTON HQ | E39: Game Security Engineering Dept. | F39: OVERHEAD/OTHERS | G39: 황범석 | H39: 황범석 | I39: 안티치트실 공용 인프라 서비스용 사용중입니다 | J39: =VLOOKUP(표4[[#This Row],[Team]],표1[[내역]:[코스트 센터]],2,0) -> 100415 | K39: =VLOOKUP(표4[[#This Row],[Project]],표2[],2,0) -> I100099999
A40: AWS_pubg-dev@pubg.com(423068853949) | B40: AWS | C40: KRAFTON HQ | D40: PUBG STUDIO | E40: PUBG PC&Console Dev Div. | F40: BATTLEGROUNDS_PC/CONSOLE | G40: 김정헌 | H40: 최준석 | J40: =VLOOKUP(표4[[#This Row],[Team]],표1[[내역]:[코스트 센터]],2,0) -> 100414 | K40: =VLOOKUP(표4[[#This Row],[Project]],표2[],2,0) -> P100010012
A41: aws_pubg-devops@bluehole.net(974771722734) | B41: AWS | C41: KRAFTON HQ | D41: PUBG STUDIO | E41: Platform Dept. | F41: BATTLEGROUNDS_PC/CONSOLE | G41: 김정헌 | H41: 최준석 | J41: =VLOOKUP(표4[[#This Row],[Team]],표1[[내역]:[코스트 센터]],2,0) -> 100355 | K41: =VLOOKUP(표4[[#This Row],[Project]],표2[],2,0) -> P100010012
A42: AWS_pubg-Esports@pubg.com(054649872353) | B42: AWS | C42: KRAFTON HQ | D42: PUBG STUDIO | E42: PUBG PC&Console Dev Div. | F42: BATTLEGROUNDS_PC/CONSOLE | G42: 김정헌 | H42: 최준석 | J42: =VLOOKUP(표4[[#This Row],[Team]],표1[[내역]:[코스트 센터]],2,0) -> 100414 | K42: =VLOOKUP(표4[[#This Row],[Project]],표2[],2,0) -> P100010012
A43: AWS_PUBG-F2Pweblive@pubg.com(033775294411) | B43: AWS | C43: KRAFTON HQ | D43: KRAFTON HQ | E43: Service DevOps Team | F43: BATTLEGROUNDS_PC/CONSOLE | G43: 엄기성 | H43: 엄기성 | J43: =VLOOKUP(표4[[#This Row],[Team]],표1[[내역]:[코스트 센터]],2,0) -> 100033 | K43: =VLOOKUP(표4[[#This Row],[Project]],표2[],2,0) -> P100010012
A44: AWS_pubg-Gcoin@pubg.com(804173125569) | B44: AWS | C44: KRAFTON HQ | D44: PUBG STUDIO | E44: Data Engineering Dept. | F44: BATTLEGROUNDS_PC/CONSOLE | G44: 염화음 | H44: 김시훈 | J44: =VLOOKUP(표4[[#This Row],[Team]],표1[[내역]:[코스트 센터]],2,0) -> 100212 | K44: =VLOOKUP(표4[[#This Row],[Project]],표2[],2,0) -> P100010012
A45: AWS_pubg-playground@pubg.com(338204589111) | B45: AWS | C45: KRAFTON HQ | D45: PUBG STUDIO | E45: PUBG PC&Console Dev Div. | F45: BATTLEGROUNDS_PC/CONSOLE | G45: 김정헌 | H45: 최준석 | J45: =VLOOKUP(표4[[#This Row],[Team]],표1[[내역]:[코스트 센터]],2,0) -> 100414 | K45: =VLOOKUP(표4[[#This Row],[Project]],표2[],2,0) -> P100010012
A46: AWS_PUBGM-Esports-Live@krafton.com(633237459216) | B46: AWS | C46: KRAFTON HQ | D46: KRAFTON HQ | E46: Service DevOps Team | F46: BATTLEGROUNDS_MOBILE | G46: 엄기성 | H46: 엄기성 | J46: =VLOOKUP(표4[[#This Row],[Team]],표1[[내역]:[코스트 센터]],2,0) -> 100033 | K46: =VLOOKUP(표4[[#This Row],[Project]],표2[],2,0) -> P100030012
A47: aws_relugames@bluehole.net(309943519623) | B47: AWS | C47: ReLu Games | D47: ReLu Games | E47: ReLU Dev Dept. | F47: OVERHEAD/OTHERS | G47: 오준석 | H47: 오준석 | J47: =VLOOKUP(표4[[#This Row],[Team]],표1[[내역]:[코스트 센터]],2,0) -> #N/A | K47: =VLOOKUP(표4[[#This Row],[Project]],표2[],2,0) -> I100099999
A48: AWS_SDS-DevOps@sds.com(290246912864) | B48: AWS | C48: KRAFTON HQ | D48: SDS | E48: Striking Distance Studios | F48: The Callisto Protocol | G48: Minkz Ngo | H48: Jordan Yerkes | J48: =VLOOKUP(표4[[#This Row],[Team]],표1[[내역]:[코스트 센터]],2,0) -> 100561 | K48: =VLOOKUP(표4[[#This Row],[Project]],표2[],2,0) -> P100010013
A49: AWS_SDS-Infra@sds.com(375608835244) | B49: AWS | C49: KRAFTON HQ | D49: SDS | E49: Striking Distance Studios | F49: The Callisto Protocol | G49: Minkz Ngo | H49: Jordan Yerkes | J49: =VLOOKUP(표4[[#This Row],[Team]],표1[[내역]:[코스트 센터]],2,0) -> 100561 | K49: =VLOOKUP(표4[[#This Row],[Project]],표2[],2,0) -> P100010013
A50: aws_sds-security@bluehole.net(667131346962) | B50: AWS | C50: KRAFTON HQ | D50: SDS | E50: Striking Distance Studios | F50: The Callisto Protocol | G50: Minkz Ngo | H50: Jordan Yerkes | J50: =VLOOKUP(표4[[#This Row],[Team]],표1[[내역]:[코스트 센터]],2,0) -> 100561 | K50: =VLOOKUP(표4[[#This Row],[Project]],표2[],2,0) -> P100010013
A51: AWS_SDS-VDI@sds.com(956486919325) | B51: AWS | C51: KRAFTON HQ | D51: SDS | E51: Striking Distance Studios | F51: The Callisto Protocol | G51: Minkz Ngo | H51: Jordan Yerkes | J51: =VLOOKUP(표4[[#This Row],[Team]],표1[[내역]:[코스트 센터]],2,0) -> 100561 | K51: =VLOOKUP(표4[[#This Row],[Project]],표2[],2,0) -> P100010013
... A53: aws_studio_m@bluehole.net(827588337044) | B53: AWS | C53: KRAFTON HQ | D53: Montreal Studio | E53: PGY_Art Cell | F53: STUDIO M | G53: Julien Copin | H53: Julien Copin | J53: =VLOOKUP(표4[[#This Row],[Team]],표1[[내역]:[코스트 센터]],2,0) -> 101695 | K53: =VLOOKUP(표4[[#This Row],[Project]],표2[],2,0) -> I100090821
A54: aws_team-endurance-dev@bluehole.net(526785180557) | B54: AWS | C54: KRAFTON HQ | D54: PUBG STUDIO | E54: Adrenaline Rush Lab Unit | F54: OVERHEAD/OTHERS | G54: 김대원 | H54: Deleted(24.7) | I54: https://ask.krafton.com/browse/ASKIT-22118 | J54: =VLOOKUP(표4[[#This Row],[Team]],표1[[내역]:[코스트 센터]],2,0) -> 101465 | K54: =VLOOKUP(표4[[#This Row],[Project]],표2[],2,0) -> I100099999
A55: aws_tech_network@bluehole.net(413470838121) | B55: AWS | C55: KRAFTON HQ | D55: KRAFTON HQ | E55: IT Dept. | F55: OVERHEAD/OTHERS | G55: 이승호 | H55: 이승호 | J55: =VLOOKUP(표4[[#This Row],[Team]],표1[[내역]:[코스트 센터]],2,0) -> 100036 | K55: =VLOOKUP(표4[[#This Row],[Project]],표2[],2,0) -> I100099999
A56: AWS_Test-Acc01@krafton.com(103463619944) | B56: AWS | C56: KRAFTON HQ | D56: KRAFTON HQ | E56: IT Dept. | F56: OVERHEAD/OTHERS | G56: 정채원 | H56: Deleted(25.5) | I56: 25.5.16 삭제완료/정채원 삭제요청 | J56: =VLOOKUP(표4[[#This Row],[Team]],표1[[내역]:[코스트 센터]],2,0) -> 100036 | K56: =VLOOKUP(표4[[#This Row],[Project]],표2[],2,0) -> I100099999
A57: AWS_Test-Acc02@krafton.com(394049916894) | B57: AWS | C57: KRAFTON HQ | D57: KRAFTON HQ | E57: IT Dept. | F57: OVERHEAD/OTHERS | G57: 정채원 | H57: Deleted(25.5) | I57: 25.5.16 삭제완료/정채원 삭제요청 | J57: =VLOOKUP(표4[[#This Row],[Team]],표1[[내역]:[코스트 센터]],2,0) -> 100036 | K57: =VLOOKUP(표4[[#This Row],[Project]],표2[],2,0) -> I100099999
A58: AWS_Titan-Build@sds.com(025476091557) | B58: AWS | C58: KRAFTON HQ | D58: SDS | E58: Striking Distance Studios | F58: The Callisto Protocol | G58: Minkz Ngo | H58: Jordan Yerkes | J58: =VLOOKUP(표4[[#This Row],[Team]],표1[[내역]:[코스트 센터]],2,0) -> 100561 | K58: =VLOOKUP(표4[[#This Row],[Project]],표2[],2,0) -> P100010013
A59: AWS_Titan-Dev@sds.com(948684412557) | B59: AWS | C59: KRAFTON HQ | D59: SDS | E59: Striking Distance Studios | F59: The Callisto Protocol | G59: Minkz Ngo | H59: Jordan Yerkes | J59: =VLOOKUP(표4[[#This Row],[Team]],표1[[내역]:[코스트 센터]],2,0) -> 100561 | K59: =VLOOKUP(표4[[#This Row],[Project]],표2[],2,0) -> P100010013
A60: AWS_Titan-Live@sds.com(668355933448) | B60: AWS | C60: KRAFTON HQ | D60: SDS | E60: Striking Distance Studios | F60: The Callisto Protocol | G60: Minkz Ngo | H60: Jordan Yerkes | J60: =VLOOKUP(표4[[#This Row],[Team]],표1[[내역]:[코스트 센터]],2,0) -> 100561 | K60: =VLOOKUP(표4[[#This Row],[Project]],표2[],2,0) -> P100010013
A61: AWS_Titan-Prod@sds.com(498442523516) | B61: AWS | C61: KRAFTON HQ | D61: SDS | E61: Striking Distance Studios | F61: The Callisto Protocol | G61: Minkz Ngo | H61: Jordan Yerkes | J61: =VLOOKUP(표4[[#This Row],[Team]],표1[[내역]:[코스트 센터]],2,0) -> 100561 | K61: =VLOOKUP(표4[[#This Row],[Project]],표2[],2,0) -> P100010013
A62: AWS_TTO-beta@pubg.com(390391905061) | B62: AWS | C62: KRAFTON HQ | D62: PUBG STUDIO | E62: Thunder Div. | F62: BATTLEGROUNDS_PC/CONSOLE | G62: Deleted | H62: Deleted | J62: =VLOOKUP(표4[[#This Row],[Team]],표1[[내역]:[코스트 센터]],2,0) -> 100351 | K62: =VLOOKUP(표4[[#This Row],[Project]],표2[],2,0) -> P100010012
A63: aws_vn_dev@bluehole.net(182073802933) | B63: AWS | C63: KRAFTON HQ | D63: Vector North | E63: Vector North Unit | F63: OVERHEAD/OTHERS | G63: Petr Matoušek | H63: Petr Matoušek | J63: =VLOOKUP(표4[[#This Row],[Team]],표1[[내역]:[코스트 센터]],2,0) -> 101214 | K63: =VLOOKUP(표4[[#This Row],[Project]],표2[],2,0) -> I100099999
A64: aws_web3_dev@bluehole.net(295140746614) | B64: AWS | C64: OVERDARE | D64: OVERDARE | E64: OVDR Tech Div. | F64: OVERHEAD/OTHERS | G64: 이상헌 | H64: 이상헌 | I64: 월 4백만원 수준 | J64: =VLOOKUP(표4[[#This Row],[Team]],표1[[내역]:[코스트 센터]],2,0) -> 460121 | K64: =VLOOKUP(표4[[#This Row],[Project]],표2[],2,0) -> I100099999
A65: AWS_WebTech@krafton.com(283281493187) | B65: AWS | C65: KRAFTON HQ | D65: KRAFTON HQ | E65: Experience Engineering Dept. | F65: OVERHEAD/OTHERS | G65: 이준호 | H65: 이준호 | I65: 비용 권한이 없습니다 / PUBG, PUBGM을 제외한 모든 프로젝트에서 사용 중입니다. https://jira.krafton.com/browse/ASKIT-25601 | J65: =VLOOKUP(표4[[#This Row],[Team]],표1[[내역]:[코스트 센터]],2,0) -> 101752 | K65: =VLOOKUP(표4[[#This Row],[Project]],표2[],2,0) -> I100099999
A66: aws_windless_dev@bluehole.net(374767687653) | B66: AWS | C66: KRAFTON HQ | D66: KRAFTON HQ | E66: PGY_Art Cell | F66: PROJECT WINDLESS | G66: Deleted | H66: Deleted | I66: 삭제confirmed | J66: =VLOOKUP(표4[[#This Row],[Team]],표1[[내역]:[코스트 센터]],2,0) -> 101695 | K66: =VLOOKUP(표4[[#This Row],[Project]],표2[],2,0) -> P100030805
A67: AWS_xtrm-acu@pubg.com(993382902515) | B67: AWS | C67: KRAFTON HQ | D67: PUBG NewState | E67: Game Security Engineering Dept. | F67: PUBG:NEW STATE | G67: 황범석 | H67: 황범석 | I67: NEWSTATE 안티치트 서비스용. 사용중입니다. | J67: =VLOOKUP(표4[[#This Row],[Team]],표1[[내역]:[코스트 센터]],2,0) -> 100415 | K67: =VLOOKUP(표4[[#This Row],[Project]],표2[],2,0) -> P100030014
A68: AWS_XTRM-NewState@pubg.com(418047124903) | B68: AWS | C68: KRAFTON HQ | D68: PUBG NewState | E68: Game Security Engineering Dept. | F68: PUBG:NEW STATE | G68: 최진욱 | H68: 김태완 | J68: =VLOOKUP(표4[[#This Row],[Team]],표1[[내역]:[코스트 센터]],2,0) -> 100415 | K68: =VLOOKUP(표4[[#This Row],[Project]],표2[],2,0) -> P100030014
A69: AWS_Xtrm-playground@pubg.com(350993443303) | B69: AWS | C69: KRAFTON HQ | D69: PUBG NewState | E69: PUBG PC&Console Dev Div. | F69: PUBG:NEW STATE | G69: 최진욱 | H69: 김태완 | J69: =VLOOKUP(표4[[#This Row],[Team]],표1[[내역]:[코스트 센터]],2,0) -> 100414 | K69: =VLOOKUP(표4[[#This Row],[Project]],표2[],2,0) -> P100030014
A70: AWS_XTRM-Web@pubg.com(312871113530) | B70: AWS | C70: KRAFTON HQ | D70: KRAFTON HQ | E70: Service DevOps Team | F70: PUBG:NEW STATE | G70: 엄기성 | H70: 엄기성 | J70: =VLOOKUP(표4[[#This Row],[Team]],표1[[내역]:[코스트 센터]],2,0) -> 100033 | K70: =VLOOKUP(표4[[#This Row],[Project]],표2[],2,0) -> P100030014
A71: AWS-Audit-Account@sds.com(881478828313) | B71: AWS | C71: KRAFTON HQ | D71: SDS | E71: Striking Distance Studios | F71: The Callisto Protocol | G71: Jordan Yerkes | H71: Jordan Yerkes | I71: 삭제 | J71: =VLOOKUP(표4[[#This Row],[Team]],표1[[내역]:[코스트 센터]],2,0) -> 100561 | K71: =VLOOKUP(표4[[#This Row],[Project]],표2[],2,0) -> P100010013
A72: aws-gpp-sandbox@krafton.com(043143570760) | B72: AWS | C72: KRAFTON HQ | D72: KRAFTON HQ | E72: KOS Engineering Dept. | F72: GPP | G72: 신근우 | H72: 신근우 | J72: =VLOOKUP(표4[[#This Row],[Team]],표1[[내역]:[코스트 센터]],2,0) -> 100025 | K72: =VLOOKUP(표4[[#This Row],[Project]],표2[],2,0) -> I100090813
A73: aws-jungle-lms@bluehole.net(628687605365) | B73: AWS | C73: KRAFTON HQ | D73: KRAFTON HQ | E73: Jungle Coaching Dept. | F73: PROJECT JUNGLE | G73: 백승현 | H73: 백승현 | I73: 새로운 정글 홈페이지 개발로 인해 10월에 비용 상승했습니다. | J73: =VLOOKUP(표4[[#This Row],[Team]],표1[[내역]:[코스트 센터]],2,0) -> 101145 | K73: =VLOOKUP(표4[[#This Row],[Project]],표2[],2,0) -> I100090820
A74: aws-fwg-chocolat@bluehole.net(738051563466) | B74: AWS | C74: Flyway Games | D74: Flyway Games | E74: Chocolat Team | F74: Chocolat | G74: 윤상구 | H74: Deleted(24.11) | I74: https://ask.krafton.com/browse/ASKIT-23771 | J74: =VLOOKUP(표4[[#This Row],[Team]],표1[[내역]:[코스트 센터]],2,0) -> 100931 | K74: =VLOOKUP(표4[[#This Row],[Project]],표2[],2,0) -> #N/A
A75: aws-krafton-braze@krafton.com(493761360527) | B75: AWS | C75: KRAFTON HQ | D75: KRAFTON HQ | E75: Data Engineering Dept. | F75: OVERHEAD/OTHERS | G75: 염화음 | H75: 김시훈 | J75: =VLOOKUP(표4[[#This Row],[Team]],표1[[내역]:[코스트 센터]],2,0) -> 100212 | K75: =VLOOKUP(표4[[#This Row],[Project]],표2[],2,0) -> I100099999
A76: aws-krafton-dld-applied@bluehole.net(847366387031) | B76: AWS | C76: KRAFTON HQ | D76: KRAFTON HQ | E76: ML Sys & Ops Team | F76: OVERHEAD/OTHERS | G76: 김동원 | H76: 김동원 | I76: https://ask.krafton.com/browse/ASKIT-29024, 정승준님 -> 김동원님 | J76: =VLOOKUP(표4[[#This Row],[Team]],표1[[내역]:[코스트 센터]],2,0) -> 100810 | K76: =VLOOKUP(표4[[#This Row],[Project]],표2[],2,0) -> I100099999
A77: aws-krafton-security@bluehole.net(205564184489) | B77: AWS | C77: KRAFTON HQ | D77: KRAFTON HQ | E77: IT Dept. | F77: OVERHEAD/OTHERS | G77: 김재윤 | H77: 김재윤 | J77: =VLOOKUP(표4[[#This Row],[Team]],표1[[내역]:[코스트 센터]],2,0) -> 100036 | K77: =VLOOKUP(표4[[#This Row],[Project]],표2[],2,0) -> I100099999
A78: AWS-Log-Archive@sds.com(766483530519) | B78: AWS | C78: KRAFTON HQ | D78: SDS | E78: Striking Distance Studios | F78: The Callisto Protocol | G78: Jordan Yerkes | H78: Jordan Yerkes | I78: 삭제 | J78: =VLOOKUP(표4[[#This Row],[Team]],표1[[내역]:[코스트 센터]],2,0) -> 100561 | K78: =VLOOKUP(표4[[#This Row],[Project]],표2[],2,0) -> P100010013
A79: aws-pubg-arc@bluehole.net(637423439253) | B79: AWS | C79: KRAFTON HQ | D79: PUBG STUDIO | E79: Arc Team | F79: OVERHEAD/OTHERS | G79: 정병철 | H79: Deleted(25.5) | J79: =VLOOKUP(표4[[#This Row],[Team]],표1[[내역]:[코스트 센터]],2,0) -> 101509 | K79: =VLOOKUP(표4[[#This Row],[Project]],표2[],2,0) -> I100099999
A80: aws-pubg-odapi@bluehole.net(731155034380) | B80: AWS | C80: KRAFTON HQ | D80: PUBG STUDIO | E80: PUBG PC&Console Dev Div. | F80: BATTLEGROUNDS_PC/CONSOLE | G80: 김정헌 | H80: 최준석 | J80: =VLOOKUP(표4[[#This Row],[Team]],표1[[내역]:[코스트 센터]],2,0) -> 100414 | K80: =VLOOKUP(표4[[#This Row],[Project]],표2[],2,0) -> P100010012
A81: aws-pubgtd-automation@bluehole.net(229951847377) | B81: AWS | C81: KRAFTON HQ | D81: PUBG STUDIO | E81: Translation Team 2 | F81: OVERHEAD/OTHERS | G81: 이경호 | H81: 이경호 | I81: 10/7 유지하는 것으로 확인 -> 슬랙 | J81: =VLOOKUP(표4[[#This Row],[Team]],표1[[내역]:[코스트 센터]],2,0) -> 100424 | K81: =VLOOKUP(표4[[#This Row],[Project]],표2[],2,0) -> I100099999
A82: aws-sandbox-fhutchinson@sds.com(312933148507) | B82: AWS | C82: KRAFTON HQ | D82: SDS | E82: Striking Distance Studios | F82: The Callisto Protocol | G82: Jordan Yerkes | H82: Jordan Yerkes | I82: 삭제 | J82: =VLOOKUP(표4[[#This Row],[Team]],표1[[내역]:[코스트 센터]],2,0) -> 100561 | K82: =VLOOKUP(표4[[#This Row],[Project]],표2[],2,0) -> P100010013
A83: aws-sandbox-jyerkes@sds.com(078595245691) | B83: AWS | C83: KRAFTON HQ | D83: SDS | E83: Striking Distance Studios | F83: The Callisto Protocol | G83: Jordan Yerkes | H83: Jordan Yerkes | I83: 삭제 | J83: =VLOOKUP(표4[[#This Row],[Team]],표1[[내역]:[코스트 센터]],2,0) -> 100561 | K83: =VLOOKUP(표4[[#This Row],[Project]],표2[],2,0) -> P100010013
A84: aws-sandbox-mtrenchard@sds.com(564290003513) | B84: AWS | C84: KRAFTON HQ | D84: SDS | E84: Striking Distance Studios | F84: The Callisto Protocol | G84: Jordan Yerkes | H84: Jordan Yerkes | I84: 삭제 | J84: =VLOOKUP(표4[[#This Row],[Team]],표1[[내역]:[코스트 센터]],2,0) -> 100561 | K84: =VLOOKUP(표4[[#This Row],[Project]],표2[],2,0) -> P100010013
A85: aws-sandbox-sfuller@sds.com(681581573890) | B85: AWS | C85: KRAFTON HQ | D85: SDS | E85: Striking Distance Studios | F85: The Callisto Protocol | G85: Jordan Yerkes | H85: Jordan Yerkes | I85: 삭제 | J85: =VLOOKUP(표4[[#This Row],[Team]],표1[[내역]:[코스트 센터]],2,0) -> 100561 | K85: =VLOOKUP(표4[[#This Row],[Project]],표2[],2,0) -> P100010013
A86: BHAWS_BRO@bluehole.net(628917336532) | B86: AWS | C86: KRAFTON HQ | D86: PUBG STUDIO | E86: PUBG PC&Console Dev Div. | F86: BATTLEGROUNDS_PC/CONSOLE | G86: 김정헌 | H86: 최준석 | J86: =VLOOKUP(표4[[#This Row],[Team]],표1[[내역]:[코스트 센터]],2,0) -> 100414 | K86: =VLOOKUP(표4[[#This Row],[Project]],표2[],2,0) -> P100010012
A87: bhaws_da@bluehole.net(218248172704) | B87: AWS | C87: BLUEHOLE | D87: BLUEHOLE | E87: [N/A]TERA | F87: TERA_CONSOLE | G87: 류현덕 | H87: 안영근 | I87: S3 게임 로그 저장및 관리 계정, 월 100만원 수준 | J87: =VLOOKUP(표4[[#This Row],[Team]],표1[[내역]:[코스트 센터]],2,0) -> 110024 | K87: =VLOOKUP(표4[[#This Row],[Project]],표2[],2,0) -> P100020001
A88: bhaws_da2@bluehole.net(456601888123) | B88: AWS | C88: BLUEHOLE | D88: BLUEHOLE | E88: [N/A]TERA | F88: TERA_CONSOLE | G88: 류현덕 | H88: 안영근 | I88: TERA PC Log -> Glacier Archive완료 및 유지관리 계정 | J88: =VLOOKUP(표4[[#This Row],[Team]],표1[[내역]:[코스트 센터]],2,0) -> 110024 | K88: =VLOOKUP(표4[[#This Row],[Project]],표2[],2,0) -> P100020001
A89: Bhaws_dbdev@bluehole.net(581185314323) | B89: AWS | C89: KRAFTON HQ | D89: KRAFTON HQ | E89: DevData Engineering Team | F89: OVERHEAD/OTHERS | G89: 김완건 | H89: 이재혁 | I89: DB R&D 용도 (팀 내부 사용) | J89: =VLOOKUP(표4[[#This Row],[Team]],표1[[내역]:[코스트 센터]],2,0) -> 101721 | K89: =VLOOKUP(표4[[#This Row],[Project]],표2[],2,0) -> I100099999
A90: BHAWS_DEDEV@bluehole.net(142757678093) | B90: AWS | C90: KRAFTON HQ | D90: KRAFTON HQ | E90: IT Dept. | F90: OVERHEAD/OTHERS | G90: 김재윤 | H90: 김재윤 | I90: Deleted 7월부터 비용발생하지 않음 | J90: =VLOOKUP(표4[[#This Row],[Team]],표1[[내역]:[코스트 센터]],2,0) -> 100036 | K90: =VLOOKUP(표4[[#This Row],[Project]],표2[],2,0) -> I100099999
A91: aws-kos@krafton.com(821843679442) | B91: AWS | C91: KRAFTON HQ | D91: KRAFTON HQ | E91: KOS Engineering Dept. | F91: GPP | G91: 신근우 | H91: 신근우 | J91: =VLOOKUP(표4[[#This Row],[Team]],표1[[내역]:[코스트 센터]],2,0) -> 100025 | K91: =VLOOKUP(표4[[#This Row],[Project]],표2[],2,0) -> I100090813
A92: bhaws_ginno@bluehole.net(477047828735) | B92: AWS | C92: KRAFTON HQ | D92: PUBG STUDIO | E92: PUBG PC&Console Dev Div. | F92: BATTLEGROUNDS_PC/CONSOLE | G92: 한상근 | H92: 최진광 | J92: =VLOOKUP(표4[[#This Row],[Team]],표1[[내역]:[코스트 센터]],2,0) -> 100414 | K92: =VLOOKUP(표4[[#This Row],[Project]],표2[],2,0) -> P100010012
A93: Bhaws_ginnosvn@bluehole.net(377253795420) | B93: AWS | C93: KRAFTON HQ | D93: KRAFTON HQ | E93: IT Dept. | F93: OVERHEAD/OTHERS | G93: 김재윤 | H93: 김재윤 | J93: =VLOOKUP(표4[[#This Row],[Team]],표1[[내역]:[코스트 센터]],2,0) -> 100036 | K93: =VLOOKUP(표4[[#This Row],[Project]],표2[],2,0) -> I100099999
A94: bhaws_intradev@bluehole.net(052342468408) | B94: AWS | C94: KRAFTON HQ | D94: KRAFTON HQ | E94: IT Dept. | F94: OVERHEAD/OTHERS | G94: 홍성철 | H94: 홍성철 | J94: =VLOOKUP(표4[[#This Row],[Team]],표1[[내역]:[코스트 센터]],2,0) -> 100036 | K94: =VLOOKUP(표4[[#This Row],[Project]],표2[],2,0) -> I100099999
A95: bhaws_kissflow@bluehole.net(612237199640) | B95: AWS | C95: KRAFTON HQ | D95: KRAFTON HQ | E95: IT Dept. | F95: OVERHEAD/OTHERS | G95: 홍성철 | H95: 홍성철 | J95: =VLOOKUP(표4[[#This Row],[Team]],표1[[내역]:[코스트 센터]],2,0) -> 100036 | K95: =VLOOKUP(표4[[#This Row],[Project]],표2[],2,0) -> I100099999
A96: bhaws_l10n@bluehole.net(432820731734) | B96: AWS | C96: KRAFTON HQ | D96: KRAFTON HQ | E96: L10N Team | F96: OVERHEAD/OTHERS | G96: 김재헌 | H96: 김진희 | J96: =VLOOKUP(표4[[#This Row],[Team]],표1[[내역]:[코스트 센터]],2,0) -> 100092 | K96: =VLOOKUP(표4[[#This Row],[Project]],표2[],2,0) -> I100099999
A97: bhaws_pubgpclitelive@bluehole.net(923284402284) | B97: AWS | C97: KRAFTON HQ | D97: PUBG STUDIO | E97: PUBG PC&Console Dev Div. | F97: BATTLEGROUNDS_PC/CONSOLE | G97: 김정헌 | H97: 최준석 | J97: =VLOOKUP(표4[[#This Row],[Team]],표1[[내역]:[코스트 센터]],2,0) -> 100414 | K97: =VLOOKUP(표4[[#This Row],[Project]],표2[],2,0) -> P100010012
A98: bhaws_si@bluehole.net(880227346986) | B98: AWS | C98: KRAFTON HQ | D98: KRAFTON HQ | E98: Service DevOps Team | F98: OVERHEAD/OTHERS | G98: 엄기성 | H98: 엄기성 | J98: =VLOOKUP(표4[[#This Row],[Team]],표1[[내역]:[코스트 센터]],2,0) -> 100033 | K98: =VLOOKUP(표4[[#This Row],[Project]],표2[],2,0) -> I100099999
A99: BHAWS_SPDev@bluehole.net(959785605440) | B99: AWS | C99: BLUEHOLE | D99: BLUEHOLE | E99: [N/A]TERA | F99: TERA_CONSOLE | G99: 이준호 | H99: 이준호 | I99: TERA는 블루홀/비용 권한이 없습니다. / Tera Console, Blueward에서 사용 중입니다. https://jira.krafton.com/browse/ASKIT-25601 | J99: =VLOOKUP(표4[[#This Row],[Team]],표1[[내역]:[코스트 센터]],2,0) -> 110024 | K99: =VLOOKUP(표4[[#This Row],[Project]],표2[],2,0) -> P100020001
A100: bhaws_tal@bluehole.net(403272232770) | B100: AWS | C100: KRAFTON HQ | D100: KRAFTON HQ | E100: Service Engineering Dept. | F100: OVERHEAD/OTHERS | G100: 박형준 | H100: Deleted(25.5) | J100: =VLOOKUP(표4[[#This Row],[Team]],표1[[내역]:[코스트 센터]],2,0) -> 100030 | K100: =VLOOKUP(표4[[#This Row],[Project]],표2[],2,0) -> I100099999
A101: bhaws_teraconsoleps@bluehole.net(569142980887) | B101: AWS | C101: BLUEHOLE | D101: BLUEHOLE | E101: T_Console Service Part | F101: TERA_CONSOLE | G101: 배인성 | H101: 배인성 | J101: =VLOOKUP(표4[[#This Row],[Team]],표1[[내역]:[코스트 센터]],2,0) -> 110119 | K101: =VLOOKUP(표4[[#This Row],[Project]],표2[],2,0) -> P100020001
...

Sheet Azure
A1: Please don't change this sheet and data. If necessary, contact Somi Choi, Chaewon Jung via Slack 1:1 DM.
A2: Account ID | B2: Provider | C2: Entity | D2: Studio | E2: Team | F2: Project | G2: Owner | H2: Cost verifier | I2: comment | J2: contact verifed?
A3: AI-Research-Deep-Learning | B3: Azure | C3: Research | D3: Research | E3: ML Sys & Ops Team | F3: DEEP LEARNING | G3: 이동기 | H3: 김지윤 | I3: https://ask.krafton.com/browse/ASKIT-29090/https://jira.krafton.com/browse/ASKIT-24250 | J3: v
A4: Azure App Service SSL Certificates - Wildcard SSL - 1 Year | B4: Azure | C4: KRAFTON HQ | D4: KRAFTON HQ | E4: IT Dept. | F4: OVERHEAD/OTHERS | G4: 유상규 | H4: 유상규 | J4: v
A5: Azure_beluga_dev | B5: Azure | C5: KRAFTON HQ | D5: KRAFTON HQ | E5: Project Beluga Dept. | F5: Project Beluga | G5: Deleted | H5: Deleted | J5: v
A6: AzureOpsLAB-DevTest-20181205 | B6: Azure | C6: KRAFTON HQ | D6: KRAFTON HQ | E6: Service DevOps Team | F6: OVERHEAD/OTHERS | G6: 엄기성 | H6: 엄기성 | J6: v
A7: AzureOpsLAB-Enterprise-20171102 | B7: Azure | C7: KRAFTON HQ | D7: KRAFTON HQ | E7: Service DevOps Team | F7: OVERHEAD/OTHERS | G7: 엄기성 | H7: 엄기성 | J7: v
A8: BEAVER-DevTest | B8: Azure | C8: KRAFTON HQ | D8: KRAFTON HQ | E8: Service DevOps Team | F8: Project Biringam | G8: Deleted | H8: Deleted | J8: v
A9: BGMI-DB-Monitoring | B9: Azure | C9: KRAFTON HQ | D9: KRAFTON HQ | E9: DevData Engineering Team | F9: (2022)BATTLEGROUNDS_MOBILE_IN | G9: 김도현 | H9: 김도현 | I9: DB Monitoring 용도 (팀 내부 사용) | J9: v
A10: bgmiops | B10: Azure | C10: KRAFTON HQ | D10: KRAFTON HQ | E10: BGMI DevOps Team | F10: (2022)BATTLEGROUNDS_MOBILE_IN | G10: 조동현 | H10: 조한경 | I10: https://ask.krafton.com/browse/ASKIT-37773 | J10: v
A11: data-accounting | B11: Azure | C11: KRAFTON HQ | D11: KRAFTON HQ | E11: Data Engineering Dept. | F11: OVERHEAD/OTHERS | G11: 염화음 | H11: 김시훈 | J11: v
A12: Data-engineering | B12: Azure | C12: KRAFTON HQ | D12: KRAFTON HQ | E12: Data Engineering Dept. | F12: OVERHEAD/OTHERS | G12: Deleted | H12: Deleted | J12: v
A13: data-tech | B13: Azure | C13: KRAFTON HQ | D13: KRAFTON HQ | E13: Data Engineering Dept. | F13: OVERHEAD/OTHERS | G13: 염화음 | H13: 김시훈 | J13: v
A14: DB-Monitoring | B14: Azure | C14: KRAFTON HQ | D14: KRAFTON HQ | E14: DevData Engineering Team | F14: OVERHEAD/OTHERS | G14: 이동준 | H14: 이동준 | I14: DB Monitoring 용도 (팀 내부 사용) | J14: v
A15: DB-Tech_BHS | B15: Azure | C15: KRAFTON HQ | D15: KRAFTON HQ | E15: DevData Engineering Team | F15: OVERHEAD/OTHERS | G15: 김도현 | H15: 김도현 | I15: DB R&D 용도 (팀 내부 사용) | J15: v
A16: EME-SUNSET-API | B16: Azure | C16: KRAFTON HQ | D16: KRAFTON HQ | E16: Service DevOps Team | F16: OVERHEAD/OTHERS | G16: 장은진 | H16: 장은진 | I16: https://ask.krafton.com/browse/ASKIT-27818,25년 5월부터 장은진님으로 변경,24년 2월부터는 정승호님이 담당 | J16: v
A17: EME-SUNSET-BACKUP | B17: Azure | C17: KRAFTON HQ | D17: KRAFTON HQ | E17: Publishing Tech PM Part | F17: OVERHEAD/OTHERS | G17: 김정언 | H17: 김정언 | J17: v
A18: ERP_SystemCell | B18: Azure | C18: KRAFTON HQ | D18: KRAFTON HQ | E18: IT Dept. | F18: OVERHEAD/OTHERS | G18: 백용원 | H18: 백용원 | I18: ERP 운영 서버 그룹 | J18: v
A19: GameDevTest2304 | B19: Azure | C19: KRAFTON HQ | D19: KRAFTON HQ | E19: Service DevOps Team | F19: OVERHEAD/OTHERS | G19: 엄기성 | H19: 엄기성 | J19: v
A20: giseongeom-DevTest | B20: Azure | C20: KRAFTON HQ | D20: KRAFTON HQ | E20: Service DevOps Team | F20: OVERHEAD/OTHERS | G20: 엄기성 | H20: 엄기성 | J20: v
A21: GitHub-Cloud-Azure-Enterprise | B21: Azure | C21: KRAFTON HQ | D21: KRAFTON HQ | E21: System Team | F21: OVERHEAD/OTHERS | G21: 백용원 | H21: 백용원 | I21: KRAFTON Github Cloud Copilot 라이선스 용도 | J21: v
A22: Grafana Cloud | B22: Azure | C22: KRAFTON HQ | D22: KRAFTON HQ | E22: Engineering Div. | F22: OVERHEAD/OTHERS | G22: Deleted | H22: Deleted | J22: v
A23: HARTH-Azure-Enterprise | B23: Azure | C23: KRAFTON HQ | D23: KRAFTON HQ | E23: Engineering Div. | F23: OVERHEAD/OTHERS | G23: 엄기성 | H23: 엄기성 | J23: v
A24: L10N | B24: Azure | C24: KRAFTON HQ | D24: KRAFTON HQ | E24: L10N Team | F24: OVERHEAD/OTHERS | G24: 김재헌 | H24: 전평준 | J24: v
A25: Overdare_VisualStudio | B25: Azure | C25: OVERDARE | D25: OVERDARE | E25: OVDR People Team | F25: OVERHEAD/OTHERS | G25: 나윤호 | H25: 나윤호 | J25: v
A26: Project-H2 | B26: Azure | C26: KRAFTON HQ | D26: KRAFTON HQ | E26: H2 Team | F26: Special Project II | G26: Deleted | H26: Deleted | J26: v
A27: Project-MC | B27: Azure | C27: Flyway Games | D27: Flyway Games | E27: Service DevOps Team | F27: Project MC | G27: 엄기성 | H27: 엄기성 | I27: 정채원:Flyway Games? | J27: v
A28: Project-TT | B28: Azure | C28: BLUEHOLE | D28: BLUEHOLE | E28: Thunder Div. | F28: OVERHEAD/OTHERS | G28: Deleted | H28: Deleted | J28: v
A29: PUBG Console | B29: Azure | C29: KRAFTON HQ | D29: PUBG STUDIO | E29: PUBG PC&Console Dev Div. | F29: BATTLEGROUNDS_PC/CONSOLE | G29: 김정헌 | H29: 최준석 | J29: v
A30: PUBG Dev | B30: Azure | C30: KRAFTON HQ | D30: PUBG STUDIO | E30: PUBG Dev Div. | F30: BATTLEGROUNDS_PC/CONSOLE | G30: Deleted | H30: Deleted | J30: v
A31: PUBG DevOps | B31: Azure | C31: KRAFTON HQ | D31: PUBG STUDIO | E31: PUBG PC&Console Dev Div. | F31: BATTLEGROUNDS_PC/CONSOLE | G31: 김정헌 | H31: 최준석 | J31: v
A32: PUBG PC | B32: Azure | C32: KRAFTON HQ | D32: PUBG STUDIO | E32: PUBG PC&Console Dev Div. | F32: BATTLEGROUNDS_PC/CONSOLE | G32: 김정헌 | H32: 최준석 | J32: v
A33: pubg_mobile | B33: Azure | C33: KRAFTON HQ | D33: KRAFTON HQ | E33: BGMI DevOps Team | F33: (2022)BATTLEGROUNDS_MOBILE_IN | G33: 조동현 | H33: 조한경 | I33: https://ask.krafton.com/browse/ASKIT-37773 | J33: v
A34: pubg_mobile_DB | B34: Azure | C34: KRAFTON HQ | D34: KRAFTON HQ | E34: Service Engineering Dept. | F34: OVERHEAD/OTHERS | G34: Deleted | H34: Deleted | I34: (김완건) 용도 모름.. 사용 안 함.. | J34: v
A35: pubg_mobile_Test | B35: Azure | C35: KRAFTON HQ | D35: KRAFTON HQ | E35: BGMI DevOps Team | F35: (2022)BATTLEGROUNDS_MOBILE_IN | G35: 조동현 | H35: 조한경 | I35: https://ask.krafton.com/browse/ASKIT-37773 | J35: v
A36: ReLU Games | B36: Azure | C36: Relu Studio | D36: ReLu Games | E36: ReLU Dev Dept. | F36: OVERHEAD/OTHERS | G36: Deleted | H36: Deleted(25.5) | J36: v
A37: ReLu_deep learning | B37: Azure | C37: Relu Studio | D37: ReLu Games | E37: ReLU Dev Dept. | F37: ReLU Games | G37: 이기문 | H37: 이기문 | J37: v
A38: Research | B38: Azure | C38: Research | D38: Research | E38: AI research center | F38: OVERHEAD/OTHERS | G38: 심재한 | H38: 심재한
A39: sbx-central | B39: Azure | C39: KRAFTON HQ | D39: OVERDARE | E39: OVDR Platform Engineering Team | F39: OVERHEAD/OTHERS | G39: Deleted | H39: Deleted(25.5) | I39: 월 1~2$ 수준으로 무시해도 됨
A40: sbx-development | B40: Azure | C40: KRAFTON HQ | D40: KRAFTON HQ | E40: OVDR Platform Engineering Team | F40: OVERHEAD/OTHERS | G40: Deleted | H40: Deleted | J40: v
A41: SDS-Azure subscription | B41: Azure | C41: KRAFTON HQ | D41: SDS | E41: Striking Distance Studios | F41: The Callisto Protocol | G41: Jordan Yerkes | H41: Jordan Yerkes
A42: Security_VDI | B42: Azure | C42: KRAFTON HQ | D42: KRAFTON HQ | E42: Security Dept. | F42: OVERHEAD/OTHERS | G42: 홍석범 | H42: 홍석범 | J42: v
A43: sp2-O2-sunpak | B43: Azure | C43: Relu Studio | D43: ReLu Games | E43: ReLU Dev Dept. | F43: OVERHEAD/OTHERS | G43: Deleted | H43: Deleted | J43: v
A44: sp2-staff | B44: Azure | C44: Relu Studio | D44: ReLu Games | E44: ReLU Dev Dept. | F44: OVERHEAD/OTHERS | G44: Deleted | H44: Deleted | J44: v
A45: sp2z3 | B45: Azure | C45: KRAFTON HQ | D45: KRAFTON HQ | E45: Z3 Team | F45: SPECIAL PROJECT II | G45: 조재욱 | H45: Deleted(25.5) | I45: 10/11 JIRA통해 조재욱님 삭제요청
A46: Special-Project-II-Team-S1-Dev | B46: Azure | C46: KRAFTON HQ | D46: KRAFTON HQ | E46: S1 Team | F46: OVERHEAD/OTHERS | G46: Deleted | H46: Deleted | J46: v
A47: StreamSets Data Collector | B47: Azure | C47: KRAFTON HQ | D47: KRAFTON HQ | E47: IT Dept. | F47: OVERHEAD/OTHERS | G47: Deleted | H47: Deleted | J47: v
A48: TRCS-AP-Azure-Enterprise | B48: Azure | C48: BLUEHOLE | D48: BLUEHOLE | E48: T_Console Service Part | F48: TERA_Console | G48: 장은진 | H48: 장은진 | I48: https://ask.krafton.com/browse/ASKIT-27818,25년 5월부터 장은진님으로 변경,24년 2월부터는 정승호님이 담당 | J48: v
A49: TRCS-AP-Azure-Enterprise-DevTest | B49: Azure | C49: BLUEHOLE | D49: BLUEHOLE | E49: T_Console Service Part | F49: TERA_Console | G49: 장은진 | H49: 장은진 | I49: https://ask.krafton.com/browse/ASKIT-27818,25년 5월부터 장은진님으로 변경,24년 2월부터는 정승호님이 담당 | J49: v
A50: TRCS-Azure-Enterprise | B50: Azure | C50: BLUEHOLE | D50: BLUEHOLE | E50: T_Console Service Part | F50: TERA_Console | G50: 장은진 | H50: 장은진 | I50: https://ask.krafton.com/browse/ASKIT-27818,25년 5월부터 장은진님으로 변경,24년 2월부터는 정승호님이 담당 | J50: v
A51: TRCS-Azure-Enterprise-DevTest | B51: Azure | C51: BLUEHOLE | D51: BLUEHOLE | E51: T_Console Service Part | F51: TERA_Console | G51: 장은진 | H51: 장은진 | I51: https://ask.krafton.com/browse/ASKIT-27818,25년 5월부터 장은진님으로 변경,24년 2월부터는 정승호님이 담당 | J51: v
A52: TRPC-DevTest | B52: Azure | C52: BLUEHOLE | D52: BLUEHOLE | E52: Publishing Tech PM Part | F52: TERA_PC | G52: 김정언 | H52: 김정언 | J52: v
A53: XTRM-data | B53: Azure | C53: KRAFTON HQ | D53: PUBG NewState | E53: [N/A]New State Dev Div. | F53: PUBG:NEW STATE | G53: 염화음 | H53: 김시훈 | J53: v
A54: xtrm-newstate | B54: Azure | C54: KRAFTON HQ | D54: PUBG NewState | E54: [N/A]New State Dev Div. | F54: PUBG:NEW STATE | G54: 최진욱 | H54: 김태완 | J54: v
A55: XTRM-Web | B55: Azure | C55: KRAFTON HQ | D55: PUBG NewState | E55: Service DevOps Team | F55: PUBG:NEW STATE | G55: 엄기성 | H55: 엄기성 | I55: https://jira.krafton.com/browse/ASKIT-18307 | J55: v
A56: AzureOpsLAB-Platform-20231227 | B56: Azure | C56: KRAFTON HQ | D56: PUBG NewState | E56: [N/A]New State Dev Div. | F56: PUBG:NEW STATE | G56: 엄기성 | H56: 엄기성
A57: data-platform | B57: Azure | C57: KRAFTON HQ | D57: KRAFTON HQ | E57: Data Engineering Dept. | F57: OVERHEAD/OTHERS | G57: 염화음 | H57: 김시훈 | I57: https://ask.krafton.com/browse/ASKIT-27918, askit-18641.Azure Databricks 분석 환경용 구독 | J57: v
A58: Flyway-visualstudio | B58: Azure | C58: Flyway Games | D58: Flyway Games | E58: Flyway Games | F58: Flyway Games | G58: 전민욱 | H58: 전민욱 | I58: https://ask.krafton.com/browse/ASKIT-28499 | J58: v
A59: relu_deeplearning_prod | B59: Azure | C59: Relu Studio | D59: Relu Studio | E59: ReLU Dev Dept. | F59: ReLU Games | G59: 이기문 | H59: 이기문
A60: relu_deeplearning_prod_secondary | B60: Azure | C60: Relu Studio | D60: Relu Studio | E60: ReLU Dev Dept. | F60: ReLU Games | G60: 이기문 | H60: 이기문
A61: ded-data-intelligence | B61: Azure | C61: KRAFTON HQ | D61: KRAFTON HQ | E61: Data Engineering Dept. | F61: OVERHEAD/OTHERS | G61: 염화음 | H61: 문중현 | I61: https://jira.krafton.com/browse/ASKIT-24250
A62: data-service | B62: Azure | C62: KRAFTON HQ | D62: KRAFTON HQ | E62: Data Engineering Dept. | F62: OVERHEAD/OTHERS | G62: 염화음 | H62: 문중현 | J62: v
A63: majesta | B63: Azure | C63: KRAFTON HQ | D63: PUBG STUDIO | E63: MS DevOps Team | F63: OVERHEAD/OTHERS | G63: 천궁원 | H63: 엄희영 | I63: 계정생성자 배시은님 확인
A64: PBB Dev | B64: Azure | C64: KRAFTON HQ | D64: PUBG STUDIO | E64: Black Budget Div. | F64: BLACK BUDGET | G64: 조원빈 | H64: 조원빈 | I64: 박경도님확인
A65: PUBG-Madison | B65: Azure | C65: KRAFTON HQ | D65: PUBG STUDIO | E65: PUBG Valor Div. | F65: Valor_console | G65: 송영재 | H65: 송영재 | I65: 송영재님 확인(slack) | J65: v
A66: EMEA_VisualStudio | B66: Azure | C66: KRAFTON EUROPE B.V. | D66: KRAFTON EUROPE B.V. | E66: EME IT Admin Part | F66: BLACK BUDGET | G66: Ben Moore | H66: Ben Moore | I66: ASKIT-19469 이윤슬님생성(visual studio)
A67: PPE-KCN | B67: Azure | C67: KRAFTON HQ | D67: KRAFTON HQ | E67: KOS Engineering Dept. | F67: OVERHEAD/OTHERS | G67: 조국환 | H67: 신근우 | I67: KCN 프로젝트의 Azure AI 서비스 리서치용
A68: WPS AI Ops Team (wps_ai_ops_team) | B68: Azure | C68: KRAFTON HQ | D68: KRAFTON EUROPE B.V. | E68: West Scale-up Dept. | F68: OVERHEAD/OTHERS | G68: Love Hedman | H68: Love Hedman | I68: West Publishing AI Ops Team internal testing
A69: DL-Service-SafeCanvas-inZOI-Publishing2 | B69: Azure | C69: KRAFTON HQ | D69: KRAFTON HQ | E69: GPD1 Publishing Coordination Team | F69: inZOI | G69: 임형진 | H69: 국용상 | I69: inzoi 에 들어갈 safe canvas (선정적정보 필터링) 기능을 위한 Azure OPENAI API 발급용
A70: DL-Service-Toxic-Filter-inZOI | B70: Azure | C70: KRAFTON HQ | D70: KRAFTON HQ | E70: Live Service Support Dept. | F70: inZOI | G70: 오명석 | H70: 오명석 | I70: Live Service Support Dept에서 사용하실 AI 채팅 검수 서비스 운영 | J70: v
A71: DL-Service-Toxic-Filter-DnDM | B71: Azure | C71: KRAFTON HQ | D71: KRAFTON HQ | E71: Live Service Support Dept. | F71: Dark and Darker_Mobile | G71: 오명석 | H71: 오명석 | I71: Live Service Support Dept에서 사용하실 AI 채팅 검수 서비스 운영 | J71: v
A72: DL-Service-SafeCanvas-inZOI-LiveOps | B72: Azure | C72: KRAFTON HQ | D72: KRAFTON HQ | E72: Live Service Support Dept. | F72: inZOI | G72: 임형진 | H72: 임형진 | I72: inzoi 에 들어갈 safe canvas (선정적정보 필터링) 기능을 위한 Azure OPENAI API 발급용 | J72: v
A73: ded-engineering | B73: Azure | C73: KRAFTON HQ | D73: KRAFTON HQ | E73: Data Engineering Dept. | F73: (2022)BATTLEGROUNDS_MOBILE_IN | G73: 염화음 | H73: 김시훈 | I73: 텐센트 측의 BGMI 요청 처리용 구독 | J73: v
A74: Nautilus_azure_sce_krafton_general | B74: Azure | C74: Nautilus | D74: Nautilus | E74: Nautilus | F74: Nautilus | G74: Mithil Bhatia | H74: Mithil Bhatia | J74: v
A75: Nautilus_azure_sce_krafton_dummytest_1 | B75: Azure | C75: Nautilus | D75: Nautilus | E75: Nautilus | F75: Nautilus | G75: Mithil Bhatia | H75: Mithil Bhatia | J75: v
A76: Nautilus_azure_sce_krafton_dummytest_2 | B76: Azure | C76: Nautilus | D76: Nautilus | E76: Nautilus | F76: Nautilus | G76: Mithil Bhatia | H76: Mithil Bhatia | J76: v
A77: xe_git_bee | B77: Azure | C77: KRAFTON HQ | D77: KRAFTON HQ | E77: Experience Engineering Dept. | F77: OVERHEAD/OTHERS | G77: 허지호 | H77: 이준호 | I77: LLM을 사용한 코드리뷰를 위해 Azure OpenAI Service 사용 | J77: v
A78: ART_ALI_Vision | B78: Azure | C78: KRAFTON HQ | D78: KRAFTON HQ | E78: Art Management Part | F78: OVERHEAD/OTHERS | G78: 배준석 | H78: 배준석 | J78: v
A79: MRSO | B79: Azure | C79: KRAFTON HQ | D79: KRAFTON HQ | E79: Milestone Review Support Office | F79: OVERHEAD/OTHERS | G79: 송진나 | H79: 송진나 | I79: https://ask.krafton.com/browse/ASKIT-37599
A80: ART_ALI_CustomVision | B80: Azure | C80: KRAFTON HQ | D80: KRAFTON HQ | E80: Art Management Part | F80: OVERHEAD/OTHERS | G80: 배준석 | H80: 배준석 | I80: https://ask.krafton.com/browse/ASKIT-33845 | J80: v
A81: azure-ait-genai-api-project | B81: Azure | C81: KRAFTON HQ | D81: KRAFTON HQ | E81: AI Transformation Team | F81: OVERHEAD/OTHERS | G81: 이재준 | H81: 이재준 | I81: https://ask.krafton.com/browse/ASKIT-33055
A82: KraftonMontrealStudio | B82: Azure | C82: KRAFTON HQ | D82: KRAFTON Montreal | F82: OVERHEAD/OTHERS
A83: security_policy_prod | B83: Azure | C83: KRAFTON HQ | D83: KRAFTON HQ | E83: Security Policy Part | F83: OVERHEAD/OTHERS | G83: 조남원 | H83: 조남원 | I83: https://ask.krafton.com/browse/ASKIT-39295 | J83: v
A84: GP Project | B84: Azure | C84: KRAFTON HQ | D84: KRAFTON HQ | E84: IN Platform Business Dept. | F84: OVERHEAD/OTHERS | G84: 김형진 | H84: 김형진 | I84: https://ask.krafton.com/browse/ASKIT-38096
A85: MCA | B85: Azure | C85: KRAFTON HQ | D85: KRAFTON HQ | E85: IN Platform Business Dept._HQ | F85: OVERHEAD/OTHERS | G85: 이승우 | H85: 이승우 | I85: https://ask.krafton.com/browse/ASKIT-37675
A86: SRC-India-DEV | B86: Azure | C86: KRAFTON HQ | D86: KRAFTON HQ | E86: IN Platform Business Dept._HQ | F86: Cricket All Stars | G86: 김정언 | H86: 김정언
A87: Strategic Alignment Office | B87: Azure | C87: KRAFTON HQ | D87: KRAFTON HQ | E87: Strategic Alignment Office | F87: OVERHEAD/OTHERS | G87: 박승아 | H87: 박승아 | I87: https://ask.krafton.com/browse/ASKIT-39214
A88: Teams Room Pro | B88: Azure | C88: KRAFTON HQ | D88: KRAFTON HQ | E88: System Team | F88: OVERHEAD/OTHERS | G88: 정윤환 | H88: 정윤환
A89: Battlin Project | B89: Azure | C89: KRAFTON HQ | D89: KRAFTON HQ | E89: IN Platform Business Dept._HQ | F89: OVERHEAD/OTHERS | G89: 김형진 | H89: 김형진 | I89: https://ask.krafton.com/browse/ASKIT-38096
A90: SUNZO | B90: Azure | C90: KRAFTON HQ | D90: KRAFTON HQ | E90: IN Platform Business Dept._HQ | F90: OVERHEAD/OTHERS | G90: 이승우 | H90: 이승우 | I90: https://ask.krafton.com/browse/ASKIT-37675
A91: SUNZO_old | B91: Azure | C91: KRAFTON HQ | D91: KRAFTON HQ | E91: IN Platform Business Dept._HQ | F91: OVERHEAD/OTHERS | G91: 이승우 | H91: 이승우 | I91: https://ask.krafton.com/browse/ASKIT-37675
A92: Battlin Project_old | B92: Azure | C92: KRAFTON HQ | D92: KRAFTON HQ | E92: IN Platform Business Dept._HQ | F92: OVERHEAD/OTHERS | G92: 김형진 | H92: 김형진 | I92: https://ask.krafton.com/browse/ASKIT-38096
A93: MRSO_old | B93: Azure | C93: KRAFTON HQ | D93: KRAFTON HQ | E93: Milestone Review Support Office | F93: OVERHEAD/OTHERS | G93: 송진나 | H93: 송진나 | I93: https://ask.krafton.com/browse/ASKIT-37599
A94: azure-cas-prod | B94: Azure | C94: KRAFTON HQ | D94: KRAFTON HQ | E94: DevData Engineering Team | F94: Cricket All Stars | G94: 안연주 | H94: 안연주 | I94: https://ask.krafton.com/browse/ASKIT-45103
A95: azure-cas-qa | B95: Azure | C95: KRAFTON HQ | D95: KRAFTON HQ | E95: DevData Engineering Team | F95: Cricket All Stars | G95: 안연주 | H95: 안연주
A96: CorpDev_GameDataAnalysis | B96: Azure | C96: KRAFTON HQ | D96: KRAFTON HQ | E96: M&A Dept. | F96: OVERHEAD/OTHERS | G96: 이유림 | H96: 이유림 | I96: https://ask.krafton.com/browse/ASKIT-43948
A97: gp-playtest-tool | B97: Azure | C97: KRAFTON HQ | D97: KRAFTON HQ | E97: Publishing Portfolio Management Team | F97: OVERHEAD/OTHERS | G97: 백상훈 | H97: 백상훈 | I97: https://ask.krafton.com/browse/ASKIT-45551
A98: WoW | B98: Azure | C98: KRAFTON HQ | D98: KRAFTON HQ | E98: Culture Team | F98: OVERHEAD/OTHERS | G98: 이서진 | H98: 이서진 | I98: https://ask.krafton.com/browse/ASKIT-45770

Sheet Tencent
A1: Please don't change this sheet and data. If necessary, contact Chaewon Jung via Slack 1:1 DM.
A2: Account ID | B2: Provider | C2: Entity | D2: Studio | E2: Team | F2: Project | G2: Owner | H2: Cost verifier | I2: comment | J2: contact verifed?
A3: TC_PUBGM@krafton.com(100006855235) | B3: Tencent Cloud | C3: KRAFTON HQ | D3: KRAFTON HQ | E3: PUBGM Product Management Dept. | F3: BATTLEGROUNDS_MOBILE | G3: 김연 | H3: 최윤채 | I3: 8월부터는 김민우님 -> 최윤채님 | J3: v
A4: TC_PUBG@krafton.com(100013364605) | B4: Tencent Cloud | C4: KRAFTON HQ | D4: PUBG STUDIO | E4: PUBG PC&Console Dev Div. | F4: BATTLEGROUNDS_PC/CONSOLE | G4: 김정헌 | H4: 최준석 | I4: pubg-tcyun
A5: TC_XTRM_Voice(200018966832) | B5: Tencent Cloud | C5: KRAFTON HQ | D5: PUBG NewState | E5: New State Dev Div. | F5: PUBG:NEW STATE | G5: 김남윤 | H5: 김남윤 | I5: people
A6: TC_XTRM(200019689895) | B6: Tencent Cloud | C6: KRAFTON HQ | D6: PUBG NewState | E6: New State Dev Div. | F6: PUBG:NEW STATE | G6: 최진욱 | H6: Delete | I6: 삭제되었다고 하는데…..
A7: TC_XTRM-Staging(200022166247) | B7: Tencent Cloud | C7: KRAFTON HQ | D7: PUBG NewState | E7: New State Dev Div. | F7: PUBG:NEW STATE | G7: 천궁원 | H7: 천궁원 | I7: 삭제되었다고 하는데….. | J7: v
A8: TC_XTRM-Dev@pubg.com(200022166252) | B8: Tencent Cloud | C8: KRAFTON HQ | D8: PUBG NewState | E8: New State Dev Div. | F8: PUBG:NEW STATE | G8: 최진욱 | H8: Delete | I8: XTRM Dev & staging | J8: v
A9: TC_XTRM-Prod@pubg.com(200022166258) | B9: Tencent Cloud | C9: KRAFTON HQ | D9: KRAFTON HQ | E9: Service DevOps Team | F9: PUBG:NEW STATE | G9: 엄기성 | H9: 엄기성 | I9: Service Infra team QA 용도 | J9: v
A10: TC_RU-CDN@krafton.com(200022872415) | B10: Tencent Cloud | C10: KRAFTON HQ | D10: KRAFTON HQ | E10: Service DevOps Team | F10: BATTLEGROUNDS_PC/CONSOLE | G10: 신근우 | H10: 신근우 | J10: v
A11: TC_ServiceInfra-Test(200022975744) | B11: Tencent Cloud | C11: KRAFTON HQ | D11: KRAFTON HQ | E11: Service DevOps Team | F11: OVERHEAD/OTHERS | G11: 안연주 | H11: 안연주 | I11: Service Infra 테스트 계정 | J11: v
A12: TC_Overdare(200027738757) | B12: Tencent Cloud | C12: OVERDARE | D12: OVERDARE | E12: OVDR Platform Engineering Team | F12: OVERHEAD/OTHERS | G12: 이제우 | H12: 이제우 | J12: v
A13: TC_sbx-dev@krafton.com(200028932067) | B13: Tencent Cloud | C13: OVERDARE | D13: OVERDARE | E13: OVDR Platform Engineering Team | F13: OVERHEAD/OTHERS | G13: 이제우 | H13: 이제우 | I13: 사용량 없음
A14: tencent_systemT@krafton.com(200030930341) | B14: Tencent Cloud | C14: KRAFTON HQ | D14: KRAFTON HQ | E14: IT Dept. | F14: OVERHEAD/OTHERS | G14: 김재윤 | H14: 김재윤 | J14: v
A15: TC_PSPASTOOL(200032060947) | B15: Tencent Cloud | C15: KRAFTON HQ | D15: KRAFTON HQ | E15: Publishing Support Div. | F15: OVERHEAD/OTHERS | G15: 예홍옥 | H15: 예홍옥 | I15: CS 데이터에 대해 활용 및 관리
A16: TC_PAB(200032704449) | B16: Tencent Cloud | C16: BLUEHOLE | D16: BLUEHOLE | E16: B_production Div. | F16: Dark and Darker_Mobile | G16: 박소임 | H16: 박소임
A17: TC_TCP_Publishing(200034873049) | B17: Tencent Cloud | C17: KRAFTON HQ | D17: KRAFTON HQ | E17: Compatibility & Optimization QA Team | F17: OVERHEAD/OTHERS | G17: 전지훈 | H17: 전지훈 | I17: Wetest 서비스를 구매하기 위해 신청한 계정 | J17: v
A18: TC_PSPASTOOL@krafton.com(200032060947) | B18: Tencent Cloud | C18: KRAFTON HQ | D18: KRAFTON HQ | E18: Player Support Team | F18: BATTLEGROUNDS_PC/CONSOLE | G18: 예홍옥 | H18: 권명숙 | I18: CS 데이터에 대해 활용 및 관리
A19: TC_service_sh@krafton.com(200037618761) | B19: Tencent Cloud | C19: KRAFTON HQ | D19: KRAFTON CHINA | E19: CN Service Ops Team_HQ | F19: BATTLEGROUNDS_PC/CONSOLE | G19: Pei Jun Xue | H19: Yan Ru Xu | I19: CN Service Ops Team/ 1년에 1번
A20: TC_PERFDOG@krafton.com(100009236773) | B20: Tencent Cloud | C20: KRAFTON HQ | D20: KRAFTON HQ | E20: IT Dept. | F20: OVERHEAD/OTHERS | G20: 이윤슬 | H20: 이윤슬 | I20: Perfdog 구매 계정
A21: TC_xe@krafton.com(200041394676) | B21: Tencent Cloud | C21: KRAFTON HQ | D21: KRAFTON HQ | E21: Experience Engineering Dept. | F21: OVERHEAD/OTHERS | G21: 이준호 | H21: 이준호

Sheet Datadog
A1: Please don't change this sheet and data. If necessary, contact Chaewon Jung via Slack 1:1 DM.
A2: Account ID | B2: Provider | C2: Entity | D2: Studio | E2: Team | F2: Project | G2: Owner | H2: Cost verifier | I2: comment | J2: contact verifed?
A3: Beluga | B3: Datadog | C3: KRAFTON HQ | D3: KRAFTON HQ | E3: Project Beluga Dept. | F3: Project Beluga | G3: Deleted | H3: Deleted | J3: v
A4: BLUEHOLE-Harth | B4: Datadog | C4: BLUEHOLE | D4: BLUEHOLE | E4: ELYON Unit | F4: ELYON PC | G4: Delete(25.06) | H4: 엄기성 | I4: 엄기성님께서 삭제 티켓 작성함 | J4: v
A5: BLUEHOLE-TechSupport | B5: Datadog | C5: KRAFTON HQ | D5: KRAFTON HQ | E5: Service DevOps Team | F5: OVERHEAD/OTHERS | G5: 엄기성 | H5: 엄기성 | J5: v
A6: BLUEHOLE-TRCS | B6: Datadog | C6: BLUEHOLE | D6: BLUEHOLE | E6: T_Console Service Part | F6: TERA_Console | G6: 엄기성 | H6: 엄기성 | J6: v
A7: Dark&Darker Mobile | B7: Datadog | C7: KRAFTON HQ | D7: KRAFTON HQ | E7: Publishing Tech PM Part | F7: Dark and Darker_Mobile | G7: 김정언 | H7: 김정언
A8: datadog_RW_defensederby | B8: Datadog | C8: KRAFTON HQ | D8: KRAFTON HQ | E8: Publishing Tech PM Part | F8: DEFENSE DERBY | G8: 김정언 | H8: 이진호 | J8: v
A9: Unknown Worlds | B9: Datadog | C9: Unknownworlds | D9: Unknownworlds | E9: Unknownworlds | F9: SUBNAUTICA 2 | G9: Jack Smith | H9: Jack Smith | I9: SUBNAUTICA 2 -> Unknown Worlds로 변경 24.08/ Mike Verrette이 7/19 담당자 jack으로 변경요청
A10: Datadog_UW_BM_Prod | B10: Datadog | C10: KRAFTON HQ | D10: KRAFTON HQ | E10: Service DevOps Team | F10: UW-MOONBREAKER | G10: Delete(25.06) | H10: 엄기성 | I10: 엄기성님께서 삭제 티켓 작성함 | J10: v
A11: KRAFTON - SDS DevOps | B11: Datadog | C11: KRAFTON HQ | D11: SDS | E11: Striking Distance Studios | F11: The Callisto Protocol | G11: Jordan Yerkes | H11: Jordan Yerkes | J11: v
A12: KRAFTON - SDS ITSEC | B12: Datadog | C12: KRAFTON HQ | D12: SDS | E12: Striking Distance Studios | F12: The Callisto Protocol | G12: Jordan Yerkes | H12: Jordan Yerkes | J12: v
A13: KRAFTON_DE | B13: Datadog | C13: KRAFTON HQ | D13: KRAFTON HQ | E13: Data Engineering Dept. | F13: OVERHEAD/OTHERS | G13: 연화음 | H13: 김시훈 | J13: v
A14: KRAFTON-KOS | B14: Datadog | C14: KRAFTON HQ | D14: KRAFTON HQ | E14: KOS Engineering Dept. | F14: GPP | G14: 신근우 | H14: 신근우 | J14: v
A15: Krafton-infra-platform | B15: Datadog | C15: KRAFTON HQ | D15: KRAFTON HQ | E15: IT Dept. | F15: OVERHEAD/OTHERS | G15: 홍성철 | H15: 홍성철 | J15: v
A16: krafton-system | B16: Datadog | C16: KRAFTON HQ | D16: KRAFTON HQ | E16: IT Dept. | F16: OVERHEAD/OTHERS | G16: 백용원 | H16: 백용원 | J16: v
A17: Krafton-TRCS-AP | B17: Datadog | C17: BLUEHOLE | D17: BLUEHOLE | E17: T_Console Service Part | F17: TERA_Console | G17: 엄기성 | H17: 엄기성 | J17: v
A18: Krafton-TRPC | B18: Datadog | C18: BLUEHOLE | D18: BLUEHOLE | E18: TERA | F18: TERA_PC | G18: Delete(25.06) | H18: 엄기성 | I18: 엄기성님께서 삭제 티켓 작성함 | J18: v
A19: Krafton-WebService | B19: Datadog | C19: KRAFTON HQ | D19: KRAFTON HQ | E19: Experience Engineering Dept. | F19: OVERHEAD/OTHERS | G19: 이준호 | H19: 이준호 | I19: 비용권한이 없습니다. / New State 뿐만 아니라 저희 팀에서 진행하는 모든 프로젝트에서 사용 중입니다. | J19: v
A20: PUBG eSports | B20: Datadog | C20: KRAFTON HQ | D20: KRAFTON HQ | E20: Publishing Tech PM Part | F20: OVERHEAD/OTHERS | G20: 김정언 | H20: 김정언
A21: Migaloo | B21: Datadog | C21: OVERDARE | D21: OVERDARE | E21: OVDR Web 3.0 Product Team | F21: OVERHEAD/OTHERS | G21: 이상헌 | H21: 이상헌 | I21: 이제 사용 안함 계정만 살려둔 상태 | J21: v
A22: PUBG Black Budget | B22: Datadog | C22: KRAFTON HQ | D22: KRAFTON HQ | E22: PUBG PC&Console Dev Div. | F22: BLACK BUDGET | G22: 김정헌 | H22: 최준석 | J22: v
A23: PUBG DevOps | B23: Datadog | C23: KRAFTON HQ | D23: KRAFTON HQ | E23: PUBG PC&Console Dev Div. | F23: BATTLEGROUNDS_PC/CONSOLE | G23: 김정헌 | H23: 최준석
A24: KRAFTON PUBG eSports | B24: Datadog | C24: KRAFTON HQ | D24: KRAFTON HQ | E24: Publishing Tech PM Part | F24: OVERHEAD/OTHERS | G24: 김정언 | H24: 김정언
A25: PUBG Corporation | B25: Datadog | C25: KRAFTON HQ | D25: PUBG STUDIO | E25: PUBG PC&Console Dev Div. | F25: BATTLEGROUNDS_PC/CONSOLE | G25: 김정헌 | H25: 최준석 | J25: v
A26: PUBG Intelligent Services | B26: Datadog | C26: KRAFTON HQ | D26: PUBG STUDIO | E26: PUBG PC&Console Dev Div. | F26: BATTLEGROUNDS_PC/CONSOLE | G26: 김정헌 | H26: 최준석 | J26: v
A27: PUBG_TTO | B27: Datadog | C27: KRAFTON HQ | D27: PUBG STUDIO | E27: Service Infra Team | F27: PROJECT TT | G27: Deleted(25.5) | H27: 박형준 | I27: 삭제 진행 요청 함 | J27: v
A28: PUBGNS_DE | B28: Datadog | C28: KRAFTON HQ | D28: PUBG NewState | E28: Data Engineering Dept. | F28: PUBG:NEW STATE | G28: 염화음 | H28: 김시훈 | J28: v
A29: Inzoi | B29: Datadog | C29: KRAFTON HQ | D29: KRAFTON HQ | E29: Service Infra Team | F29: project blue | G29: Deleted(25.4) | H29: 양장수 | I29: 24' 사용량 없음
A30: KRAFTON-cookierun-india | B30: Datadog | C30: KRAFTON HQ | D30: KRAFTON HQ | E30: Publishing Tech PM Part | F30: Cookie Run India | G30: 김정언 | H30: 김정언 | I30: 24' 12/11 그랜드런칭 OVERHEAD/OTHERS 맞습니다
A31: KRAFTON-KCN | B31: Datadog | C31: KRAFTON HQ | D31: KRAFTON HQ | E31: KOS Engineering Dept. | F31: GPP | G31: 신근우 | H31: 신근우 | I31: Publishing Platform Div. 에서 신규 개발하는 KCN 의 모니터링 | J31: v
A32: KTAFTON_bgmi_event | B32: Datadog | C32: KRAFTON HQ | D32: KRAFTON HQ | E32: Experience Engineering Dept. | F32: (2022)BATTLEGROUNDS_MOBILE_IN | G32: 이준호 | H32: 이준호 | I32: BGMI 이벤트 전용 모니터링 | J32: v
A33: MadGlory_Valor | B33: Datadog | C33: KRAFTON HQ | D33: Mad Glory | E33: Valor Core Tech Team | F33: Valor_Console | G33: 송영재 | H33: 송영재 | I33: Project Valor 개발 모니터링 | J33: v
A34: datadog-website | B34: Datadog | C34: KRAFTON HQ | D34: KRAFTON HQ | E34: System Team | F34: OVERHEAD/OTHERS | G34: 김재윤 | H34: 김재윤
A35: Krafton_AISD | B35: Datadog | C35: KRAFTON HQ | D35: KRAFTON HQ | E35: [N/A]AI Service Engineering Team | F35: OVERHEAD/OTHERS | G35: 임지영 | H35: 임지영
A36: datadog_cricket-all-start | B36: Datadog | C36: KRAFTON HQ | D36: KRAFTON HQ | E36: Service DevOps Team | F36: Cricket All Stars | G36: 장은진 | H36: 장은진
A37: datadog_axt | B37: Datadog | C37: KRAFTON HQ | D37: KRAFTON HQ | E37: AI Transformation Dept. | F37: OVERHEAD/OTHERS | G37: 이정우 | H37: 이정우

Sheet GWS
A1: Please don't change this sheet and data. If necessary, contact Chaewon Jung via Slack 1:1 DM.
A2: Account ID | B2: Provider | C2: Entity | D2: Studio | E2: Team | F2: Project | G2: Owner | H2: Cost verifier | I2: comment | J2: contact verifed?
A3: GWS | B3: GWS | C3: KRAFTON HQ | D3: KRAFTON HQ | E3: IT Dept. | F3: OVERHEAD/OTHERS | G3: 이윤슬 | H3: 이윤슬 | J3: v
A4: Gemini | B4: GWS | C4: KRAFTON HQ | D4: KRAFTON HQ | E4: AI Transformation Team | F4: OVERHEAD/OTHERS | G4: 김도균 | H4: 김도균

Sheet Yandex
A1: Please don't change this sheet and data. If necessary, contact Chaewon Jung via Slack 1:1 DM.
A2: Account ID | B2: Provider | C2: Entity | D2: Studio | E2: Team | F2: Project | G2: Owner | H2: Cost verifier | I2: comment | J2: contact verifed?
A3: cloud-pubgdevops | B3: Yandex Cloud | C3: KRAFTON HQ | D3: PUBG STUDIO | E3: PUBG PC&Console Dev Div. | F3: BATTLEGROUNDS_PC/CONSOLE | G3: 김정헌 | H3: 최준석 | J3: v

Sheet GCP
A1: Please don't change this sheet and data. If necessary, contact Chaewon Jung via Slack 1:1 DM.
A2: Account ID | B2: Provider | C2: Entity | D2: Studio | E2: Team | F2: Project | G2: Owner | H2: Cost verifier | I2: comment | J2: contact verifed? | K2: 세로 막대형1
A3: Armor | B3: GCP | C3: KRAFTON HQ | D3: KRAFTON HQ | E3: Service DevOps Team | F3: OVERHEAD/OTHERS | G3: 엄기성 | H3: 엄기성 | I3: 왜 Wiki에 없지? | J3: v
A4: dataplatform-api | B4: GCP | C4: KRAFTON HQ | D4: KRAFTON HQ | E4: IT Dept. | F4: OVERHEAD/OTHERS | G4: 백용원 | H4: 백용원
A5: diet-357705 | B5: GCP | C5: KRAFTON HQ | D5: KRAFTON HQ | E5: DevData Engineering Team | F5: OVERHEAD/OTHERS | G5: 이동준 | H5: 이동준 | I5: DB R&D 용도 (팀 내부 사용) | J5: v
A6: dm-rtv-empires | B6: GCP | C6: KRAFTON HQ | D6: KRAFTON HQ | E6: India Publishing Dept._HQ | F6: OVERHEAD/OTHERS | G6: 신지호 | H6: 신지호
A7: GCP Support Fee | B7: GCP | C7: KRAFTON HQ | D7: KRAFTON HQ | E7: IT Dept. | F7: OVERHEAD/OTHERS | G7: 백용원 | H7: Deleted | I7: GCP Support fee 정책 변경에 따른 비용을 위한 임시(24.11) | J7: v
A8: api-6414577526685413251-707161 | B8: GCP | C8: KRAFTON HQ | D8: PUBG STUDIO | E8: Platform Management Team | F8: OVERHEAD/OTHERS | G8: 신지호 | H8: 신지호 | I8: 서강석:Google Play 계정은 현재 Publishing Support Div.>Publishing QA Dept.>Platform Management Team 신지호님이 관리하고 계십니다. | J8: v
A9: krafton-l10n | B9: GCP | C9: KRAFTON HQ | D9: KRAFTON HQ | E9: L10N Team | F9: OVERHEAD/OTHERS | G9: 김재헌 | H9: 전평준 | J9: v
A10: krafton-chatbot | B10: GCP | C10: KRAFTON HQ | D10: KRAFTON HQ | E10: AI research center | F10: DEEP LEARNING | G10: 이기쁨 | H10: Deleted(24.06) | I10: https://ask.krafton.com/browse/ASKIT-27850
A11: kraftonjungle | B11: GCP | C11: KRAFTON HQ | D11: KRAFTON HQ | E11: Jungle Coaching Dept. | F11: PROJECT JUNGLE | G11: 김현수 | H11: 김현수 | I11: cost verifier를 백승현 -> 김현수 로 변경
A12: serviceinfratest | B12: GCP | C12: KRAFTON HQ | D12: KRAFTON HQ | E12: Service DevOps Team | F12: OVERHEAD/OTHERS | G12: 엄기성 | H12: 엄기성 | J12: v
A13: sfreer | B13: GCP | C13: KRAFTON HQ | D13: KRAFTON HQ | E13: O2 Team | F13: OVERHEAD/OTHERS | G13: Deleted | H13: Deleted | J13: v
A14: uw-mb-prod | B14: GCP | C14: KRAFTON HQ | D14: KRAFTON America | E14: Service DevOps Team | F14: UW-MOONBREAKER | G14: 엄기성 | H14: 엄기성 | J14: v
A15: vn-holmlands-dev | B15: GCP | C15: KRAFTON HQ | D15: Vector North | E15: Vector North Unit | F15: OVERHEAD/OTHERS | G15: Petr Matoušek | H15: Petr Matoušek | J15: v
A16: PUBG DevOps US Central Test | B16: GCP | C16: KRAFTON HQ | D16: PUBG STUDIO | E16: PUBG PC&Console Dev Div. | F16: BATTLEGROUNDS_PC/CONSOLE | G16: 김정헌 | H16: 김정헌 | I16: 23,000원 꾸준히 발생, 계정 삭제 | J16: v
A17: vital-axiom-238107 | B17: GCP | C17: KRAFTON HQ | D17: PUBG STUDIO | E17: Infra Div. | F17: OVERHEAD/OTHERS | G17: 심재한 | H17: 심재한 | I17: 심재한:Research용이고 google play log수집 하고 있습니다
A18: migaloo-web3 | B18: GCP | C18: KRAFTON HQ | D18: OVERDARE | E18: OVDR Web 3.0 Product Team | F18: OVERHEAD/OTHERS | G18: 당정현 | H18: 당정현 | I18: 사용량 없음/ASKIT-26336 변경요청 | J18: v
A19: ReLU Games | B19: GCP | C19: ReLu Games | D19: ReLu Games | E19: ReLU Dev Dept. | F19: OVERHEAD/OTHERS | G19: 오준석 | H19: 오준석
A20: garuda-saga-india | B20: GCP | C20: KRAFTON HQ | D20: KRAFTON HQ | E20: India Publishing Dept._HQ | F20: OVERHEAD/OTHERS | G20: 신지호 | H20: 신지호
A21: moonbreaker-production | B21: GCP | C21: Unknownworlds | D21: Unknownworlds | E21: Unknownworlds | F21: UW-MOONBREAKER | G21: Jack Smith | H21: Jack Smith
A22: warpaint-backend | B22: GCP | C22: Unknownworlds | D22: Unknownworlds | E22: Unknownworlds | F22: OVERHEAD/OTHERS | G22: Jack Smith | H22: Jack Smith
A23: warpaint-developer-280614 | B23: GCP | C23: Unknownworlds | D23: Unknownworlds | E23: Unknownworlds | F23: OVERHEAD/OTHERS | G23: Jack Smith | H23: Jack Smith
A24: krafton-nlp-eng | B24: GCP | C24: KRAFTON HQ | D24: KRAFTON HQ | E24: AI Research Design Team | F24: OVERHEAD/OTHERS | G24: 이에나 | H24: 이에나 | I24: Deleted(25.06)
A25: archeryking | B25: GCP | C25: KRAFTON HQ | D25: KRAFTON HQ | E25: India Publishing Dept._HQ | F25: OVERHEAD/OTHERS | G25: 신지호 | H25: 신지호
A26: krafton-hermione | B26: GCP | C26: KRAFTON HQ | D26: KRAFTON HQ | E26: ML Infra Team | F26: OVERHEAD/OTHERS | G26: 유상규 | H26: 유상규 | I26: delete
A27: pc-api-7226728469668669189-510 | B27: GCP | C27: KRAFTON HQ | D27: OVERDARE | E27: OVDR Platform Engineering Dept. | F27: OVERHEAD/OTHERS | G27: 나윤호 | H27: 이제우
A28: krafton-dld-ai | B28: GCP | C28: KRAFTON HQ | D28: KRAFTON HQ | E28: AI Product Dev Chapter Dept. | F28: DEEP LEARNING | G28: 이에나 | H28: 이에나 | J28: v | K28: v
A29: GitLab | B29: GCP | C29: KRAFTON HQ | D29: KRAFTON HQ | E29: KRAFTON HQ | F29: OVERHEAD/OTHERS | G29: 정채원 | H29: 사용완료
A30: Looker | B30: GCP | C30: KRAFTON HQ | D30: KRAFTON HQ | E30: Data Engineering Dept. | F30: OVERHEAD/OTHERS | G30: 송은석 | H30: 사용완료
A31: oge-scraper | B31: GCP | C31: KRAFTON HQ | D31: KRAFTON HQ | E31: Data Engineering Dept. | F31: OVERHEAD/OTHERS | G31: 염화음 | H31: 신수연 | I31: Oge 붙어 있거나 data voyager 로 되어있으면 ded 조직 프로젝트는 Data Infra Team
A32: dl-service-dev | B32: GCP | C32: KRAFTON HQ | D32: KRAFTON HQ | E32: AI Agent Research Team | F32: OVERHEAD/OTHERS | G32: 정기영 | H32: 정기영
A33: krafton-ded-ai | B33: GCP | C33: KRAFTON HQ | D33: KRAFTON HQ | E33: Data Engineering Dept. | F33: OVERHEAD/OTHERS | G33: 염화음 | H33: 문중현 | I33: https://jira.krafton.com/browse/ASKIT-24251
A34: Kissflow | B34: GCP | C34: KRAFTON HQ | D34: KRAFTON HQ | E34: KRAFTON HQ | F34: OVERHEAD/OTHERS | G34: 송은석 | H34: 사용완료
A35: pubg-mobile-fit-29242572 | B35: GCP | C35: KRAFTON HQ | D35: KRAFTON HQ | E35: Platform Management Team | F35: (2022)BATTLEGROUNDS_MOBILE_IN | G35: 신지호 | H35: 신지호
A36: krafton-ded-infra | B36: GCP | C36: KRAFTON HQ | D36: KRAFTON HQ | E36: Data Engineering Dept. | F36: OVERHEAD/OTHERS | G36: 염화음 | H36: 김시훈
A37: logdescriptor | B37: GCP | C37: KRAFTON HQ | D37: KRAFTON HQ | E37: Data Analytics Dept. | F37: (2022)BATTLEGROUNDS_MOBILE_IN | G37: 김준형 | H37: 김준형 | J37: v
A38: project-ddm-405802 | B38: GCP | C38: KRAFTON HQ | D38: KRAFTON HQ | E38: Platform Management Team | F38: Dark and Darker_Mobile | G38: 신지호 | H38: 신지호 | I38: https://ask.krafton.com/browse/ASKIT-26386
A39: gamebench-456108 | B39: GCP | C39: KRAFTON HQ | D39: KRAFTON HQ | E39: AI Model Research Dept. | F39: OVERHEAD/OTHERS | G39: 박동민 | H39: 박동민 | I39: https://ask.krafton.com/browse/ASKIT-26729 | J39: v
A40: krafton-creator-network | B40: GCP | C40: KRAFTON HQ | D40: KRAFTON HQ | E40: KOS Engineering Dept. | F40: OVERHEAD/OTHERS | G40: 이동호 | H40: 이동호 | I40: https://ask.krafton.com/browse/ASKIT-24653
A41: gamingslm | B41: GCP | C41: KRAFTON HQ | D41: KRAFTON HQ | E41: DL Research Dept. | F41: OVERHEAD/OTHERS | G41: 안재우 | H41: Deleted(25.06) | I41: 동민님 계정통합/Gemini API Key for gamingslm (ORAK)/ https://ask.krafton.com/browse/ASKIT-27697
A42: gamingslm1 | B42: GCP | C42: KRAFTON HQ | D42: KRAFTON HQ | E42: DL Research Dept. | F42: OVERHEAD/OTHERS | G42: 박인규 | H42: Deleted(25.06) | I42: 동민님 계정통합/ https://ask.krafton.com/browse/ASKIT-27729
A43: orak-459308 | B43: GCP | C43: KRAFTON HQ | D43: KRAFTON HQ | E43: DL Research Dept. | F43: OVERHEAD/OTHERS | G43: 김민규 | H43: Deleted(25.06) | I43: 동민님 계정통합// https://ask.krafton.com/browse/ASKIT-27724
A44: orakgamingslm | B44: GCP | C44: KRAFTON HQ | D44: KRAFTON HQ | E44: DL Research Dept. | F44: OVERHEAD/OTHERS | G44: 이종현 | H44: Deleted(25.06) | I44: 동민님 계정통합// Gemini 2.5 Pro API/ k.krafton.com/browse/ASKIT-27692
A45: orak-junhyuck | B45: GCP | C45: KRAFTON HQ | D45: KRAFTON HQ | E45: DL Research Dept. | F45: OVERHEAD/OTHERS | G45: 김준혁 | H45: Deleted(25.06) | I45: https://ask.krafton.com/browse/ASKIT-27727
A46: pubg-ally | B46: GCP | C46: KRAFTON HQ | D46: KRAFTON HQ | E46: PUBG Ally DL TF Team | F46: OVERHEAD/OTHERS | G46: 임효정 | H46: 임효정 | I46: Video Understanding 을 통한 PUBG Play Video Evaluation/ https://ask.krafton.com/browse/ASKIT-27870/김현승 -> 임효정 | J46: v
A47: agds-462601 | B47: GCP | C47: KRAFTON HQ | D47: PUBG STUDIO | E47: PBB_S Platform Team | F47: BLACK BUDGET | G47: 조원빈 | H47: 조원빈 | I47: https://ask.krafton.com/browse/ASKIT-28514
A48: pubg-new-state-beta-59019398 | B48: GCP | C48: KRAFTON HQ | D48: KRAFTON HQ | E48: PUBG Business Planning Team | F48: PUBG:NEW STATE | G48: 김남윤 | H48: 김남윤
A49: pubg-platform-ai | B49: GCP | C49: KRAFTON HQ | D49: PUBG STUDIO | E49: PUBG PC&Console Dev Div. | F49: BATTLEGROUNDS_PC/CONSOLE | G49: 김정헌 | H49: 최준석 | I49: https://ask.krafton.com/browse/ASKIT-28425/GCP Kubernetes 클러스터 테스트 및 Vertex / Google AI Studio 등 AI 솔루션 활용
A50: pubg-primer | B50: GCP | C50: KRAFTON HQ | D50: KRAFTON HQ | E50: KRAFTON HQ | F50: OVERHEAD/OTHERS
A51: dld-tpu-llm-training | B51: GCP | C51: KRAFTON HQ | D51: KRAFTON HQ | E51: ML Sys & Ops Team | F51: OVERHEAD/OTHERS | G51: 김동원 | H51: 김동원 | I51: https://ask.krafton.com/browse/ASKIT-28420/LG CNS 하부 계정으로 PoC진행 중, Max 49K까지 Credit 소진시까지 당분간 비용 발생하지 않음
A52: ga-youtube-linking | B52: GCP | C52: KRAFTON HQ | D52: KRAFTON HQ
A53: inzoi-dev-rnd | B53: GCP | C53: KRAFTON HQ | D53: INZOI Studio | E53: inZOI Dev R&D Team | F53: INZOI | G53: 이상문 | H53: 이상문 | I53: https://ask.krafton.com/browse/ASKIT-25110 | J53: v | K53: v
A54: palworld-m | B54: GCP | C54: KRAFTON HQ | D54: KRAFTON HQ | E54: PalM Unit | F54: PalM | G54: 양병성 | H54: 양병성 | I54: https://ask.krafton.com/browse/ASKIT-24217
A55: veo3-461205 | B55: GCP | C55: KRAFTON HQ | D55: KRAFTON HQ | E55: AI Applied Research Dept. | F55: OVERHEAD/OTHERS | G55: 선주형 | H55: 선주형 | J55: v
A56: relugames | B56: GCP | C56: KRAFTON HQ | D56: ReLu Games | F56: OVERHEAD/OTHERS | G56: 오준석 | H56: 오준석 | I56: https://cloud.jira.krafton.com/browse/ASKIT-17127
A57: migaloo-web3-369008 | B57: GCP | C57: KRAFTON HQ | D57: OVERDARE | F57: OVERHEAD/OTHERS | G57: 당정현 | H57: 당정현 | I57: https://ask.krafton.com/browse/ASKIT-26336
A58: backpackarena | B58: GCP | C58: KRAFTON HQ | D58: 5minLab | F58: OVERHEAD/OTHERS
A59: smash-dungeon | B59: GCP | C59: KRAFTON HQ | D59: 5minLab | F59: OVERHEAD/OTHERS
A60: ai-workflow-automation-project | B60: GCP | C60: KRAFTON HQ | D60: KRAFTON HQ | E60: CEO's Office | F60: OVERHEAD/OTHERS | G60: 양윤상 | H60: 양윤상 | I60: https://ask.krafton.com/browse/ASKIT-32261
A61: atoz-dev-470901 | B61: GCP | C61: KRAFTON HQ | D61: KRAFTON HQ | E61: AI Applied Research Dept. | F61: DEEP LEARNING | G61: 김재욱 | H61: 김재욱
A62: dld-anticheat | B62: GCP | C62: KRAFTON HQ | D62: KRAFTON HQ | E62: AI Applied Research Dept. | F62: DEEP LEARNING | G62: 이혁 | H62: 이혁 | I62: https://ask.krafton.com/browse/ASKIT-30437
A63: krafton-online-services | B63: GCP | C63: KRAFTON HQ | D63: KRAFTON HQ | E63: KOS Engineering Dept. | F63: GPP | G63: 조국환 | H63: 조국환 | I63: https://ask.krafton.com/browse/ASKIT-33205
A64: loon-camp | B64: GCP | C64: KRAFTON HQ | D64: KRAFTON HQ | E64: Camp Dept. | F64: OVERHEAD/OTHERS | G64: 이태형 | H64: 이태형 | I64: https://ask.krafton.com/browse/ASKIT-32260
A65: lootbox-item-ad-post-oversight | B65: GCP | C65: KRAFTON HQ | D65: KRAFTON HQ | E65: Service Policy Team | F65: OVERHEAD/OTHERS | G65: 구민찬 | H65: 황민지 | I65: https://ask.krafton.com/browse/ASKIT-30923
A66: tableau-tf | B66: GCP | C66: KRAFTON HQ | D66: KRAFTON HQ | E66: Data Analytics Dept. | F66: OVERHEAD/OTHERS | G66: 김태혁 | H66: 김태혁 | I66: https://ask.krafton.com/projects/ASKIT/queues/issue/ASKIT-31858
A67: workautomation-472302 | B67: GCP | C67: KRAFTON HQ | D67: KRAFTON HQ | E67: S2 Team | F67: OVERHEAD/OTHERS | G67: 조승석 | H67: 조승석 | I67: https://ask.krafton.com/browse/ASKIT-32553
A68: xe-dept | B68: GCP | C68: KRAFTON HQ | D68: KRAFTON HQ | E68: Experience Engineering Dept. | F68: GPP | G68: 이준호 | H68: 이준호 | I68: https://ask.krafton.com/browse/ASKIT-32782
A69: gcp-msu-devops | B69: GCP | C69: KRAFTON HQ | D69: PUBG STUDIO | E69: MS DevOps Team | F69: OVERHEAD/OTHERS | G69: 천궁원 | H69: 배시은 | I69: https://ask.krafton.com/browse/ASKIT-31967
A70: ai-transformation-467006 | B70: GCP | C70: KRAFTON HQ | D70: KRAFTON HQ | E70: AI Transformation Team | F70: OVERHEAD/OTHERS | G70: 김도균 | H70: 김도균 | I70: https://ask.krafton.com/browse/ASKIT-30204
A71: dinkum-automation | B71: GCP | C71: KRAFTON HQ | D71: KRAFTON HQ | E71: Publishing Launchpad Team | F71: Dinkum | G71: 라샛별 | H71: 라샛별 | I71: https://ask.krafton.com/browse/ASKIT-35276
